Workbook

Sheet Tabla dinámica 1

Sheet DASHBOARD
B2: SISTEMA INTELIGENTE JIT - CONTROL DE INVENTARIO Y ABASTECIMIENTO
B3: Gestion de Flota 260 Buses | Principios Logisticos Ballou | Repotenciado 2100 Refs
B4: Las formulas se alimentan de la hoja DATA (base de datos diaria) y DATA PENDIENTES (OC abiertas)
B6: NAVEGACION RAPIDA
B9: INDICADORES CLAVE DE RENDIMIENTO - KPI
B10: =COUNTA(DATA!B4:B2103) -> 1828 | E10: ='Tabla dinámica 1'!B10 -> 2067844421 | G10: 636 | I10: 1192 | K10: =COUNTA('DATA PENDIENTES'!B4:B2103) -> 264
B11: Total Referencias | E11: Valor Total Inventario ($) | G11: Productos Stock CERO | I11: Productos con Stock | K11: Ordenes Pendientes
B13: 1144 | E13: 335 | G13: 349 | I13: =IFERROR(AVERAGE(DATA!E4:E2103),0) -> 323.32652 | K13: =COUNTA('DATA PENDIENTES'!B4:B2103) -> 264
B14: Clase A (Alto Valor) | E14: Clase B (Medio) | G14: Clase C (Normal) | I14: Stock Promedio/Ref | K14: Items Pendientes Detalle
B16: SEMAFORO DE ALERTAS - SISTEMA JIT (Punto de Reorden Dinamico - Ballou Cap. 9)
B17: ='Tabla dinámica 1'!B2 -> 21471177 | E17: ='Tabla dinámica 1'!B3 -> 2.3342555e+08 | F17: ='Tabla dinámica 1'!B4 -> 50045141 | G17: ='Tabla dinámica 1'!B5 -> 153762018 | H17: ='Tabla dinámica 1'!B6 -> 1.4287297e+08 | I17: ='Tabla dinámica 1'!B7 -> 4.7733398e+08 | J17: ='Tabla dinámica 1'!B8 -> 1.6376702e+08 | L17: ='Tabla dinámica 1'!B9 -> 8.2516657e+08 | N17: =SUM(B17:M17) -> 2067844421
B18: CAJA | E18: CARROCERIA | F18: COMBUSTIBLE | G18: COMUNICACIONES | H18: ELECTRICIDAD | I18: LLANTAS | J18: LUBRICANTES | L18: PLATAFORMA | N18: TOTAL
B19: =COUNTIF('CONTROL INVENTARIO'!$Q$4:$Q$2103,"CRITICO") -> 632 | F19: =COUNTIF('CONTROL INVENTARIO'!$Q$4:$Q$2103,"REORDEN INMEDIATO") -> 303 | I19: =COUNTIF('CONTROL INVENTARIO'!$Q$4:$Q$2103,"PRECAUCION") -> 165 | L19: =COUNTIF('CONTROL INVENTARIO'!$Q$4:$Q$2103,"OPTIMO")+COUNTIF('CONTROL INVENTARIO'!$Q$4:$Q$2103,"EXCESO") -> 728
B20: CRITICO - STOCK CERO RIESGO PARADA DE FLOTA | F20: REORDEN INMEDIATO Stock <= Punto Reorden | I20: PROXIMO A MINIMO Revisar en 48 horas | L20: STOCK SEGURO Nivel Optimo JIT
B22: TOP 20 PRODUCTOS DE MAYOR VALOR EN INVENTARIO | K22: PRODUCTOS CRITICOS - STOCK CERO (RIESGO PARADA)
B23: # | C23: OC | D23: REFERENCIA | E23: DESCRIPCION | F23: PROVEEDOR | G23: STOCK | H23: COSTO UNIT. | I23: VALOR TOTAL | J23: ABC | K23: REFERENCIA | L23: DESCRIPCION | M23: PROVEEDOR | N23: CONSUMO | O23: CONS. DIARIO
B24: 1 | C24: =IFERROR('TOP 20 VALOR'!C4,"") | D24: =IFERROR('TOP 20 VALOR'!D4,"") -> 77101000 | E24: =IFERROR('TOP 20 VALOR'!E4,"") -> RIN RUEDA DE DISCO 8.25X22.5 CON AVELLAN | F24: =IFERROR('TOP 20 VALOR'!F4,"") -> LLANTAS REPUESTOS Y SERVICIO SAS | G24: =IFERROR('TOP 20 VALOR'!G4,"") -> 202 | H24: =IFERROR('TOP 20 VALOR'!H4,"") -> 1750000 | I24: =IFERROR('TOP 20 VALOR'!I4,"") -> 353500000 | J24: =IFERROR('TOP 20 VALOR'!J4,"") -> A | K24: =IFERROR('TOP 20 CERO'!C4,"") -> 2210101 | L24: =IFERROR('TOP 20 CERO'!D4,"") -> GRASA SHEEL GADUS S3 V220C | M24: =IFERROR('TOP 20 CERO'!E4,"") -> 800186960 | N24: =IFERROR('TOP 20 CERO'!F4,"") -> 213338.7 | O24: =IFERROR('TOP 20 CERO'!G4,"") -> 584.48959
B25: 2 | C25: =IFERROR('TOP 20 VALOR'!C5,"") -> SU114003 | D25: =IFERROR('TOP 20 VALOR'!D5,"") -> 7730306 | E25: =IFERROR('TOP 20 VALOR'!E5,"") -> RODAMIENTO CUBO RUEDA DE REMOLQUE | F25: =IFERROR('TOP 20 VALOR'!F5,"") -> VOLVO GROUP COLOMBIA S A S | G25: =IFERROR('TOP 20 VALOR'!G5,"") -> 60 | H25: =IFERROR('TOP 20 VALOR'!H5,"") -> 1849900 | I25: =IFERROR('TOP 20 VALOR'!I5,"") -> 110994000 | J25: =IFERROR('TOP 20 VALOR'!J5,"") -> A | K25: =IFERROR('TOP 20 CERO'!C5,"") -> 801702021 | L25: =IFERROR('TOP 20 CERO'!D5,"") -> AGAMIX | M25: =IFERROR('TOP 20 CERO'!E5,"") -> 901319175 | N25: =IFERROR('TOP 20 CERO'!F5,"") -> 87200 | O25: =IFERROR('TOP 20 CERO'!G5,"") -> 238.90411
B26: 3 | C26: =IFERROR('TOP 20 VALOR'!C6,"") -> SU115530 | D26: =IFERROR('TOP 20 VALOR'!D6,"") -> 77101008 | E26: =IFERROR('TOP 20 VALOR'!E6,"") -> LLANTA NUEVA RADIAL 295/80-R22.5 | F26: =IFERROR('TOP 20 VALOR'!F6,"") -> LLANTAS REPUESTOS Y SERVICIO SAS | G26: =IFERROR('TOP 20 VALOR'!G6,"") -> 46 | H26: =IFERROR('TOP 20 VALOR'!H6,"") -> 2354430 | I26: =IFERROR('TOP 20 VALOR'!I6,"") -> 108303780 | J26: =IFERROR('TOP 20 VALOR'!J6,"") -> A | K26: =IFERROR('TOP 20 CERO'!C6,"") -> 801702028 | L26: =IFERROR('TOP 20 CERO'!D6,"") -> OXIGENO | M26: =IFERROR('TOP 20 CERO'!E6,"") -> 901319175 | N26: =IFERROR('TOP 20 CERO'!F6,"") -> 31800 | O26: =IFERROR('TOP 20 CERO'!G6,"") -> 87.123288
B27: 4 | C27: =IFERROR('TOP 20 VALOR'!C7,"") -> SU114827 | D27: =IFERROR('TOP 20 VALOR'!D7,"") -> 13210008 | E27: =IFERROR('TOP 20 VALOR'!E7,"") -> ALTERNADOR | F27: =IFERROR('TOP 20 VALOR'!F7,"") -> INNOVATEQ S.A.S | G27: =IFERROR('TOP 20 VALOR'!G7,"") -> 51 | H27: =IFERROR('TOP 20 VALOR'!H7,"") -> 1487533 | I27: =IFERROR('TOP 20 VALOR'!I7,"") -> 75864183 | J27: =IFERROR('TOP 20 VALOR'!J7,"") -> A | K27: =IFERROR('TOP 20 CERO'!C7,"") -> 21100002 | L27: =IFERROR('TOP 20 CERO'!D7,"") -> CASQUILLO DE TAPA VALVULAS | M27: =IFERROR('TOP 20 CERO'!E7,"") -> 900315569 | N27: =IFERROR('TOP 20 CERO'!F7,"") -> 23653 | O27: =IFERROR('TOP 20 CERO'!G7,"") -> 64.80274
B28: 5 | C28: =IFERROR('TOP 20 VALOR'!C8,"") | D28: =IFERROR('TOP 20 VALOR'!D8,"") -> 20220003 | E28: =IFERROR('TOP 20 VALOR'!E8,"") -> ACEITE MOTOR MOBIL DELVAC MODERN 15W 40 | F28: =IFERROR('TOP 20 VALOR'!F8,"") -> ORGANIZACION TERPEL S.A. | G28: =IFERROR('TOP 20 VALOR'!G8,"") -> 1171.1 | H28: =IFERROR('TOP 20 VALOR'!H8,"") -> 56520.99 | I28: =IFERROR('TOP 20 VALOR'!I8,"") -> 66191731 | J28: =IFERROR('TOP 20 VALOR'!J8,"") -> A | K28: =IFERROR('TOP 20 CERO'!C8,"") -> 80120006 | L28: =IFERROR('TOP 20 CERO'!D8,"") -> FRANELA DE COLOR | M28: =IFERROR('TOP 20 CERO'!E8,"") -> 900449648 | N28: =IFERROR('TOP 20 CERO'!F8,"") -> 18937 | O28: =IFERROR('TOP 20 CERO'!G8,"") -> 51.882192
B29: 6 | C29: =IFERROR('TOP 20 VALOR'!C9,"") -> SU114003 | D29: =IFERROR('TOP 20 VALOR'!D9,"") -> 5100101 | E29: =IFERROR('TOP 20 VALOR'!E9,"") -> DISCO DE FRENO VENTILADO | F29: =IFERROR('TOP 20 VALOR'!F9,"") -> VOLVO GROUP COLOMBIA S A S | G29: =IFERROR('TOP 20 VALOR'!G9,"") -> 54 | H29: =IFERROR('TOP 20 VALOR'!H9,"") -> 1193464 | I29: =IFERROR('TOP 20 VALOR'!I9,"") -> 64447056 | J29: =IFERROR('TOP 20 VALOR'!J9,"") -> A | K29: =IFERROR('TOP 20 CERO'!C9,"") -> 20220002 | L29: =IFERROR('TOP 20 CERO'!D9,"") -> ACEITE MOTOR MOBIL M-DEL XHP 10W 40 | M29: =IFERROR('TOP 20 CERO'!E9,"") -> 830095213 | N29: =IFERROR('TOP 20 CERO'!F9,"") -> 15675.01 | O29: =IFERROR('TOP 20 CERO'!G9,"") -> 42.945233
B30: 7 | C30: =IFERROR('TOP 20 VALOR'!C10,"") | D30: =IFERROR('TOP 20 VALOR'!D10,"") -> 80200005 | E30: =IFERROR('TOP 20 VALOR'!E10,"") -> NVR -SREAMAX A8 | F30: =IFERROR('TOP 20 VALOR'!F10,"") -> COLOMBIA TELECOMUNICACIONES S.A E.S.P | G30: =IFERROR('TOP 20 VALOR'!G10,"") -> 7 | H30: =IFERROR('TOP 20 VALOR'!H10,"") -> 8725736 | I30: =IFERROR('TOP 20 VALOR'!I10,"") -> 61080152 | J30: =IFERROR('TOP 20 VALOR'!J10,"") -> A | K30: =IFERROR('TOP 20 CERO'!C10,"") -> 43000004 | L30: =IFERROR('TOP 20 CERO'!D10,"") -> ACEITE DIFERENCIAL MOBIL LUBE HD 85W140 | M30: =IFERROR('TOP 20 CERO'!E10,"") -> 830095213 | N30: =IFERROR('TOP 20 CERO'!F10,"") -> 13695 | O30: =IFERROR('TOP 20 CERO'!G10,"") -> 37.520548
B31: 8 | C31: =IFERROR('TOP 20 VALOR'!C11,"") -> SU114595 | D31: =IFERROR('TOP 20 VALOR'!D11,"") -> 5100200 | E31: =IFERROR('TOP 20 VALOR'!E11,"") -> JUEGO DE PASTILLAS DE DISCO DE FRENO | F31: =IFERROR('TOP 20 VALOR'!F11,"") -> COMERCONZA SAS | G31: =IFERROR('TOP 20 VALOR'!G11,"") -> 122 | H31: =IFERROR('TOP 20 VALOR'!H11,"") -> 500272 | I31: =IFERROR('TOP 20 VALOR'!I11,"") -> 61033184 | J31: =IFERROR('TOP 20 VALOR'!J11,"") -> A | K31: =IFERROR('TOP 20 CERO'!C11,"") -> 80130267-G | L31: =IFERROR('TOP 20 CERO'!D11,"") -> POLIURETANO VERDE | M31: =IFERROR('TOP 20 CERO'!E11,"") -> 900449648 | N31: =IFERROR('TOP 20 CERO'!F11,"") -> 12000 | O31: =IFERROR('TOP 20 CERO'!G11,"") -> 32.876712
B32: 9 | C32: =IFERROR('TOP 20 VALOR'!C12,"") -> SU114612 | D32: =IFERROR('TOP 20 VALOR'!D12,"") -> 2540131 | E32: =IFERROR('TOP 20 VALOR'!E12,"") -> ADBLUE ARLA 32 AUTOMOTRIZ | F32: =IFERROR('TOP 20 VALOR'!F12,"") -> HIDROTECNIK S A S | G32: =IFERROR('TOP 20 VALOR'!G12,"") -> 16174.9 | H32: =IFERROR('TOP 20 VALOR'!H12,"") -> 3094 | I32: =IFERROR('TOP 20 VALOR'!I12,"") -> 50045141 | J32: =IFERROR('TOP 20 VALOR'!J12,"") -> A | K32: =IFERROR('TOP 20 CERO'!C12,"") -> 2210102 | L32: =IFERROR('TOP 20 CERO'!D12,"") -> ACEITE MOTOR SHEEL RIMULA R5 LE 10 W 40 | M32: =IFERROR('TOP 20 CERO'!E12,"") -> 800186960 | N32: =IFERROR('TOP 20 CERO'!F12,"") -> 9347.991 | O32: =IFERROR('TOP 20 CERO'!G12,"") -> 25.610934
B33: 10 | C33: =IFERROR('TOP 20 VALOR'!C13,"") | D33: =IFERROR('TOP 20 VALOR'!D13,"") -> 20220008 | E33: =IFERROR('TOP 20 VALOR'!E13,"") -> BOMBA DE ACEITE MOTOR | F33: =IFERROR('TOP 20 VALOR'!F13,"") -> VOLVO GROUP COLOMBIA S A S | G33: =IFERROR('TOP 20 VALOR'!G13,"") -> 4 | H33: =IFERROR('TOP 20 VALOR'!H13,"") -> 11534730 | I33: =IFERROR('TOP 20 VALOR'!I13,"") -> 46138920 | J33: =IFERROR('TOP 20 VALOR'!J13,"") -> A | K33: =IFERROR('TOP 20 CERO'!C13,"") -> 80110144-R | L33: =IFERROR('TOP 20 CERO'!D13,"") -> EXTINTOR DE INCENDIO | M33: =IFERROR('TOP 20 CERO'!E13,"") -> 800105847 | N33: =IFERROR('TOP 20 CERO'!F13,"") -> 6145 | O33: =IFERROR('TOP 20 CERO'!G13,"") -> 16.835616
B34: 11 | C34: =IFERROR('TOP 20 VALOR'!C14,"") | D34: =IFERROR('TOP 20 VALOR'!D14,"") -> 43000003 | E34: =IFERROR('TOP 20 VALOR'!E14,"") -> ACEITE DIFERENCIAL MOBIL LUBE HD PLUS 85W140 | F34: =IFERROR('TOP 20 VALOR'!F14,"") -> ORGANIZACION TERPEL S.A. | G34: =IFERROR('TOP 20 VALOR'!G14,"") -> 451.07 | H34: =IFERROR('TOP 20 VALOR'!H14,"") -> 85083.15 | I34: =IFERROR('TOP 20 VALOR'!I14,"") -> 38378456 | J34: =IFERROR('TOP 20 VALOR'!J14,"") -> A | K34: =IFERROR('TOP 20 CERO'!C14,"") -> 80120180 | L34: =IFERROR('TOP 20 CERO'!D14,"") -> CATALIZADOR RAPIDO | M34: =IFERROR('TOP 20 CERO'!E14,"") -> 900449648 | N34: =IFERROR('TOP 20 CERO'!F14,"") -> 5588 | O34: =IFERROR('TOP 20 CERO'!G14,"") -> 15.309589
B35: 12 | C35: =IFERROR('TOP 20 VALOR'!C15,"") | D35: =IFERROR('TOP 20 VALOR'!D15,"") -> 43000006 | E35: =IFERROR('TOP 20 VALOR'!E15,"") -> ACEITE CAJA MOBIL ATF DELVAC DRUM | F35: =IFERROR('TOP 20 VALOR'!F15,"") -> ORGANIZACION TERPEL S.A. | G35: =IFERROR('TOP 20 VALOR'!G15,"") -> 236.31 | H35: =IFERROR('TOP 20 VALOR'!H15,"") -> 156917.6 | I35: =IFERROR('TOP 20 VALOR'!I15,"") -> 37081198 | J35: =IFERROR('TOP 20 VALOR'!J15,"") -> A | K35: =IFERROR('TOP 20 CERO'!C15,"") -> 77101027-R | L35: =IFERROR('TOP 20 CERO'!D15,"") -> LLANTA REENCAUCHADA RADIAL 295/80-R22.5 | M35: =IFERROR('TOP 20 CERO'!E15,"") -> 900268222 | N35: =IFERROR('TOP 20 CERO'!F15,"") -> 5367 | O35: =IFERROR('TOP 20 CERO'!G15,"") -> 14.70411
... B43: 20 | C43: =IFERROR('TOP 20 VALOR'!C23,"") -> SU111857 | D43: =IFERROR('TOP 20 VALOR'!D23,"") -> 7260200 | E43: =IFERROR('TOP 20 VALOR'!E23,"") -> FUELLE NEUMATICO DELANTERO | F43: =IFERROR('TOP 20 VALOR'!F23,"") -> VOLVO GROUP COLOMBIA S A S | G43: =IFERROR('TOP 20 VALOR'!G23,"") -> 19 | H43: =IFERROR('TOP 20 VALOR'!H23,"") -> 690200 | I43: =IFERROR('TOP 20 VALOR'!I23,"") -> 13113800 | J43: =IFERROR('TOP 20 VALOR'!J23,"") -> A | K43: =IFERROR('TOP 20 CERO'!C23,"") -> 4370100 | L43: =IFERROR('TOP 20 CERO'!D23,"") -> ACEITE CAJA SHEEL ATF S4 HDX | M43: =IFERROR('TOP 20 CERO'!E23,"") -> 800186960 | N43: =IFERROR('TOP 20 CERO'!F23,"") -> 1980 | O43: =IFERROR('TOP 20 CERO'!G23,"") -> 5.4246575
B45: PRINCIPIOS LOGISTICOS APLICADOS (Ballou - Logistica: Cadena de Suministro 5ta Ed.)
B46: Clasificacion ABC (Pareto 80/20) | F46: Productos A (alto valor), B (medio), C (bajo). Clase A = control estricto. | L46: ="A:"&COUNTIF(DATA!M4:M2103,"A")&" | B:"&COUNTIF(DATA!M4:M2103,"B")&" | C:"&COUNTIF(DATA!M4:M2103,"C") -> A:1144 | B:335 | C:349
B47: Punto de Reorden (ROP) | F47: ROP = Consumo Diario x Lead Time + Stock Seguridad. | L47: Formula en CONTROL INVENTARIO
B48: Just In Time (JIT) | F48: Minimizar inventario manteniendo disponibilidad. | L48: Aplicado en todas las formulas
B49: EOQ - Cantidad Economica | F49: Equilibra costos de ordenar vs. mantener inventario. | L49: ="Total refs: "&COUNTA(DATA!B4:B2103) -> Total refs: 1828
B50: Stock de Seguridad | F50: Buffer para variabilidad en demanda y lead time. | L50: ="Refs sin stock: "&COUNTIF(DATA!E4:E2103,0) -> Refs sin stock: 632
B51: Rotacion de Inventario | F51: Consumo / Stock Promedio. Mayor rotacion = mejor gestion. | L51: ="Valor inv: $"&TEXT(SUM('CONTROL INVENTARIO'!J4:J2103),"#,##0") -> Valor inv: $2.067.844.421
B54: LEYENDA DE COLORES - FORMATO CONDICIONAL (Cuando Pedir)
B55: ROJO - CRITICO | F55: Stock = 0 o Stock < Punto de Reorden. PEDIR INMEDIATAMENTE.
B56: NARANJA - REORDEN | F56: Stock en punto de reorden. Generar OC en 24 horas.
B57: AMARILLO - PRECAUCION | F57: Stock entre 1x y 2x del punto de reorden. Monitorear.
B58: VERDE - OPTIMO | F58: Stock > 2x Punto de Reorden. Nivel saludable JIT.
B59: MORADO - EXCESO | F59: Stock > 5x Consumo mensual. Evaluar reduccion.
B62: DISTRIBUCION ABC
B63: Clase A | D63: =COUNTIF(DATA!M4:M2103,"A") -> 1144
B64: Clase B | D64: =COUNTIF(DATA!M4:M2103,"B") -> 335
B65: Clase C | D65: =COUNTIF(DATA!M4:M2103,"C") -> 349
B67: ESTADO DE STOCK
B68: Stock Cero | D68: =COUNTIF(DATA!E4:E2103,0) -> 632
B69: Con Stock | D69: =COUNTIF(DATA!E4:E2103,">0") -> 1196
B86: NAVEGACION RAPIDA
B87: DATA | D87: Base de datos principal - Pegue datos Mainsaver aqui
B88: DATA PENDIENTES | D88: Ordenes de compra pendientes por llegar
B89: PENDIENTES DETALLE | D89: Detalle automatico de entregas pendientes
B90: CONTROL INVENTARIO | D90: Control JIT con formulas Ballou
B91: PROVEEDORES | D91: Maestro de proveedores (NIT + Nombre)
B92: TOP 20 VALOR | D92: Top 20 productos de mayor valor
B93: TOP 20 CERO | D93: Top 20 productos en stock cero
B94: DINAMICA | D94: Tabla dinamica de valores por cuenta
B96: Sistema JIT - Ballou 5ta Ed. | Generado: 07/04/2026 | Repotenciado para 2100 referencias

Sheet DATA
B1: BASE DE DATOS DE INVENTARIO - DESCARGA DIARIA MAINSAVER
B2: Pegue aqui los datos de Mainsaver | Las hojas CONTROL INVENTARIO, DASHBOARD, TOP 20 se actualizan automaticamente
B3: REFERENCIA | C3: DESCRIPCION | D3: PARTE FABRICANTE | E3: STOCK ACTUAL | F3: COSTO UNITARIO | G3: TOTAL STOCK | H3: CUENTA | I3: PUNTO PEDIDO | J3: MINIMO | K3: MAXIMO | L3: UM EMISION | M3: CLASE ABC | N3: USO ANNO | O3: USO ANNO ANT. | P3: LEAD TIME PROM. | Q3: ROTACION ANNO | R3: ROTACION ANT. | S3: QUIEBRES ANNO | T3: QUIEBRES ANT. | U3: COSTO PROM. | V3: ULTIMO COSTO | W3: NIT PROVEEDOR | X3: BODEGA
B4: 12110002 | C4: TORNILLO FIJACION TAPAVALVULAS | D4: 3169658 | E4: 6 | F4: 92885.63 | G4: =F4*E4 -> 557313.78 | H4: PLATAFORMA | I4: 3 | J4: 5 | K4: 10 | L4: UND | M4: A | N4: 125 | O4: 0 | P4: 0 | Q4: 1 | R4: 0 | S4: 8 | T4: 0 | U4: 92885.6 | V4: 92361.04 | W4: 900315569 | X4: SU01F0303
B5: 12110003 | C5: PERNO BOLA | D5: 20501055 | E5: 3 | F5: 26069.17 | G5: =F5*E5 -> 78207.51 | H5: PLATAFORMA | I5: 0 | J5: 0 | K5: 0 | L5: UND | M5: C | N5: 5 | O5: 0 | P5: 0 | Q5: 0 | R5: 0 | S5: 0 | T5: 0 | U5: 26069.2 | V5: 26517.51 | W5: 900315569 | X5: SU01F0204
B6: 12110004 | C6: TUERCA HEXAGONAL | D6: 60111964 | E6: 4 | F6: 45754.34 | G6: =F6*E6 -> 183017.36 | H6: PLATAFORMA | I6: 0 | J6: 0 | K6: 0 | L6: UND | M6: C | N6: 4 | O6: 0 | P6: 0 | Q6: 0 | R6: 0 | S6: 0 | T6: 0 | U6: 45754.3 | V6: 45889.39 | W6: 900315569 | X6: SU01F0203
B7: 12110005 | C7: ANILO TORICO | D7: 944364 | E7: 5 | F7: 2620.185 | G7: =F7*E7 -> 13100.925 | H7: PLATAFORMA | I7: 0 | J7: 0 | K7: 0 | L7: UND | M7: C | N7: 1 | O7: 0 | P7: 0 | Q7: 0 | R7: 0 | S7: 0 | T7: 0 | U7: 2620.18 | V7: 2620.185 | W7: 900315569 | X7: SU01A0202
B8: 12110006 | C8: ANILLO RETEN CAJA INTERMEDIA | D8: 20526428 | E8: 8 | F8: 12974.52 | G8: =F8*E8 -> 103796.16 | H8: PLATAFORMA | I8: 0 | J8: 0 | K8: 0 | L8: UND | M8: A | N8: 65 | O8: 0 | P8: 0 | Q8: 0 | R8: 0 | S8: 8 | T8: 0 | U8: 12974.5 | V8: 12974.52 | W8: 900315569 | X8: SU01F0202
B9: 12110007 | C9: CASQUETE ARBOL DE LEVAS | D9: 20503200 | E9: 6 | F9: 132652.4 | G9: =F9*E9 -> 795914.4 | H9: PLATAFORMA | I9: 0 | J9: 0 | K9: 0 | L9: UND | M9: C | N9: 4 | O9: 0 | P9: 0 | Q9: 0 | R9: 0 | S9: 2 | T9: 0 | U9: 132652 | V9: 119312 | W9: 900315569 | X9: SU01F0203
B10: 12110008 | C10: MANGUITO INYECTOR (CAMISILLA) | D10: 21351717 | E10: 87 | F10: 121057.9 | G10: =F10*E10 -> 10532037 | H10: PLATAFORMA | I10: 60 | J10: 50 | K10: 100 | L10: UND | M10: A | N10: 3631 | O10: 0 | P10: 0 | Q10: 0 | R10: 0 | S10: 3 | T10: 0 | U10: 121058 | V10: 120069.4 | W10: 900315569 | X10: SU01F0201
B11: 12110009 | C11: ANILLO TORICO 26,2x3 mm | D11: 949721 | E11: 9 | F11: 12783.38 | G11: =F11*E11 -> 115050.42 | H11: PLATAFORMA | I11: 5 | J11: 5 | K11: 10 | L11: UND | M11: A | N11: 125 | O11: 0 | P11: 0 | Q11: 0 | R11: 0 | S11: 6 | T11: 0 | U11: 12783.4 | V11: 10863.41 | W11: 900315569 | X11: SU01F0202
B12: 12110010 | C12: JUNTA DE CULATA | D12: 3099100 | E12: 4 | F12: 1148356 | G12: =F12*E12 -> 4593424 | H12: PLATAFORMA | I12: 1 | J12: 1 | K12: 2 | L12: UND | M12: A | N12: 40 | O12: 0 | P12: 0 | Q12: 0 | R12: 0 | S12: 13 | T12: 0 | U12: 1148356 | V12: 1148356 | W12: 900315569 | X12: SU01E0107
B13: 12110011 | C13: CASQUETE ARBOL DE LEVAS | D13: 276630 | E13: 0 | F13: 107001.6 | G13: =F13*E13 -> 0 | H13: PLATAFORMA | I13: 0 | J13: 6 | K13: 0 | L13: UND | M13: C | N13: 102 | O13: 0 | P13: 0 | Q13: 0 | R13: 0 | S13: 8 | T13: 0 | U13: 107002 | V13: 108306.7 | W13: 900315569 | X13: SU01F0203
B14: 12110012 | C14: TAPA BANCADA ARBOL DE LEVAS | D14: 3165309 | E14: 0 | F14: 11987543 | G14: =F14*E14 -> 0 | H14: PLATAFORMA | I14: 0 | J14: 0 | K14: 0 | L14: UND | M14: A | N14: 2 | O14: 0 | P14: 0 | Q14: 0 | R14: 0 | S14: 2 | T14: 0 | U14: 12000000 | V14: 11987543 | W14: 900315569 | X14: SU01E0107
B15: 12110013 | C15: RETEN MOLDURA TAPA DE DISTRIBUCIÓN | D15: 20714247 | E15: 11 | F15: 76313.15 | G15: =F15*E15 -> 839444.65 | H15: PLATAFORMA | I15: 1 | J15: 1 | K15: 2 | L15: UND | M15: A | N15: 20 | O15: 0 | P15: 0 | Q15: 0 | R15: 0 | S15: 6 | T15: 0 | U15: 76313.2 | V15: 65972.17 | W15: 900315569 | X15: SU01F0202
... B43: 12130022 | C43: CAPÓ (CARTER SECO) | D43: 21704040 | E43: 0 | F43: 522.75 | G43: =F43*E43 -> 0 | H43: PLATAFORMA | I43: 0 | J43: 0 | K43: 0 | L43: UND | M43: C | N43: 0 | O43: 0 | P43: 0 | Q43: 0 | R43: 0 | S43: 0 | T43: 0 | U43: 522.75 | V43: 0 | W43: 900315569 | X43: SU01A0202
B44: 12130022-R | C44: CAPÓ (CARTER SECO) | D44: 21704040 | E44: 0 | F44: 181594 | G44: =F44*E44 -> 0 | H44: PLATAFORMA | I44: 0 | J44: 0 | K44: 0 | L44: UND | M44: A | N44: 43 | O44: 0 | P44: 0 | Q44: 0 | R44: 0 | S44: 43 | T44: 0 | U44: 181594 | V44: 181594 | W44: 901327111 | X44: SU01C0203
B45: 12130023 | C45: DEPOSITO ACEITE (CARTER DE FILTROS) | D45: 23416531 | E45: 0 | F45: 1933.5 | G45: =F45*E45 -> 0 | H45: PLATAFORMA | I45: 0 | J45: 0 | K45: 0 | L45: UND | M45: B | N45: 0 | O45: 0 | P45: 0 | Q45: 0 | R45: 0 | S45: 0 | T45: 0 | U45: 1933.5 | V45: 0 | W45: 900315569 | X45: SU01A0202
B46: 12130023-R | C46: DEPOSITO ACEITE (CARTER DE FILTROS) | D46: 23416531 | E46: 1 | F46: 214021.5 | G46: =F46*E46 -> 214021.5 | H46: PLATAFORMA | I46: 0 | J46: 0 | K46: 0 | L46: UND | M46: C | N46: 1 | O46: 0 | P46: 0 | Q46: 0 | R46: 0 | S46: 1 | T46: 0 | U46: 214022 | V46: 214021.5 | W46: 901327111 | X46: SU01A0202
B47: 12140000 | C47: KIT DE RETENES DISTRIBUCIÓN | D47: 85104153 | E47: 4 | F47: 612221.8 | G47: =F47*E47 -> 2448887.2 | H47: PLATAFORMA | I47: 2 | J47: 2 | K47: 4 | L47: UND | M47: A | N47: 65 | O47: 0 | P47: 0 | Q47: 0 | R47: 0 | S47: 25 | T47: 0 | U47: 612222 | V47: 612221.8 | W47: 900315569 | X47: SU01F0203
B48: 12140001 | C48: ARANDELA AXIAL DE DISTRIBUCIÓN | D48: 8170220 | E48: 0 | F48: 88909 | G48: =F48*E48 -> 0 | H48: PLATAFORMA | I48: 0 | J48: 0 | K48: 0 | L48: UND | M48: C | N48: 20 | O48: 0 | P48: 0 | Q48: 0 | R48: 0 | S48: 3 | T48: 0 | U48: 88909 | V48: 89150.93 | W48: 900315569 | X48: SU01F0203
B49: 12140002 | C49: ARANDELA DE PRESIÓN DISTRIBUCIÓN | D49: 3184865 | E49: 0 | F49: 84838.65 | G49: =F49*E49 -> 0 | H49: PLATAFORMA | I49: 0 | J49: 0 | K49: 0 | L49: UND | M49: A | N49: 20 | O49: 0 | P49: 0 | Q49: 0 | R49: 0 | S49: 3 | T49: 0 | U49: 84838.6 | V49: 86790.27 | W49: 900315569 | X49: SU01F0203
B50: 12140003 | C50: RETENEDOR CIGÜEÑAL TRASERO | D50: 24817250 | E50: 3 | F50: 451909.4 | G50: =F50*E50 -> 1355728.2 | H50: PLATAFORMA | I50: 2 | J50: 1 | K50: 4 | L50: UND | M50: A | N50: 49 | O50: 0 | P50: 0 | Q50: 1 | R50: 0 | S50: 12 | T50: 0 | U50: 451909 | V50: 451909.4 | W50: 900315569 | X50: SU01F0203
B51: 12140004 | C51: JUNTA CHAPA DE DISTRIBUCIÓN | D51: 20489341 | E51: 4 | F51: 92361.04 | G51: =F51*E51 -> 369444.16 | H51: PLATAFORMA | I51: 1 | J51: 1 | K51: 2 | L51: UND | M51: A | N51: 39 | O51: 0 | P51: 0 | Q51: 0 | R51: 0 | S51: 16 | T51: 0 | U51: 92361 | V51: 92361.04 | W51: 900315569 | X51: SU01F0202
B52: 12140005 | C52: JUNTA MEDIA TAPA DE DISTRIBUCION | D52: 3830184 | E52: 4 | F52: 50138.85 | G52: =F52*E52 -> 200555.4 | H52: PLATAFORMA | I52: 2 | J52: 2 | K52: 6 | L52: UND | M52: A | N52: 75 | O52: 0 | P52: 0 | Q52: 0 | R52: 0 | S52: 26 | T52: 0 | U52: 50138.9 | V52: 50138.85 | W52: 900315569 | X52: SU01F0202
B53: 12140006 | C53: JUNTA MEDIA TAPA DE DISTRIBUCION | D53: 20509433 | E53: 4 | F53: 36944.42 | G53: =F53*E53 -> 147777.68 | H53: PLATAFORMA | I53: 2 | J53: 1 | K53: 4 | L53: UND | M53: A | N53: 77 | O53: 0 | P53: 0 | Q53: 0 | R53: 0 | S53: 22 | T53: 0 | U53: 36944.4 | V53: 36944.42 | W53: 900315569 | X53: SU01F0202
B54: 12140007 | C54: RETENEDOR CIGUEÑAL DELANTERO | D54: 21347087 | E54: 5 | F54: 360383.4 | G54: =F54*E54 -> 1801917 | H54: PLATAFORMA | I54: 1 | J54: 0 | K54: 3 | L54: UND | M54: C | N54: 10 | O54: 0 | P54: 0 | Q54: 0 | R54: 0 | S54: 2 | T54: 0 | U54: 360383 | V54: 376936.7 | W54: 900315569 | X54: SU01F0203
B55: 12220007 | C55: TAPON MAGNETICO CARTER MOTOR | D55: 949175 | E55: 2 | F55: 70010.96 | G55: =F55*E55 -> 140021.92 | H55: PLATAFORMA | I55: 0 | J55: 0 | K55: 0 | L55: UND | M55: C | N55: 34 | O55: 0 | P55: 0 | Q55: 1 | R55: 0 | S55: 2 | T55: 0 | U55: 70011 | V55: 74801.57 | W55: 900315569 | X55: SU01F0304
B56: 12220008 | C56: TAPON MAGNETICO CARTER | D56: 20556987 | E56: 0 | F56: 0 | G56: =F56*E56 -> 0 | H56: PLATAFORMA | I56: 0 | J56: 0 | K56: 0 | L56: UND | M56: A | N56: 0 | O56: 0 | P56: 0 | Q56: 0 | R56: 0 | S56: 0 | T56: 0 | U56: 0 | V56: 0 | W56: 900315569 | X56: SU01C0203
B57: 12220009 | C57: SILICONA ULTRA GREY LOCTITE 300 ML | E57: 1 | F57: 143076.1 | G57: =F57*E57 -> 143076.1 | H57: PLATAFORMA | I57: 2 | J57: 2 | K57: 3 | L57: UND | M57: A | N57: 111 | O57: 0 | P57: 0 | Q57: 2 | R57: 0 | S57: 7 | T57: 0 | U57: 143076 | V57: 143076.1 | W57: 811025549 | X57: SU01E0304
B58: 12220010 | C58: ANILLO RETEN TUBO ACEITE | D58: 1677370 | E58: 13 | F58: 8480.923 | G58: =F58*E58 -> 110252 | H58: PLATAFORMA | I58: 10 | J58: 4 | K58: 20 | L58: UND | M58: A | N58: 196 | O58: 0 | P58: 0 | Q58: 0 | R58: 0 | S58: 8 | T58: 0 | U58: 8480.92 | V58: 8224.53 | W58: 900315569 | X58: SU01F0202
B59: 12220011 | C59: MANGUERA BAYONETA DE ACEITE | D59: 8149606 | E59: 1 | F59: 132911.1 | G59: =F59*E59 -> 132911.1 | H59: PLATAFORMA | I59: 1 | J59: 1 | K59: 3 | L59: UND | M59: A | N59: 18 | O59: 0 | P59: 0 | Q59: 1 | R59: 0 | S59: 8 | T59: 0 | U59: 132911 | V59: 132911.1 | W59: 900315569 | X59: SU01F0202
B60: 12220012 | C60: JUEGO DE RETENES CARTER DE ACEITE | D60: 85104152 | E60: 4 | F60: 1142638 | G60: =F60*E60 -> 4570552 | H60: PLATAFORMA | I60: 2 | J60: 2 | K60: 4 | L60: UND | M60: A | N60: 68 | O60: 0 | P60: 0 | Q60: 0 | R60: 0 | S60: 26 | T60: 0 | U60: 1142638 | V60: 1142638 | W60: 900315569 | X60: SU01F0202
B61: 12220013 | C61: LISTON DE GOMA | D61: 8192235 | E61: 9 | F61: 102916.6 | G61: =F61*E61 -> 926249.4 | H61: PLATAFORMA | I61: 6 | J61: 6 | K61: 12 | L61: M | M61: A | N61: 240 | O61: 0 | P61: 0 | Q61: 0 | R61: 0 | S61: 19 | T61: 0 | U61: 102917 | V61: 102916.6 | W61: 900315569 | X61: SU01F0202
B62: 12220014 | C62: SILICONA ULTRA GREY LOCTITE 50 ML | D62: 6581 | E62: 9 | F62: 19456.5 | G62: =F62*E62 -> 175108.5 | H62: PLATAFORMA | I62: 10 | J62: 5 | K62: 20 | L62: UND | M62: A | N62: 270 | O62: 0 | P62: 0 | Q62: 1 | R62: 0 | S62: 13 | T62: 0 | U62: 19456.5 | V62: 19456.5 | W62: 900057383 | X62: SU01E0304
B63: 12330003 | C63: TUBO PLASTICO DE COMBUSTIBLE 12MM | D63: 980833 | E63: 5 | F63: 19648.68 | G63: =F63*E63 -> 98243.4 | H63: PLATAFORMA | I63: 0 | J63: 0 | K63: 0 | L63: M | M63: C | N63: 40 | O63: 0 | P63: 0 | Q63: 0 | R63: 0 | S63: 0 | T63: 0 | U63: 19648.7 | V63: 5.32 | W63: 900315569 | X63: SU01A0203
B64: 12330004 | C64: ABRAZADERA ENCAUCHETADA 1 1/2" #40 | D64: 101030007 | E64: 8 | F64: 4385.15 | G64: =F64*E64 -> 35081.2 | H64: PLATAFORMA | I64: 4 | J64: 4 | K64: 8 | L64: UND | M64: A | N64: 451 | O64: 0 | P64: 0 | Q64: 0 | R64: 0 | S64: 2 | T64: 0 | U64: 4385.15 | V64: 4385.15 | W64: 826003816 | X64: SU01D0303
B65: 12330005 | C65: VALVULA DE AIREACION (DESFOGUE TANQUE COMB.) | D65: 20572888 | E65: 0 | F65: 114568.5 | G65: =F65*E65 -> 0 | H65: PLATAFORMA | I65: 0 | J65: 0 | K65: 0 | L65: UND | M65: A | N65: 1 | O65: 0 | P65: 0 | Q65: 0 | R65: 0 | S65: 1 | T65: 0 | U65: 114568 | V65: 114568.5 | W65: 900315569 | X65: SU01C0204
B66: 12330006 | C66: TUBO DESFOGUE TANQUE COMBUSTIBLE | D66: 980832 | E66: 0 | F66: 0 | G66: =F66*E66 -> 0 | H66: PLATAFORMA | I66: 0 | J66: 0 | K66: 0 | L66: UND | M66: A | N66: 0 | O66: 0 | P66: 0 | Q66: 0 | R66: 0 | S66: 0 | T66: 0 | U66: 0 | V66: 0 | W66: 900315569 | X66: SU01C0204
B67: 12330007 | C67: INYECTOR BOMBA | D67: 20569291 | E67: 0 | F67: 3278355 | G67: =F67*E67 -> 0 | H67: PLATAFORMA | I67: 0 | J67: 0 | K67: 0 | L67: UND | M67: A | N67: 8 | O67: 0 | P67: 0 | Q67: 0 | R67: 0 | S67: 3 | T67: 0 | U67: 3278355 | V67: 3278355 | W67: 900315569 | X67: SU01B0202
B68: 12330007-R | C68: INYECTOR BOMBA | D68: 20569291 | E68: 19 | F68: 570465.2 | G68: =F68*E68 -> 10838839 | H68: PLATAFORMA | I68: 0 | J68: 0 | K68: 0 | L68: UND | M68: A | N68: 2451 | O68: 0 | P68: 0 | Q68: 0 | R68: 0 | S68: 62 | T68: 0 | U68: 570465 | V68: 1785000 | W68: 900559647 | X68: SU01B0202
B69: 12330008 | C69: SENSOR NIVEL COMBUSTIBLE (PESCADOR) | D69: 22098806 | E69: 1 | F69: 1287252 | G69: =F69*E69 -> 1287252 | H69: PLATAFORMA | I69: 0 | J69: 0 | K69: 0 | L69: UND | M69: C | N69: 5 | O69: 0 | P69: 0 | Q69: 0 | R69: 0 | S69: 7 | T69: 0 | U69: 1287252 | V69: 1287252 | W69: 900315569 | X69: SU01F0203
B70: 12330009 | C70: ELECTROVALVULA CIERRE COMBUSTIBLE | D70: 22463597 | E70: 0 | F70: 654568.4 | G70: =F70*E70 -> 0 | H70: PLATAFORMA | I70: 0 | J70: 0 | K70: 0 | L70: UND | M70: A | N70: 4 | O70: 0 | P70: 0 | Q70: 0 | R70: 0 | S70: 4 | T70: 0 | U70: 654568 | V70: 654568.4 | W70: 900315569 | X70: SU01F0203
B71: 12330010 | C71: JUNTA DE BOMBA DE COMBUSTIBLE | D71: 3964833 | E71: 7 | F71: 86048.6 | G71: =F71*E71 -> 602340.2 | H71: PLATAFORMA | I71: 10 | J71: 5 | K71: 20 | L71: UND | M71: A | N71: 272 | O71: 0 | P71: 0 | Q71: 1 | R71: 0 | S71: 10 | T71: 0 | U71: 86048.6 | V71: 83124.94 | W71: 900315569 | X71: SU01F0203
B72: 12330011 | C72: BOMBA DE COMBUSTIBLE | D72: 21539988 | E72: 0 | F72: 1134123 | G72: =F72*E72 -> 0 | H72: PLATAFORMA | I72: 1 | J72: 0 | K72: 2 | L72: UND | M72: A | N72: 33 | O72: 0 | P72: 0 | Q72: 0 | R72: 0 | S72: 16 | T72: 0 | U72: 1134123 | V72: 1134123 | W72: 900315569 | X72: SU01F0202
B73: 12330011-R | C73: BOMBA DE COMBUSTIBLE | D73: 21539988 | E73: 0 | F73: 478975 | G73: =F73*E73 -> 0 | H73: PLATAFORMA | I73: 2 | J73: 0 | K73: 4 | L73: UND | M73: B | N73: 1 | O73: 0 | P73: 0 | Q73: 0 | R73: 0 | S73: 1 | T73: 0 | U73: 478975 | V73: 478975 | W73: 900449648 | X73: SU01B0203
B74: 12330012 | C74: MANGUERA 12 MM | D74: 21327788 | E74: 5 | F74: 11024.16 | G74: =F74*E74 -> 55120.8 | H74: PLATAFORMA | I74: 3 | J74: 3 | K74: 5 | L74: M | M74: A | N74: 61 | O74: 0 | P74: 0 | Q74: 0 | R74: 0 | S74: 1 | T74: 0 | U74: 11024.2 | V74: 11024.16 | W74: 900603232 | X74: SU01D0204
B75: 12330013 | C75: JUEGO DE ANILLO TORICO DE INYECTOR | D75: 276948 | E75: 23 | F75: 23036.26 | G75: =F75*E75 -> 529833.98 | H75: PLATAFORMA | I75: 0 | J75: 0 | K75: 0 | L75: UND | M75: A | N75: 15 | O75: 0 | P75: 0 | Q75: 0 | R75: 0 | S75: 1 | T75: 0 | U75: 23036.3 | V75: 22111.89 | W75: 900315569 | X75: SU01F0202
B76: 12330014 | C76: ANILLO RETEN DUCTOS DE COMBUSTIBLE | D76: 20883435 | E76: 10 | F76: 16167.97 | G76: =F76*E76 -> 161679.7 | H76: PLATAFORMA | I76: 0 | J76: 0 | K76: 0 | L76: UND | M76: A | N76: 0 | O76: 0 | P76: 0 | Q76: 0 | R76: 0 | S76: 0 | T76: 0 | U76: 16168 | V76: 16167.97 | W76: 900315569 | X76: SU01A0202
B77: 12330015 | C77: ANILLO RETEN DUCTOS DE COMBUSTIBLE | D77: 20852764 | E77: 1 | F77: 12390.89 | G77: =F77*E77 -> 12390.89 | H77: PLATAFORMA | I77: 1 | J77: 1 | K77: 2 | L77: UND | M77: A | N77: 17 | O77: 0 | P77: 0 | Q77: 1 | R77: 0 | S77: 4 | T77: 0 | U77: 12390.9 | V77: 12390.89 | W77: 900315569 | X77: SU01F0303
B78: 12330016 | C78: ANILLO RETEN DUCTOS DE COMBUSTIBLE | D78: 20852765 | E78: 1 | F78: 15894.27 | G78: =F78*E78 -> 15894.27 | H78: PLATAFORMA | I78: 0 | J78: 0 | K78: 0 | L78: UND | M78: A | N78: 16 | O78: 0 | P78: 0 | Q78: 0 | R78: 0 | S78: 3 | T78: 0 | U78: 15894.3 | V78: 15894.27 | W78: 900315569 | X78: SU01F0303
B79: 12330017 | C79: ANILLO RETEN DUCTOS DE COMBUSTIBLE | D79: 21123193 | E79: 3 | F79: 16167.97 | G79: =F79*E79 -> 48503.91 | H79: PLATAFORMA | I79: 0 | J79: 0 | K79: 0 | L79: UND | M79: A | N79: 7 | O79: 0 | P79: 0 | Q79: 0 | R79: 0 | S79: 0 | T79: 0 | U79: 16168 | V79: 16167.97 | W79: 900315569 | X79: SU01F0303
B80: 12330018 | C80: ANILLO RETEN DUCTOS DE COMBUSTIBLE | D80: 20852762 | E80: 10 | F80: 15864.97 | G80: =F80*E80 -> 158649.7 | H80: PLATAFORMA | I80: 0 | J80: 0 | K80: 0 | L80: UND | M80: A | N80: 0 | O80: 0 | P80: 0 | Q80: 0 | R80: 0 | S80: 0 | T80: 0 | U80: 15865 | V80: 15864.97 | W80: 900315569 | X80: SU01A0202
B81: 12330019 | C81: ANILLO RETÉN | D81: 8148471 | E81: 4 | F81: 79590.97 | G81: =F81*E81 -> 318363.88 | H81: PLATAFORMA | I81: 8 | J81: 6 | K81: 15 | L81: UND | M81: C | N81: 290 | O81: 0 | P81: 0 | Q81: 2 | R81: 0 | S81: 6 | T81: 0 | U81: 79591 | V81: 72569.39 | W81: 900315569 | X81: SU01F0304
B82: 12330020 | C82: ANILLO RETÉN | D82: 1547951 | E82: 12 | F82: 30904.96 | G82: =F82*E82 -> 370859.52 | H82: PLATAFORMA | I82: 4 | J82: 1 | K82: 10 | L82: UND | M82: C | N82: 144 | O82: 0 | P82: 0 | Q82: 0 | R82: 0 | S82: 3 | T82: 0 | U82: 30905 | V82: 30611.08 | W82: 900315569 | X82: SU01F0304
B83: 12330021 | C83: TUBO DE COMBUSTIBLE | D83: 21329470 | E83: 1 | F83: 314162.7 | G83: =F83*E83 -> 314162.7 | H83: PLATAFORMA | I83: 1 | J83: 1 | K83: 2 | L83: UND | M83: C | N83: 23 | O83: 0 | P83: 0 | Q83: 1 | R83: 0 | S83: 14 | T83: 0 | U83: 314163 | V83: 314162.7 | W83: 900315569 | X83: SU01F0304
B84: 12330022 | C84: ARANDELA CAMISILLA | D84: 21261987 | E84: 146 | F84: 34591.4 | G84: =F84*E84 -> 5050344.4 | H84: PLATAFORMA | I84: 30 | J84: 20 | K84: 36 | L84: UND | M84: A | N84: 1071 | O84: 0 | P84: 0 | Q84: 0 | R84: 0 | S84: 13 | T84: 0 | U84: 34591.4 | V84: 34591.4 | W84: 900315569 | X84: SU01F0304
B85: 12330023 | C85: SENSOR DE PRESION COMBUSTIBLE Y ACEITE | D85: 22899626 | E85: 2 | F85: 377386.3 | G85: =F85*E85 -> 754772.6 | H85: PLATAFORMA | I85: 2 | J85: 2 | K85: 4 | L85: UND | M85: B | N85: 26 | O85: 0 | P85: 0 | Q85: 1 | R85: 0 | S85: 10 | T85: 0 | U85: 377386 | V85: 373670.7 | W85: 900315569 | X85: SU01F0204
B86: 12330024 | C86: TORNILLO FLANJE 10 X 1 ½ PASO 1,5 | E86: 15 | F86: 2243.15 | G86: =F86*E86 -> 33647.25 | H86: PLATAFORMA | I86: 5 | J86: 0 | K86: 10 | L86: UND | M86: B | N86: 167 | O86: 0 | P86: 0 | Q86: 0 | R86: 0 | S86: 2 | T86: 0 | U86: 2243.15 | V86: 2243.15 | W86: 900664298 | X86: SU01E0203
B87: 12330025 | C87: TORNILLO EMBUTIDO | D87: 60113537 | E87: 10 | F87: 2.05 | G87: =F87*E87 -> 20.5 | H87: PLATAFORMA | I87: 0 | J87: 0 | K87: 0 | L87: UND | M87: B | N87: 0 | O87: 0 | P87: 0 | Q87: 0 | R87: 0 | S87: 0 | T87: 0 | U87: 2.05 | V87: 0 | W87: 900315569 | X87: SU01A0202
B88: 12330026 | C88: TORNILLO PERFORADO | D88: 991048 | E88: 2 | F88: 15228.12 | G88: =F88*E88 -> 30456.24 | H88: PLATAFORMA | I88: 0 | J88: 0 | K88: 0 | L88: UND | M88: B | N88: 2 | O88: 0 | P88: 0 | Q88: 0 | R88: 0 | S88: 1 | T88: 0 | U88: 15228.1 | V88: 15228.12 | W88: 900315569 | X88: SU01F0203
B89: 12330027 | C89: JUNTA | D89: 20725116 | E89: 8 | F89: 2316.064 | G89: =F89*E89 -> 18528.512 | H89: PLATAFORMA | I89: 0 | J89: 0 | K89: 0 | L89: UND | M89: B | N89: 2 | O89: 0 | P89: 0 | Q89: 0 | R89: 0 | S89: 0 | T89: 0 | U89: 2316.06 | V89: 20810.17 | W89: 900315569 | X89: SU01A0202
B90: 12330028 | C90: MANGUERA ALIMENTACIÓN DE COMBUSTIBLE | D90: 22446560 | E90: 1 | F90: 683168.8 | G90: =F90*E90 -> 683168.8 | H90: PLATAFORMA | I90: 1 | J90: 1 | K90: 3 | L90: UND | M90: B | N90: 13 | O90: 0 | P90: 0 | Q90: 1 | R90: 0 | S90: 2 | T90: 0 | U90: 683169 | V90: 683168.8 | W90: 900315569 | X90: SU01F0301
B91: 12330028-R | C91: MANGUERA ALIMENTACIÓN DE COMBUSTIBLE | D91: 22446560 | E91: 3 | F91: 119000 | G91: =F91*E91 -> 357000 | H91: PLATAFORMA | I91: 0 | J91: 0 | K91: 0 | L91: UND | M91: B | N91: 3 | O91: 0 | P91: 0 | Q91: 0 | R91: 0 | S91: 0 | T91: 0 | U91: 119000 | V91: 119000 | W91: 901299713 | X91: SU01A0202
B92: 12330029 | C92: TUBO CONEXIÓN ENTRETANQUES | D92: 20924258 | E92: 0 | F92: 432711.8 | G92: =F92*E92 -> 0 | H92: PLATAFORMA | I92: 0 | J92: 0 | K92: 0 | L92: UND | M92: C | N92: 1 | O92: 0 | P92: 0 | Q92: 0 | R92: 0 | S92: 1 | T92: 0 | U92: 432712 | V92: 432711.8 | W92: 900315569 | X92: SU01A0202
B93: 12330030 | C93: ABRAZADERA TUBO CONEXIÓN ENTRETANQUES | D93: 947457 | E93: 0 | F93: 11635.14 | G93: =F93*E93 -> 0 | H93: PLATAFORMA | I93: 0 | J93: 0 | K93: 0 | L93: UND | M93: C | N93: 2 | O93: 0 | P93: 0 | Q93: 0 | R93: 0 | S93: 1 | T93: 0 | U93: 11635.1 | V93: 11635.14 | W93: 900315569 | X93: SU01A0202
B94: 12330031 | C94: MANGUERA TANQUE DE COMBUSTIBLE | D94: 20929351 | E94: 0 | F94: 46877.12 | G94: =F94*E94 -> 0 | H94: PLATAFORMA | I94: 0 | J94: 0 | K94: 0 | L94: UND | M94: A | N94: 2 | O94: 0 | P94: 0 | Q94: 0 | R94: 0 | S94: 1 | T94: 0 | U94: 46877.1 | V94: 46877.12 | W94: 900315569 | X94: SU01A0202
B95: 12330032 | C95: SOPORTE CONSOLA | D95: 965545 | E95: 2 | F95: 16421.94 | G95: =F95*E95 -> 32843.88 | H95: PLATAFORMA | I95: 0 | J95: 0 | K95: 0 | L95: UND | M95: C | N95: 0 | O95: 0 | P95: 0 | Q95: 0 | R95: 0 | S95: 0 | T95: 0 | U95: 16421.9 | V95: 16421.94 | W95: 900315569 | X95: SU01A0202
B96: 12330033 | C96: ABRAZADERA TUBO COMBUSTIBLE | D96: 942810 | E96: 18 | F96: 5950 | G96: =F96*E96 -> 107100 | H96: PLATAFORMA | I96: 2 | J96: 2 | K96: 4 | L96: UND | M96: A | N96: 272 | O96: 0 | P96: 0 | Q96: 0 | R96: 0 | S96: 1 | T96: 0 | U96: 5950 | V96: 5950 | W96: 900315569 | X96: SU01D0303
B97: 12330034 | C97: CAUCHO ABRAZADERA 16 MM | E97: 5 | F97: 10710 | G97: =F97*E97 -> 53550 | H97: PLATAFORMA | I97: 2 | J97: 2 | K97: 3 | L97: M | M97: B | N97: 25 | O97: 0 | P97: 0 | Q97: 0 | R97: 0 | S97: 2 | T97: 0 | U97: 10710 | V97: 10710 | W97: 901327111 | X97: SU01D0303
B98: 12330035 | C98: TORNILLO EMBRIDADO MORDAZA FIJACION INYECTOR | D98: 21344774 | E98: 26 | F98: 6446.361 | G98: =F98*E98 -> 167605.39 | H98: PLATAFORMA | I98: 10 | J98: 3 | K98: 20 | L98: UND | M98: B | N98: 249 | O98: 0 | P98: 0 | Q98: 0 | R98: 0 | S98: 0 | T98: 0 | U98: 6446.36 | V98: 6289.352 | W98: 900315569 | X98: SU01F0203
B99: 12330036 | C99: TERMINAL ESPIGA | D99: 21336484 | E99: 12 | F99: 5027.81 | G99: =F99*E99 -> 60333.72 | H99: PLATAFORMA | I99: 0 | J99: 0 | K99: 0 | L99: UND | M99: C | N99: 12 | O99: 0 | P99: 0 | Q99: 0 | R99: 0 | S99: 0 | T99: 0 | U99: 5027.81 | V99: 5027.81 | W99: 900315569 | X99: SU01E0102
B100: 12330037 | C100: CONECTOR | D100: 20429371 | E100: 2 | F100: 57570.4 | G100: =F100*E100 -> 115140.8 | H100: PLATAFORMA | I100: 0 | J100: 0 | K100: 0 | L100: UND | M100: C | N100: 4 | O100: 0 | P100: 0 | Q100: 0 | R100: 0 | S100: 0 | T100: 0 | U100: 57570.4 | V100: 57570.4 | W100: 900315569 | X100: SU01E0102
B101: 12330038 | C101: SELLADOR DE CABLE | D101: 20734499 | E101: 2 | F101: 2034.15 | G101: =F101*E101 -> 4068.3 | H101: PLATAFORMA | I101: 0 | J101: 0 | K101: 0 | L101: UND | M101: C | N101: 22 | O101: 0 | P101: 0 | Q101: 0 | R101: 0 | S101: 0 | T101: 0 | U101: 2034.15 | V101: 2034.15 | W101: 900315569 | X101: SU01E0102
B102: 12540004 | C102: FILTRO DE PARTICULAS | D102: 85112568 | E102: 0 | F102: 17497663 | G102: =F102*E102 -> 0 | H102: PLATAFORMA | I102: 0 | J102: 0 | K102: 0 | L102: UND | M102: A | N102: 1 | O102: 0 | P102: 0 | Q102: 0 | R102: 0 | S102: 1 | T102: 0 | U102: 17000000 | V102: 17497663 | W102: 900315569 | X102: A1
B103: 12540004-R | C103: FILTRO DE PARTICULAS | D103: 21068809 | E103: 0 | F103: 749700 | G103: =F103*E103 -> 0 | H103: PLATAFORMA | I103: 0 | J103: 0 | K103: 0 | L103: UND | M103: A | N103: 1123 | O103: 0 | P103: 0 | Q103: 0 | R103: 0 | S103: 446 | T103: 0 | U103: 749700 | V103: 749700 | W103: 900315569 | X103: SU01C0101
B104: 12540005 | C104: TAPA FILTRO DE ADBLUE | D104: 20877939 | E104: 3 | F104: 220168.9 | G104: =F104*E104 -> 660506.7 | H104: PLATAFORMA | I104: 1 | J104: 1 | K104: 2 | L104: UND | M104: A | N104: 55 | O104: 0 | P104: 0 | Q104: 0 | R104: 0 | S104: 16 | T104: 0 | U104: 220169 | V104: 214409.6 | W104: 900315569 | X104: SU01F0304
B105: 12540006 | C105: MANGUERA DE ADMISION SENSOR DE PRESION ATMOSFERICA | D105: 9955984 | E105: 0 | F105: 714394.5 | G105: =F105*E105 -> 0 | H105: PLATAFORMA | I105: 1 | J105: 1 | K105: 2 | L105: UND | M105: C | N105: 58 | O105: 0 | P105: 0 | Q105: 2 | R105: 0 | S105: 24 | T105: 0 | U105: 714394 | V105: 714394.5 | W105: 900315569 | X105: SU01F0301
B106: 12540006-R | C106: MANGUERA DE ADMISION SENSOR DE PRESION ATMOSFERICA | D106: 9955984 | E106: 3 | F106: 118118.2 | G106: =F106*E106 -> 354354.6 | H106: PLATAFORMA | I106: 1 | J106: 0 | K106: 2 | L106: UND | M106: C | N106: 12 | O106: 0 | P106: 0 | Q106: 0 | R106: 0 | S106: 2 | T106: 0 | U106: 118118 | V106: 118118.2 | W106: 901327111 | X106: SU01A0202
B107: 12540007 | C107: JUNTA METALICA TAPA FILTRO DE PARTICULAS | D107: 3183660 | E107: 6 | F107: 351140.8 | G107: =F107*E107 -> 2106844.8 | H107: PLATAFORMA | I107: 5 | J107: 5 | K107: 10 | L107: UND | M107: A | N107: 229 | O107: 0 | P107: 0 | Q107: 0 | R107: 0 | S107: 14 | T107: 0 | U107: 351141 | V107: 339756.7 | W107: 900315569 | X107: SU01F0304
B108: 12540008 | C108: TAPON TOMA DE PRESION FILTRO DE PARTICULAS | D108: PROSOMU01 | E108: 2 | F108: 125925.8 | G108: =F108*E108 -> 251851.6 | H108: PLATAFORMA | I108: 1 | J108: 1 | K108: 2 | L108: UND | M108: C | N108: 22 | O108: 0 | P108: 0 | Q108: 1 | R108: 0 | S108: 10 | T108: 0 | U108: 125926 | V108: 125925.8 | W108: 901327111 | X108: SU01D0303
B109: 12540009 | C109: JUNTA TAPA FILTRO DE PARTICULAS | D109: 3183659 | E109: 3 | F109: 355551.7 | G109: =F109*E109 -> 1066655.1 | H109: PLATAFORMA | I109: 2 | J109: 1 | K109: 4 | L109: UND | M109: A | N109: 63 | O109: 0 | P109: 0 | Q109: 1 | R109: 0 | S109: 8 | T109: 0 | U109: 355552 | V109: 349652.5 | W109: 900315569 | X109: SU01F0302
B110: 12540010 | C110: ADAPTADOR DE UNIDAD BOMBA DE ADBLUE | D110: 21333211 | E110: 0 | F110: 2610173 | G110: =F110*E110 -> 0 | H110: PLATAFORMA | I110: 0 | J110: 0 | K110: 0 | L110: UND | M110: C | N110: 4 | O110: 0 | P110: 0 | Q110: 0 | R110: 0 | S110: 4 | T110: 0 | U110: 2610173 | V110: 2610173 | W110: 900315569 | X110: SU01F0203
B111: 12540011 | C111: TAPON PEQUEÑO M10 TOMA PRESION FILTRO DE PARTICULAS | E111: 1 | F111: 11900 | G111: =F111*E111 -> 11900 | H111: PLATAFORMA | I111: 0 | J111: 0 | K111: 0 | L111: UND | M111: B | N111: 9 | O111: 0 | P111: 0 | Q111: 0 | R111: 0 | S111: 0 | T111: 0 | U111: 11900 | V111: 11900 | W111: 830074603 | X111: SU01D0303
B112: 12540012 | C112: ABRAZADERA DE MANGUERA CON TORNILLO SIN FIN Ø 160 MM | D112: 60114887 | E112: 1 | F112: 24255.82 | G112: =F112*E112 -> 24255.82 | H112: PLATAFORMA | I112: 1 | J112: 1 | K112: 2 | L112: UND | M112: B | N112: 28 | O112: 0 | P112: 0 | Q112: 1 | R112: 0 | S112: 9 | T112: 0 | U112: 24255.8 | V112: 24255.82 | W112: 900315569 | X112: SU01F0204
B113: 12540013 | C113: MANGUERA DE ESCAPE | D113: 22456989 | E113: 2 | F113: 479446.5 | G113: =F113*E113 -> 958893 | H113: PLATAFORMA | I113: 2 | J113: 1 | K113: 3 | L113: UND | M113: A | N113: 60 | O113: 0 | P113: 0 | Q113: 2 | R113: 0 | S113: 16 | T113: 0 | U113: 479446 | V113: 475282.9 | W113: 900315569 | X113: SU01F0301
B114: 12540014 | C114: ABRAZADERA TUBO DE ESCAPE | D114: 21408723 | E114: 3 | F114: 95711.02 | G114: =F114*E114 -> 287133.06 | H114: PLATAFORMA | I114: 4 | J114: 4 | K114: 10 | L114: UND | M114: A | N114: 186 | O114: 0 | P114: 0 | Q114: 1 | R114: 0 | S114: 12 | T114: 0 | U114: 95711 | V114: 95056.59 | W114: 900315569 | X114: SU01F0304
B115: 12540015 | C115: SENSOR P Y T MULTIPLE ADMISIÓN | D115: 20912144 | E115: 2 | F115: 1130846 | G115: =F115*E115 -> 2261692 | H115: PLATAFORMA | I115: 1 | J115: 1 | K115: 2 | L115: UND | M115: A | N115: 37 | O115: 0 | P115: 0 | Q115: 0 | R115: 0 | S115: 12 | T115: 0 | U115: 1130846 | V115: 1130846 | W115: 900315569 | X115: SU01F0304
B116: 12540016 | C116: TUERCA DE ACOPLAMIENTO | D116: 954356 | E116: 3 | F116: 7793.28 | G116: =F116*E116 -> 23379.84 | H116: PLATAFORMA | I116: 2 | J116: 2 | K116: 4 | L116: UND | M116: B | N116: 47 | O116: 0 | P116: 0 | Q116: 2 | R116: 0 | S116: 1 | T116: 0 | U116: 7793.28 | V116: 7619.784 | W116: 900315569 | X116: SU01F0203
B117: 12540017 | C117: CONO | D117: 954364 | E117: 3 | F117: 17570.67 | G117: =F117*E117 -> 52712.01 | H117: PLATAFORMA | I117: 1 | J117: 1 | K117: 2 | L117: UND | M117: C | N117: 49 | O117: 0 | P117: 0 | Q117: 1 | R117: 0 | S117: 3 | T117: 0 | U117: 17570.7 | V117: 17020.82 | W117: 900315569 | X117: SU01F0303
B118: 12540018 | C118: MANGUERA ENSAMBLADO | D118: 60113714 | E118: 0 | F118: 432671.4 | G118: =F118*E118 -> 0 | H118: PLATAFORMA | I118: 1 | J118: 1 | K118: 3 | L118: UND | M118: A | N118: 43 | O118: 0 | P118: 0 | Q118: 1 | R118: 0 | S118: 15 | T118: 0 | U118: 432671 | V118: 432671.4 | W118: 900315569 | X118: SU01F0301
B119: 12540019 | C119: TURBOCOMPRESOR | D119: 20824850 | E119: 0 | F119: 7889700 | G119: =F119*E119 -> 0 | H119: PLATAFORMA | I119: 0 | J119: 0 | K119: 0 | L119: UND | M119: A | N119: 1 | O119: 0 | P119: 0 | Q119: 0 | R119: 0 | S119: 1 | T119: 0 | U119: 7889700 | V119: 7889700 | W119: 900315569 | X119: SU01C0101
B120: 12540019-R | C120: TURBOCOMPRESOR | D120: 20824850 | E120: 2 | F120: 565250 | G120: =F120*E120 -> 1130500 | H120: PLATAFORMA | I120: 0 | J120: 0 | K120: 0 | L120: UND | M120: A | N120: 288 | O120: 0 | P120: 0 | Q120: 0 | R120: 0 | S120: 177 | T120: 0 | U120: 565250 | V120: 1130500 | W120: 900559647 | X120: SU01C0202
B121: 12540020 | C121: SENSOR NOX | D121: 22827995 | E121: 1 | F121: 1899260 | G121: =F121*E121 -> 1899260 | H121: PLATAFORMA | I121: 1 | J121: 1 | K121: 2 | L121: UND | M121: B | N121: 17 | O121: 0 | P121: 0 | Q121: 1 | R121: 0 | S121: 7 | T121: 0 | U121: 1899260 | V121: 1436211 | W121: 900315569 | X121: SU01F0204
B122: 12540020-R | C122: SENSOR NOX | D122: 22827995 | E122: 0 | F122: 142800 | G122: =F122*E122 -> 0 | H122: PLATAFORMA | I122: 0 | J122: 0 | K122: 0 | L122: UND | M122: B | N122: 1 | O122: 0 | P122: 0 | Q122: 0 | R122: 0 | S122: 1 | T122: 0 | U122: 142800 | V122: 142800 | W122: 901563039 | X122: SU01B0205
B123: 12540021 | C123: SENSOR TEMPERATURA CATALIZADOR | D123: 21412472 | E123: 2 | F123: 527606.5 | G123: =F123*E123 -> 1055213 | H123: PLATAFORMA | I123: 2 | J123: 2 | K123: 5 | L123: UND | M123: A | N123: 98 | O123: 0 | P123: 0 | Q123: 1 | R123: 0 | S123: 13 | T123: 0 | U123: 527607 | V123: 514582.9 | W123: 900315569 | X123: SU01F0304
B124: 12540022 | C124: ESPARRAGO TURBO | D124: 21345127 | E124: 9 | F124: 26775 | G124: =F124*E124 -> 240975 | H124: PLATAFORMA | I124: 1 | J124: 1 | K124: 2 | L124: UND | M124: B | N124: 37 | O124: 0 | P124: 0 | Q124: 0 | R124: 0 | S124: 2 | T124: 0 | U124: 26775 | V124: 26775 | W124: 900315569 | X124: SU01F0304
B125: 12540023 | C125: JUNTA PLANA EMPAQUE | D125: 20784537 | E125: 5 | F125: 23592.86 | G125: =F125*E125 -> 117964.3 | H125: PLATAFORMA | I125: 5 | J125: 3 | K125: 10 | L125: UND | M125: A | N125: 298 | O125: 0 | P125: 0 | Q125: 1 | R125: 0 | S125: 16 | T125: 0 | U125: 23592.9 | V125: 23057.27 | W125: 900315569 | X125: SU01F0304
B126: 12540024 | C126: TUERCA EMBRIDADA TURBO | D126: 1543499 | E126: 30 | F126: 8663.644 | G126: =F126*E126 -> 259909.32 | H126: PLATAFORMA | I126: 30 | J126: 15 | K126: 50 | L126: UND | M126: A | N126: 1192 | O126: 0 | P126: 0 | Q126: 1 | R126: 0 | S126: 23 | T126: 0 | U126: 8663.64 | V126: 8444.442 | W126: 900315569 | X126: SU01F0303
B127: 12540025 | C127: SENSOR TEMPERATURA FILTRO PARTICULAS | D127: 20889280 | E127: 1 | F127: 561093.3 | G127: =F127*E127 -> 561093.3 | H127: PLATAFORMA | I127: 1 | J127: 1 | K127: 2 | L127: UND | M127: B | N127: 25 | O127: 0 | P127: 0 | Q127: 1 | R127: 0 | S127: 13 | T127: 0 | U127: 561093 | V127: 561093.3 | W127: 900315569 | X127: SU01F0304
...

Sheet DATA PENDIENTES
B1: CONTROL DE MATERIALES PENDIENTES POR LLEGAR - ORDENES DE COMPRA
B2: Ultima actualizacion: 07/04/2026 | Pegue aqui datos de OC pendientes
B3: ORDEN COMPRA | C3: DESCRIPCION | D3: QTY ORDENADA | E3: UM | F3: QTY RECIBIDA | G3: QTY PENDIENTE | H3: COSTO UNIT. | I3: PROVEEDOR | J3: PARTE FABRICANTE | K3: COMPRADOR | L3: MAINSAVER | M3: FECHA PROMESA | N3: FECHA REQUERIDA | O3: VALOR IMPUESTO | P3: VALOR PENDIENTE | Q3: DIAS RETRASO | R3: ESTADO | S3: CUMPLIMIENTO | T3: PRIORIDAD
B4: SU114003 | C4: RUEDA SENSORA | D4: 312 | E4: UND | F4: 170 | G4: 142 | H4: 103221 | I4: VOLVO GROUP COLOMBIA S A S | J4: 22537018 | K4: CRISTHIAN BENITEZ | L4: 7640210 | M4: 46326 | N4: 46265 | O4: 6118941 | P4: =IFERROR(G4*H4,0) -> 14657382 | Q4: =IFERROR(IF(N4="","",MAX(TODAY()-N4,0)),0) -> 0 | R4: =IF(B4="","",IF(G4=0,"COMPLETO",IF(G4<=D4*0.1,"CASI COMPLETO","PENDIENTE"))) -> PENDIENTE | S4: =IF(B4="","",IFERROR(F4/D4,0)) -> 0.54487179 | T4: =IF(B4="","",IF(Q4>30,"CRITICO",IF(Q4>7,"URGENTE","NORMAL"))) -> NORMAL
B5: SU114003 | C5: DISCO DE FRENO VENTILADO | D5: 460 | E5: UND | F5: 280 | G5: 180 | H5: 1002911 | I5: VOLVO GROUP COLOMBIA S A S | J5: 21575071 | K5: CRISTHIAN BENITEZ | L5: 5100101 | M5: 46326 | N5: 46265 | O5: 87654421 | P5: =IFERROR(G5*H5,0) -> 180523980 | Q5: =IFERROR(IF(N5="","",MAX(TODAY()-N5,0)),0) -> 0 | R5: =IF(B5="","",IF(G5=0,"COMPLETO",IF(G5<=D5*0.1,"CASI COMPLETO","PENDIENTE"))) -> PENDIENTE | S5: =IF(B5="","",IFERROR(F5/D5,0)) -> 0.60869565 | T5: =IF(B5="","",IF(Q5>30,"CRITICO",IF(Q5>7,"URGENTE","NORMAL"))) -> NORMAL
B6: SU114003 | C6: DISCO DE FRENO SOLIDO | D6: 160 | E6: UND | F6: 110 | G6: 50 | H6: 1140000 | I6: VOLVO GROUP COLOMBIA S A S | J6: 3092710 | K6: CRISTHIAN BENITEZ | L6: 5100100 | M6: 46326 | N6: 46265 | O6: 34656000 | P6: =IFERROR(G6*H6,0) -> 57000000 | Q6: =IFERROR(IF(N6="","",MAX(TODAY()-N6,0)),0) -> 0 | R6: =IF(B6="","",IF(G6=0,"COMPLETO",IF(G6<=D6*0.1,"CASI COMPLETO","PENDIENTE"))) -> PENDIENTE | S6: =IF(B6="","",IFERROR(F6/D6,0)) -> 0.6875 | T6: =IF(B6="","",IF(Q6>30,"CRITICO",IF(Q6>7,"URGENTE","NORMAL"))) -> NORMAL
B7: SU114003 | C7: RODAMIENTO CUBO RUEDA DE REMOLQUE | D7: 360 | E7: UND | F7: 210 | G7: 150 | H7: 1554538 | I7: VOLVO GROUP COLOMBIA S A S | J7: 21036050 | K7: CRISTHIAN BENITEZ | L7: 7730306 | M7: 46326 | N7: 46265 | O7: 106000000 | P7: =IFERROR(G7*H7,0) -> 233180700 | Q7: =IFERROR(IF(N7="","",MAX(TODAY()-N7,0)),0) -> 0 | R7: =IF(B7="","",IF(G7=0,"COMPLETO",IF(G7<=D7*0.1,"CASI COMPLETO","PENDIENTE"))) -> PENDIENTE | S7: =IF(B7="","",IFERROR(F7/D7,0)) -> 0.58333333 | T7: =IF(B7="","",IF(Q7>30,"CRITICO",IF(Q7>7,"URGENTE","NORMAL"))) -> NORMAL
B8: SU115774 | C8: ANILLO RETÉN | D8: 4 | E8: UND | F8: 0 | G8: 4 | H8: 60598.23 | I8: VOLVO GROUP COLOMBIA S A S | J8: 8148471 | K8: CRISTHIAN BENITEZ | L8: 12330019 | M8: 46098 | N8: 46098 | O8: 46054.65 | P8: =IFERROR(G8*H8,0) -> 242392.92 | Q8: =IFERROR(IF(N8="","",MAX(TODAY()-N8,0)),0) -> 21 | R8: =IF(B8="","",IF(G8=0,"COMPLETO",IF(G8<=D8*0.1,"CASI COMPLETO","PENDIENTE"))) -> PENDIENTE | S8: =IF(B8="","",IFERROR(F8/D8,0)) -> 0 | T8: =IF(B8="","",IF(Q8>30,"CRITICO",IF(Q8>7,"URGENTE","NORMAL"))) -> URGENTE
B9: SU115845 | C9: TUERCA DE SUJECION FUELLE NEUMATICO | D9: 2 | E9: UND | F9: 0 | G9: 2 | H9: 6417.9 | I9: VOLVO GROUP COLOMBIA S A S | J9: 990943 | K9: CRISTHIAN BENITEZ | L9: 72601008 | M9: 46106 | N9: 46106 | O9: 2438.802 | P9: =IFERROR(G9*H9,0) -> 12835.8 | Q9: =IFERROR(IF(N9="","",MAX(TODAY()-N9,0)),0) -> 13 | R9: =IF(B9="","",IF(G9=0,"COMPLETO",IF(G9<=D9*0.1,"CASI COMPLETO","PENDIENTE"))) -> PENDIENTE | S9: =IF(B9="","",IFERROR(F9/D9,0)) -> 0 | T9: =IF(B9="","",IF(Q9>30,"CRITICO",IF(Q9>7,"URGENTE","NORMAL"))) -> URGENTE
B10: SU115897 | C10: VALVULA EPG | D10: 1 | E10: UND | F10: 0 | G10: 1 | H10: 1027415 | I10: VOLVO GROUP COLOMBIA S A S | J10: 24122364 | K10: CRISTHIAN BENITEZ | L10: 12540034 | M10: 46109 | N10: 46109 | O10: 195208.9 | P10: =IFERROR(G10*H10,0) -> 1027415 | Q10: =IFERROR(IF(N10="","",MAX(TODAY()-N10,0)),0) -> 10 | R10: =IF(B10="","",IF(G10=0,"COMPLETO",IF(G10<=D10*0.1,"CASI COMPLETO","PENDIENTE"))) -> PENDIENTE | S10: =IF(B10="","",IFERROR(F10/D10,0)) -> 0 | T10: =IF(B10="","",IF(Q10>30,"CRITICO",IF(Q10>7,"URGENTE","NORMAL"))) -> URGENTE
B11: SU115905 | C11: FILTRO DE PARTICULAS | D11: 4 | E11: UND | F11: 3 | G11: 1 | H11: 630000 | I11: VOLVO GROUP COLOMBIA S A S | J11: 21068809 | K11: CHARLY HUERTAS | L11: 12540004-R | M11: 46117 | N11: 46108 | O11: 478800 | P11: =IFERROR(G11*H11,0) -> 630000 | Q11: =IFERROR(IF(N11="","",MAX(TODAY()-N11,0)),0) -> 11 | R11: =IF(B11="","",IF(G11=0,"COMPLETO",IF(G11<=D11*0.1,"CASI COMPLETO","PENDIENTE"))) -> PENDIENTE | S11: =IF(B11="","",IFERROR(F11/D11,0)) -> 0.75 | T11: =IF(B11="","",IF(Q11>30,"CRITICO",IF(Q11>7,"URGENTE","NORMAL"))) -> URGENTE
B12: SU115941 | C12: MANGUITO INYECTOR (CAMISILLA) | D12: 60 | E12: UND | F12: 0 | G12: 60 | H12: 100898.6 | I12: VOLVO GROUP COLOMBIA S A S | J12: 21351717 | K12: CRISTHIAN BENITEZ | L12: 12110008 | M12: 46118 | N12: 46108 | O12: 1150244 | P12: =IFERROR(G12*H12,0) -> 6053916 | Q12: =IFERROR(IF(N12="","",MAX(TODAY()-N12,0)),0) -> 11 | R12: =IF(B12="","",IF(G12=0,"COMPLETO",IF(G12<=D12*0.1,"CASI COMPLETO","PENDIENTE"))) -> PENDIENTE | S12: =IF(B12="","",IFERROR(F12/D12,0)) -> 0 | T12: =IF(B12="","",IF(Q12>30,"CRITICO",IF(Q12>7,"URGENTE","NORMAL"))) -> URGENTE
B13: SU115941 | C13: MANGUERA DE REFRIGERACION RADIADOR | D13: 40 | E13: UND | F13: 0 | G13: 40 | H13: 141368.9 | I13: VOLVO GROUP COLOMBIA S A S | J13: 22129907 | K13: CRISTHIAN BENITEZ | L13: 12630024 | M13: 46118 | N13: 46108 | O13: 1074404 | P13: =IFERROR(G13*H13,0) -> 5654756 | Q13: =IFERROR(IF(N13="","",MAX(TODAY()-N13,0)),0) -> 11 | R13: =IF(B13="","",IF(G13=0,"COMPLETO",IF(G13<=D13*0.1,"CASI COMPLETO","PENDIENTE"))) -> PENDIENTE | S13: =IF(B13="","",IFERROR(F13/D13,0)) -> 0 | T13: =IF(B13="","",IF(Q13>30,"CRITICO",IF(Q13>7,"URGENTE","NORMAL"))) -> URGENTE
B14: SU115941 | C14: MANGUERA DE REFRIGERACION RADIADOR | D14: 60 | E14: UND | F14: 0 | G14: 60 | H14: 133053.1 | I14: VOLVO GROUP COLOMBIA S A S | J14: 22129120 | K14: CRISTHIAN BENITEZ | L14: 12630025 | M14: 46118 | N14: 46108 | O14: 1516806 | P14: =IFERROR(G14*H14,0) -> 7983186 | Q14: =IFERROR(IF(N14="","",MAX(TODAY()-N14,0)),0) -> 11 | R14: =IF(B14="","",IF(G14=0,"COMPLETO",IF(G14<=D14*0.1,"CASI COMPLETO","PENDIENTE"))) -> PENDIENTE | S14: =IF(B14="","",IFERROR(F14/D14,0)) -> 0 | T14: =IF(B14="","",IF(Q14>30,"CRITICO",IF(Q14>7,"URGENTE","NORMAL"))) -> URGENTE
B15: SU115941 | C15: MANGUERA DE REFRIGERACION COMPRESOR ØEXT 18MM ØINT 13MM | D15: 40 | E15: UND | F15: 0 | G15: 40 | H15: 69298.5 | I15: VOLVO GROUP COLOMBIA S A S | J15: 21339891 | K15: CRISTHIAN BENITEZ | L15: 12630027 | M15: 46118 | N15: 46108 | O15: 526668.6 | P15: =IFERROR(G15*H15,0) -> 2771940 | Q15: =IFERROR(IF(N15="","",MAX(TODAY()-N15,0)),0) -> 11 | R15: =IF(B15="","",IF(G15=0,"COMPLETO",IF(G15<=D15*0.1,"CASI COMPLETO","PENDIENTE"))) -> PENDIENTE | S15: =IF(B15="","",IFERROR(F15/D15,0)) -> 0 | T15: =IF(B15="","",IF(Q15>30,"CRITICO",IF(Q15>7,"URGENTE","NORMAL"))) -> URGENTE
B16: SU115941 | C16: MANGUERA DE UNION LARGA | D16: 30 | E16: UND | F16: 0 | G16: 30 | H16: 97017.9 | I16: VOLVO GROUP COLOMBIA S A S | J16: 22417892 | K16: CRISTHIAN BENITEZ | L16: 12630028 | M16: 46118 | N16: 46108 | O16: 553002 | P16: =IFERROR(G16*H16,0) -> 2910537 | Q16: =IFERROR(IF(N16="","",MAX(TODAY()-N16,0)),0) -> 11 | R16: =IF(B16="","",IF(G16=0,"COMPLETO",IF(G16<=D16*0.1,"CASI COMPLETO","PENDIENTE"))) -> PENDIENTE | S16: =IF(B16="","",IFERROR(F16/D16,0)) -> 0 | T16: =IF(B16="","",IF(Q16>30,"CRITICO",IF(Q16>7,"URGENTE","NORMAL"))) -> URGENTE
B17: SU115941 | C17: MANGUERA DE UNION CORTA | D17: 120 | E17: UND | F17: 0 | G17: 120 | H17: 77614.32 | I17: VOLVO GROUP COLOMBIA S A S | J17: 24288019 | K17: CRISTHIAN BENITEZ | L17: 12630029 | M17: 46118 | N17: 46108 | O17: 1769606 | P17: =IFERROR(G17*H17,0) -> 9313718.4 | Q17: =IFERROR(IF(N17="","",MAX(TODAY()-N17,0)),0) -> 11 | R17: =IF(B17="","",IF(G17=0,"COMPLETO",IF(G17<=D17*0.1,"CASI COMPLETO","PENDIENTE"))) -> PENDIENTE | S17: =IF(B17="","",IFERROR(F17/D17,0)) -> 0 | T17: =IF(B17="","",IF(Q17>30,"CRITICO",IF(Q17>7,"URGENTE","NORMAL"))) -> URGENTE
B18: SU115941 | C18: MANGUERA EN S TANQUE DE EXPANSION | D18: 60 | E18: UND | F18: 0 | G18: 60 | H18: 83158.2 | I18: VOLVO GROUP COLOMBIA S A S | J18: 22420663 | K18: CRISTHIAN BENITEZ | L18: 12630031 | M18: 46118 | N18: 46108 | O18: 948003.5 | P18: =IFERROR(G18*H18,0) -> 4989492 | Q18: =IFERROR(IF(N18="","",MAX(TODAY()-N18,0)),0) -> 11 | R18: =IF(B18="","",IF(G18=0,"COMPLETO",IF(G18<=D18*0.1,"CASI COMPLETO","PENDIENTE"))) -> PENDIENTE | S18: =IF(B18="","",IFERROR(F18/D18,0)) -> 0 | T18: =IF(B18="","",IF(Q18>30,"CRITICO",IF(Q18>7,"URGENTE","NORMAL"))) -> URGENTE
B19: SU115941 | C19: ABRAZADERA DE MANGUERA CON TORNILLO SINFÍN Ø 75MM | D19: 100 | E19: UND | F19: 0 | G19: 100 | H19: 6763.53 | I19: VOLVO GROUP COLOMBIA S A S | J19: 994565 | K19: CRISTHIAN BENITEZ | L19: 12630033 | M19: 46118 | N19: 46108 | O19: 128507.1 | P19: =IFERROR(G19*H19,0) -> 676353 | Q19: =IFERROR(IF(N19="","",MAX(TODAY()-N19,0)),0) -> 11 | R19: =IF(B19="","",IF(G19=0,"COMPLETO",IF(G19<=D19*0.1,"CASI COMPLETO","PENDIENTE"))) -> PENDIENTE | S19: =IF(B19="","",IFERROR(F19/D19,0)) -> 0 | T19: =IF(B19="","",IF(Q19>30,"CRITICO",IF(Q19>7,"URGENTE","NORMAL"))) -> URGENTE
B20: SU115941 | C20: ABRAZADERA DE MANGUERA CON TORNILLO SINFÍN Ø 66MM | D20: 600 | E20: UND | F20: 0 | G20: 600 | H20: 5904.23 | I20: VOLVO GROUP COLOMBIA S A S | J20: 994564 | K20: CRISTHIAN BENITEZ | L20: 12630034 | M20: 46118 | N20: 46108 | O20: 673082.2 | P20: =IFERROR(G20*H20,0) -> 3542538 | Q20: =IFERROR(IF(N20="","",MAX(TODAY()-N20,0)),0) -> 11 | R20: =IF(B20="","",IF(G20=0,"COMPLETO",IF(G20<=D20*0.1,"CASI COMPLETO","PENDIENTE"))) -> PENDIENTE | S20: =IF(B20="","",IFERROR(F20/D20,0)) -> 0 | T20: =IF(B20="","",IF(Q20>30,"CRITICO",IF(Q20>7,"URGENTE","NORMAL"))) -> URGENTE
B21: SU115941 | C21: ABRAZADERA DE MANGUERA CON TORNILLO SINFÍN Ø 15MM | D21: 300 | E21: UND | F21: 0 | G21: 300 | H21: 4241.07 | I21: VOLVO GROUP COLOMBIA S A S | J21: 994557 | K21: CRISTHIAN BENITEZ | L21: 12630035 | M21: 46118 | N21: 46108 | O21: 241741 | P21: =IFERROR(G21*H21,0) -> 1272321 | Q21: =IFERROR(IF(N21="","",MAX(TODAY()-N21,0)),0) -> 11 | R21: =IF(B21="","",IF(G21=0,"COMPLETO",IF(G21<=D21*0.1,"CASI COMPLETO","PENDIENTE"))) -> PENDIENTE | S21: =IF(B21="","",IFERROR(F21/D21,0)) -> 0 | T21: =IF(B21="","",IF(Q21>30,"CRITICO",IF(Q21>7,"URGENTE","NORMAL"))) -> URGENTE
B22: SU115941 | C22: ABRAZADERA DE MANGUERA CON TORNILLO SINFÍN Ø 45MM | D22: 120 | E22: UND | F22: 0 | G22: 120 | H22: 7317.92 | I22: VOLVO GROUP COLOMBIA S A S | J22: 984996 | K22: CRISTHIAN BENITEZ | L22: 12630036 | M22: 46118 | N22: 46108 | O22: 166848.6 | P22: =IFERROR(G22*H22,0) -> 878150.4 | Q22: =IFERROR(IF(N22="","",MAX(TODAY()-N22,0)),0) -> 11 | R22: =IF(B22="","",IF(G22=0,"COMPLETO",IF(G22<=D22*0.1,"CASI COMPLETO","PENDIENTE"))) -> PENDIENTE | S22: =IF(B22="","",IFERROR(F22/D22,0)) -> 0 | T22: =IF(B22="","",IF(Q22>30,"CRITICO",IF(Q22>7,"URGENTE","NORMAL"))) -> URGENTE
B23: SU115941 | C23: ABRAZADERA DE MANGUERA CON TORNILLO SINFÍN Ø 22MM | D23: 600 | E23: UND | F23: 0 | G23: 600 | H23: 5128.09 | I23: VOLVO GROUP COLOMBIA S A S | J23: 984993 | K23: CRISTHIAN BENITEZ | L23: 12630037 | M23: 46118 | N23: 46108 | O23: 584602.3 | P23: =IFERROR(G23*H23,0) -> 3076854 | Q23: =IFERROR(IF(N23="","",MAX(TODAY()-N23,0)),0) -> 11 | R23: =IF(B23="","",IF(G23=0,"COMPLETO",IF(G23<=D23*0.1,"CASI COMPLETO","PENDIENTE"))) -> PENDIENTE | S23: =IF(B23="","",IFERROR(F23/D23,0)) -> 0 | T23: =IF(B23="","",IF(Q23>30,"CRITICO",IF(Q23>7,"URGENTE","NORMAL"))) -> URGENTE
... B45: SU115951 | C45: TORNILLO EMBRIDADO M10*80 MM | D45: 5 | E45: UND | F45: 0 | G45: 5 | H45: 10533.37 | I45: VOLVO GROUP COLOMBIA S A S | J45: 984759 | K45: CRISTHIAN BENITEZ | L45: 2150209 | M45: 46122 | N45: 46120 | O45: 10006.7 | P45: =IFERROR(G45*H45,0) -> 52666.85 | Q45: =IFERROR(IF(N45="","",MAX(TODAY()-N45,0)),0) -> 0 | R45: =IF(B45="","",IF(G45=0,"COMPLETO",IF(G45<=D45*0.1,"CASI COMPLETO","PENDIENTE"))) -> PENDIENTE | S45: =IF(B45="","",IFERROR(F45/D45,0)) -> 0 | T45: =IF(B45="","",IF(Q45>30,"CRITICO",IF(Q45>7,"URGENTE","NORMAL"))) -> NORMAL
B46: SU115877 | C46: PERFIL PLASTICO AMARILLO | D46: 90 | E46: M | F46: 0 | G46: 90 | H46: 4700 | I46: UNIVERSAL DE PARTES Y REPUESTOS SAS | K46: CRISTHIAN BENITEZ | L46: 80130010 | M46: 46113 | N46: 46113 | O46: 80370 | P46: =IFERROR(G46*H46,0) -> 423000 | Q46: =IFERROR(IF(N46="","",MAX(TODAY()-N46,0)),0) -> 6 | R46: =IF(B46="","",IF(G46=0,"COMPLETO",IF(G46<=D46*0.1,"CASI COMPLETO","PENDIENTE"))) -> PENDIENTE | S46: =IF(B46="","",IFERROR(F46/D46,0)) -> 0 | T46: =IF(B46="","",IF(Q46>30,"CRITICO",IF(Q46>7,"URGENTE","NORMAL"))) -> NORMAL
B47: SU115877 | C47: ALMA (LAMINA) CAUCHO REDONDO ARTICULACIÓN | D47: 25 | E47: UND | F47: 12 | G47: 13 | H47: 22000 | I47: UNIVERSAL DE PARTES Y REPUESTOS SAS | K47: CRISTHIAN BENITEZ | L47: 801702026 | M47: 46113 | N47: 46113 | O47: 104500 | P47: =IFERROR(G47*H47,0) -> 286000 | Q47: =IFERROR(IF(N47="","",MAX(TODAY()-N47,0)),0) -> 6 | R47: =IF(B47="","",IF(G47=0,"COMPLETO",IF(G47<=D47*0.1,"CASI COMPLETO","PENDIENTE"))) -> PENDIENTE | S47: =IF(B47="","",IFERROR(F47/D47,0)) -> 0.48 | T47: =IF(B47="","",IF(Q47>30,"CRITICO",IF(Q47>7,"URGENTE","NORMAL"))) -> NORMAL
B48: SU115916 | C48: CORAZA DE 3/4" | D48: 60 | E48: M | F48: 0 | G48: 60 | H48: 1540 | I48: UNIVERSAL DE PARTES Y REPUESTOS SAS | J48: 2242 | K48: CRISTHIAN BENITEZ | L48: 80150077 | M48: 46116 | N48: 46108 | O48: 17556 | P48: =IFERROR(G48*H48,0) -> 92400 | Q48: =IFERROR(IF(N48="","",MAX(TODAY()-N48,0)),0) -> 11 | R48: =IF(B48="","",IF(G48=0,"COMPLETO",IF(G48<=D48*0.1,"CASI COMPLETO","PENDIENTE"))) -> PENDIENTE | S48: =IF(B48="","",IFERROR(F48/D48,0)) -> 0 | T48: =IF(B48="","",IF(Q48>30,"CRITICO",IF(Q48>7,"URGENTE","NORMAL"))) -> URGENTE
B49: SU115551 | C49: TORNILLO TRILOBULAR M8*25 | D49: 200 | E49: UND | F49: 0 | G49: 200 | H49: 700 | I49: TORNOHIMEC SAS | K49: CRISTHIAN BENITEZ | L49: 80110286 | M49: 46085 | N49: 46085 | O49: 26600 | P49: =IFERROR(G49*H49,0) -> 140000 | Q49: =IFERROR(IF(N49="","",MAX(TODAY()-N49,0)),0) -> 34 | R49: =IF(B49="","",IF(G49=0,"COMPLETO",IF(G49<=D49*0.1,"CASI COMPLETO","PENDIENTE"))) -> PENDIENTE | S49: =IF(B49="","",IFERROR(F49/D49,0)) -> 0 | T49: =IF(B49="","",IF(Q49>30,"CRITICO",IF(Q49>7,"URGENTE","NORMAL"))) -> CRITICO
B50: SU115882 | C50: TORNILLO TRILOBULAR M8*25 | D50: 100 | E50: UND | F50: 0 | G50: 100 | H50: 700 | I50: TORNOHIMEC SAS | K50: CRISTHIAN BENITEZ | L50: 80110286 | M50: 46113 | N50: 46113 | O50: 13300 | P50: =IFERROR(G50*H50,0) -> 70000 | Q50: =IFERROR(IF(N50="","",MAX(TODAY()-N50,0)),0) -> 6 | R50: =IF(B50="","",IF(G50=0,"COMPLETO",IF(G50<=D50*0.1,"CASI COMPLETO","PENDIENTE"))) -> PENDIENTE | S50: =IF(B50="","",IFERROR(F50/D50,0)) -> 0 | T50: =IF(B50="","",IF(Q50>30,"CRITICO",IF(Q50>7,"URGENTE","NORMAL"))) -> NORMAL
B51: SU115882 | C51: JUEGO PERFIL TAPA MOTOR | D51: 3 | E51: UND | F51: 0 | G51: 3 | H51: 220000 | I51: TORNOHIMEC SAS | K51: CRISTHIAN BENITEZ | L51: 80130020 | M51: 46113 | N51: 46113 | O51: 125400 | P51: =IFERROR(G51*H51,0) -> 660000 | Q51: =IFERROR(IF(N51="","",MAX(TODAY()-N51,0)),0) -> 6 | R51: =IF(B51="","",IF(G51=0,"COMPLETO",IF(G51<=D51*0.1,"CASI COMPLETO","PENDIENTE"))) -> PENDIENTE | S51: =IF(B51="","",IFERROR(F51/D51,0)) -> 0 | T51: =IF(B51="","",IF(Q51>30,"CRITICO",IF(Q51>7,"URGENTE","NORMAL"))) -> NORMAL
B52: SU115921 | C52: LAMINA GALVANIZADA CALIBRE 14 1,22*2,44 | D52: 1 | E52: UND | F52: 0 | G52: 1 | H52: 340000 | I52: TORNOHIMEC SAS | K52: CRISTHIAN BENITEZ | L52: 80130298 | M52: 46119 | N52: 46113 | O52: 64600 | P52: =IFERROR(G52*H52,0) -> 340000 | Q52: =IFERROR(IF(N52="","",MAX(TODAY()-N52,0)),0) -> 6 | R52: =IF(B52="","",IF(G52=0,"COMPLETO",IF(G52<=D52*0.1,"CASI COMPLETO","PENDIENTE"))) -> PENDIENTE | S52: =IF(B52="","",IFERROR(F52/D52,0)) -> 0 | T52: =IF(B52="","",IF(Q52>30,"CRITICO",IF(Q52>7,"URGENTE","NORMAL"))) -> NORMAL
B53: SU115929 | C53: BRAZO LIMPIAPARABRISAS | D53: 1 | E53: UND | F53: 0 | G53: 1 | H53: 100000 | I53: TORNOHIMEC SAS | K53: CHARLY HUERTAS | L53: 80110014-R | M53: 46122 | N53: 46111 | O53: 19000 | P53: =IFERROR(G53*H53,0) -> 100000 | Q53: =IFERROR(IF(N53="","",MAX(TODAY()-N53,0)),0) -> 8 | R53: =IF(B53="","",IF(G53=0,"COMPLETO",IF(G53<=D53*0.1,"CASI COMPLETO","PENDIENTE"))) -> PENDIENTE | S53: =IF(B53="","",IFERROR(F53/D53,0)) -> 0 | T53: =IF(B53="","",IF(Q53>30,"CRITICO",IF(Q53>7,"URGENTE","NORMAL"))) -> URGENTE
B54: SU115950 | C54: CASQUILLO | D54: 1 | E54: UND | F54: 0 | G54: 1 | H54: 30000 | I54: TORNOHIMEC SAS | K54: CRISTHIAN BENITEZ | L54: 21100014-R | M54: 46122 | N54: 46107 | O54: 5700 | P54: =IFERROR(G54*H54,0) -> 30000 | Q54: =IFERROR(IF(N54="","",MAX(TODAY()-N54,0)),0) -> 12 | R54: =IF(B54="","",IF(G54=0,"COMPLETO",IF(G54<=D54*0.1,"CASI COMPLETO","PENDIENTE"))) -> PENDIENTE | S54: =IF(B54="","",IFERROR(F54/D54,0)) -> 0 | T54: =IF(B54="","",IF(Q54>30,"CRITICO",IF(Q54>7,"URGENTE","NORMAL"))) -> URGENTE
B55: SU111857 | C55: FUELLE NEUMATICO TRASERO | D55: 612 | E55: UND | F55: 502 | G55: 110 | H55: 210000 | I55: TC IMPORTACIONES S.A.S | J55: 954090 | K55: CRISTHIAN BENITEZ | L55: 7260105 | M55: 46037 | N55: 45709 | O55: 24418800 | P55: =IFERROR(G55*H55,0) -> 23100000 | Q55: =IFERROR(IF(N55="","",MAX(TODAY()-N55,0)),0) -> 410 | R55: =IF(B55="","",IF(G55=0,"COMPLETO",IF(G55<=D55*0.1,"CASI COMPLETO","PENDIENTE"))) -> PENDIENTE | S55: =IF(B55="","",IFERROR(F55/D55,0)) -> 0.82026144 | T55: =IF(B55="","",IF(Q55>30,"CRITICO",IF(Q55>7,"URGENTE","NORMAL"))) -> CRITICO
B56: SU111857 | C56: FUELLE NEUMATICO EJE DE REMOLQUE | D56: 500 | E56: UND | F56: 450 | G56: 50 | H56: 173000 | I56: TC IMPORTACIONES S.A.S | J56: 954091 | K56: CRISTHIAN BENITEZ | L56: 7260108 | M56: 46037 | N56: 45709 | O56: 16435000 | P56: =IFERROR(G56*H56,0) -> 8650000 | Q56: =IFERROR(IF(N56="","",MAX(TODAY()-N56,0)),0) -> 410 | R56: =IF(B56="","",IF(G56=0,"COMPLETO",IF(G56<=D56*0.1,"CASI COMPLETO","PENDIENTE"))) -> CASI COMPLETO | S56: =IF(B56="","",IFERROR(F56/D56,0)) -> 0.9 | T56: =IF(B56="","",IF(Q56>30,"CRITICO",IF(Q56>7,"URGENTE","NORMAL"))) -> CRITICO
B57: SU111857 | C57: FUELLE NEUMATICO DELANTERO | D57: 260 | E57: UND | F57: 202 | G57: 58 | H57: 580000 | I57: TC IMPORTACIONES S.A.S | J57: 954089 | K57: CRISTHIAN BENITEZ | L57: 7260200 | M57: 46037 | N57: 45709 | O57: 28652000 | P57: =IFERROR(G57*H57,0) -> 33640000 | Q57: =IFERROR(IF(N57="","",MAX(TODAY()-N57,0)),0) -> 410 | R57: =IF(B57="","",IF(G57=0,"COMPLETO",IF(G57<=D57*0.1,"CASI COMPLETO","PENDIENTE"))) -> PENDIENTE | S57: =IF(B57="","",IFERROR(F57/D57,0)) -> 0.77692308 | T57: =IF(B57="","",IF(Q57>30,"CRITICO",IF(Q57>7,"URGENTE","NORMAL"))) -> CRITICO
B58: SU115560 | C58: CANTONERA PUERTA DE SERVICIO IZQUIERDA | D58: 3 | E58: UND | F58: 0 | G58: 3 | H58: 28487 | I58: SUPERPOLO S.A.S | J58: 11431971 | K58: CRISTHIAN BENITEZ | L58: 80110264 | M58: 46079 | N58: 46072 | O58: 16237.59 | P58: =IFERROR(G58*H58,0) -> 85461 | Q58: =IFERROR(IF(N58="","",MAX(TODAY()-N58,0)),0) -> 47 | R58: =IF(B58="","",IF(G58=0,"COMPLETO",IF(G58<=D58*0.1,"CASI COMPLETO","PENDIENTE"))) -> PENDIENTE | S58: =IF(B58="","",IFERROR(F58/D58,0)) -> 0 | T58: =IF(B58="","",IF(Q58>30,"CRITICO",IF(Q58>7,"URGENTE","NORMAL"))) -> CRITICO
B59: SU115924 | C59: BOOSTER DE PUERTA DE SERVICIO | D59: 1 | E59: UND | F59: 0 | G59: 1 | H59: 321023.9 | I59: SUPERPOLO S.A.S | J59: 26246687 | K59: CRISTHIAN BENITEZ | L59: 80110118 | M59: 46121 | N59: 46113 | O59: 60994.54 | P59: =IFERROR(G59*H59,0) -> 321023.9 | Q59: =IFERROR(IF(N59="","",MAX(TODAY()-N59,0)),0) -> 6 | R59: =IF(B59="","",IF(G59=0,"COMPLETO",IF(G59<=D59*0.1,"CASI COMPLETO","PENDIENTE"))) -> PENDIENTE | S59: =IF(B59="","",IFERROR(F59/D59,0)) -> 0 | T59: =IF(B59="","",IF(Q59>30,"CRITICO",IF(Q59>7,"URGENTE","NORMAL"))) -> NORMAL
B60: SU114738 | C60: TORNILLO AVELLANADO M8*1" | D60: 600 | E60: UND | F60: 0 | G60: 600 | H60: 40 | I60: SUMILOGISTICA S.A.S. | J60: 1495 | K60: CRISTHIAN BENITEZ | L60: 80110133 | M60: 45992 | N60: 45992 | O60: 4560 | P60: =IFERROR(G60*H60,0) -> 24000 | Q60: =IFERROR(IF(N60="","",MAX(TODAY()-N60,0)),0) -> 127 | R60: =IF(B60="","",IF(G60=0,"COMPLETO",IF(G60<=D60*0.1,"CASI COMPLETO","PENDIENTE"))) -> PENDIENTE | S60: =IF(B60="","",IFERROR(F60/D60,0)) -> 0 | T60: =IF(B60="","",IF(Q60>30,"CRITICO",IF(Q60>7,"URGENTE","NORMAL"))) -> CRITICO
B61: SU115064 | C61: POLIURETANO AMARILLO PASAMANOS | D61: 16000 | E61: GR | F61: 8000 | G61: 8000 | H61: 72.19 | I61: SUMILOGISTICA S.A.S. | J61: 2491 | K61: CRISTHIAN BENITEZ | L61: 801200119-G | M61: 46265 | N61: 46142 | O61: 219457.6 | P61: =IFERROR(G61*H61,0) -> 577520 | Q61: =IFERROR(IF(N61="","",MAX(TODAY()-N61,0)),0) -> 0 | R61: =IF(B61="","",IF(G61=0,"COMPLETO",IF(G61<=D61*0.1,"CASI COMPLETO","PENDIENTE"))) -> PENDIENTE | S61: =IF(B61="","",IFERROR(F61/D61,0)) -> 0.5 | T61: =IF(B61="","",IF(Q61>30,"CRITICO",IF(Q61>7,"URGENTE","NORMAL"))) -> NORMAL
B62: SU115064 | C62: POLIURETANO GRIS CLARO INTERIORES | D62: 43200 | E62: GR | F62: 32400 | G62: 10800 | H62: 87.15 | I62: SUMILOGISTICA S.A.S. | J62: 2490 | K62: CRISTHIAN BENITEZ | L62: 801200129 | M62: 46265 | N62: 46142 | O62: 715327.2 | P62: =IFERROR(G62*H62,0) -> 941220 | Q62: =IFERROR(IF(N62="","",MAX(TODAY()-N62,0)),0) -> 0 | R62: =IF(B62="","",IF(G62=0,"COMPLETO",IF(G62<=D62*0.1,"CASI COMPLETO","PENDIENTE"))) -> PENDIENTE | S62: =IF(B62="","",IFERROR(F62/D62,0)) -> 0.75 | T62: =IF(B62="","",IF(Q62>30,"CRITICO",IF(Q62>7,"URGENTE","NORMAL"))) -> NORMAL
B63: SU115064 | C63: CINTA 3M DE ENMASCARADO 2" | D63: 450 | E63: RLL | F63: 300 | G63: 150 | H63: 15855 | I63: SUMILOGISTICA S.A.S. | J63: 88 | K63: CRISTHIAN BENITEZ | L63: 80120055 | M63: 46265 | N63: 46142 | O63: 1355603 | P63: =IFERROR(G63*H63,0) -> 2378250 | Q63: =IFERROR(IF(N63="","",MAX(TODAY()-N63,0)),0) -> 0 | R63: =IF(B63="","",IF(G63=0,"COMPLETO",IF(G63<=D63*0.1,"CASI COMPLETO","PENDIENTE"))) -> PENDIENTE | S63: =IF(B63="","",IFERROR(F63/D63,0)) -> 0.66666667 | T63: =IF(B63="","",IF(Q63>30,"CRITICO",IF(Q63>7,"URGENTE","NORMAL"))) -> NORMAL
B64: SU115064 | C64: PALATAL RESINA 5346 B 10003 | D64: 30 | E64: KG | F64: 12 | G64: 18 | H64: 19272 | I64: SUMILOGISTICA S.A.S. | J64: 194 | K64: CRISTHIAN BENITEZ | L64: 80120059 | M64: 46265 | N64: 46142 | O64: 109850.4 | P64: =IFERROR(G64*H64,0) -> 346896 | Q64: =IFERROR(IF(N64="","",MAX(TODAY()-N64,0)),0) -> 0 | R64: =IF(B64="","",IF(G64=0,"COMPLETO",IF(G64<=D64*0.1,"CASI COMPLETO","PENDIENTE"))) -> PENDIENTE | S64: =IF(B64="","",IFERROR(F64/D64,0)) -> 0.4 | T64: =IF(B64="","",IF(Q64>30,"CRITICO",IF(Q64>7,"URGENTE","NORMAL"))) -> NORMAL
B65: SU115064 | C65: ACTIVADOR POLIURETANO IW205 | D65: 97768 | E65: GR | F65: 48884 | G65: 48884 | H65: 121.8 | I65: SUMILOGISTICA S.A.S. | J65: 2494 | K65: CRISTHIAN BENITEZ | L65: 80120087-G | M65: 46265 | N65: 46142 | O65: 2262547 | P65: =IFERROR(G65*H65,0) -> 5954071.2 | Q65: =IFERROR(IF(N65="","",MAX(TODAY()-N65,0)),0) -> 0 | R65: =IF(B65="","",IF(G65=0,"COMPLETO",IF(G65<=D65*0.1,"CASI COMPLETO","PENDIENTE"))) -> PENDIENTE | S65: =IF(B65="","",IFERROR(F65/D65,0)) -> 0.5 | T65: =IF(B65="","",IF(Q65>30,"CRITICO",IF(Q65>7,"URGENTE","NORMAL"))) -> NORMAL
B66: SU115064 | C66: POLIURETANO ROJO TRANSMILENIO | D66: 213200 | E66: GR | F66: 186550 | G66: 26650 | H66: 159.6 | I66: SUMILOGISTICA S.A.S. | J66: 2492 | K66: CRISTHIAN BENITEZ | L66: 80120097-G | M66: 46265 | N66: 46142 | O66: 6465077 | P66: =IFERROR(G66*H66,0) -> 4253340 | Q66: =IFERROR(IF(N66="","",MAX(TODAY()-N66,0)),0) -> 0 | R66: =IF(B66="","",IF(G66=0,"COMPLETO",IF(G66<=D66*0.1,"CASI COMPLETO","PENDIENTE"))) -> PENDIENTE | S66: =IF(B66="","",IFERROR(F66/D66,0)) -> 0.875 | T66: =IF(B66="","",IF(Q66>30,"CRITICO",IF(Q66>7,"URGENTE","NORMAL"))) -> NORMAL
B67: SU115064 | C67: PAPEL KRAFT BEIGE 18"X230 | D67: 4 | E67: RLL | F67: 0 | G67: 4 | H67: 45957.45 | I67: SUMILOGISTICA S.A.S. | J67: 156 | K67: CRISTHIAN BENITEZ | L67: 80120112 | M67: 46265 | N67: 46142 | O67: 34927.66 | P67: =IFERROR(G67*H67,0) -> 183829.8 | Q67: =IFERROR(IF(N67="","",MAX(TODAY()-N67,0)),0) -> 0 | R67: =IF(B67="","",IF(G67=0,"COMPLETO",IF(G67<=D67*0.1,"CASI COMPLETO","PENDIENTE"))) -> PENDIENTE | S67: =IF(B67="","",IFERROR(F67/D67,0)) -> 0 | T67: =IF(B67="","",IF(Q67>30,"CRITICO",IF(Q67>7,"URGENTE","NORMAL"))) -> NORMAL
B68: SU115064 | C68: POLIETILENO DE 60CM A 1,20 | D68: 14000 | E68: M | F68: 7000 | G68: 7000 | H68: 148.05 | I68: SUMILOGISTICA S.A.S. | J68: 2511 | K68: CRISTHIAN BENITEZ | L68: 80130277 | M68: 46265 | N68: 46142 | O68: 393813 | P68: =IFERROR(G68*H68,0) -> 1036350 | Q68: =IFERROR(IF(N68="","",MAX(TODAY()-N68,0)),0) -> 0 | R68: =IF(B68="","",IF(G68=0,"COMPLETO",IF(G68<=D68*0.1,"CASI COMPLETO","PENDIENTE"))) -> PENDIENTE | S68: =IF(B68="","",IFERROR(F68/D68,0)) -> 0.5 | T68: =IF(B68="","",IF(Q68>30,"CRITICO",IF(Q68>7,"URGENTE","NORMAL"))) -> NORMAL
B69: SU115064 | C69: ESPATULA PLASTICA PLANA | D69: 160 | E69: UND | F69: 120 | G69: 40 | H69: 577.5 | I69: SUMILOGISTICA S.A.S. | J69: 107 | K69: CRISTHIAN BENITEZ | L69: 80120091 | M69: 46265 | N69: 46142 | O69: 17556 | P69: =IFERROR(G69*H69,0) -> 23100 | Q69: =IFERROR(IF(N69="","",MAX(TODAY()-N69,0)),0) -> 0 | R69: =IF(B69="","",IF(G69=0,"COMPLETO",IF(G69<=D69*0.1,"CASI COMPLETO","PENDIENTE"))) -> PENDIENTE | S69: =IF(B69="","",IFERROR(F69/D69,0)) -> 0.75 | T69: =IF(B69="","",IF(Q69>30,"CRITICO",IF(Q69>7,"URGENTE","NORMAL"))) -> NORMAL
B70: SU115070 | C70: PUNTAS P3 | D70: 50 | E70: UND | F70: 34 | G70: 16 | H70: 4347 | I70: SUMILOGISTICA S.A.S. | J70: 875 | K70: CRISTHIAN BENITEZ | L70: 80110080 | M70: 46021 | N70: 46021 | O70: 41296.5 | P70: =IFERROR(G70*H70,0) -> 69552 | Q70: =IFERROR(IF(N70="","",MAX(TODAY()-N70,0)),0) -> 98 | R70: =IF(B70="","",IF(G70=0,"COMPLETO",IF(G70<=D70*0.1,"CASI COMPLETO","PENDIENTE"))) -> PENDIENTE | S70: =IF(B70="","",IFERROR(F70/D70,0)) -> 0.68 | T70: =IF(B70="","",IF(Q70>30,"CRITICO",IF(Q70>7,"URGENTE","NORMAL"))) -> CRITICO
B71: SU115136 | C71: DISCO DE ASPIRACIÓN 3M LIMPIA HK 6" P150 | D71: 1400 | E71: UND | F71: 1050 | G71: 350 | H71: 3255 | I71: SUMILOGISTICA S.A.S. | J71: 501 | K71: CRISTHIAN BENITEZ | L71: 3860302 | M71: 46142 | N71: 46142 | O71: 865830 | P71: =IFERROR(G71*H71,0) -> 1139250 | Q71: =IFERROR(IF(N71="","",MAX(TODAY()-N71,0)),0) -> 0 | R71: =IF(B71="","",IF(G71=0,"COMPLETO",IF(G71<=D71*0.1,"CASI COMPLETO","PENDIENTE"))) -> PENDIENTE | S71: =IF(B71="","",IFERROR(F71/D71,0)) -> 0.75 | T71: =IF(B71="","",IF(Q71>30,"CRITICO",IF(Q71>7,"URGENTE","NORMAL"))) -> NORMAL
B72: SU115136 | C72: DISCO DE ASPIRACIÓN 3M LIMPIA HK 6" P220 | D72: 1400 | E72: UND | F72: 1050 | G72: 350 | H72: 3255 | I72: SUMILOGISTICA S.A.S. | J72: 96 | K72: CRISTHIAN BENITEZ | L72: 3860303 | M72: 46142 | N72: 46142 | O72: 865830 | P72: =IFERROR(G72*H72,0) -> 1139250 | Q72: =IFERROR(IF(N72="","",MAX(TODAY()-N72,0)),0) -> 0 | R72: =IF(B72="","",IF(G72=0,"COMPLETO",IF(G72<=D72*0.1,"CASI COMPLETO","PENDIENTE"))) -> PENDIENTE | S72: =IF(B72="","",IFERROR(F72/D72,0)) -> 0.75 | T72: =IF(B72="","",IF(Q72>30,"CRITICO",IF(Q72>7,"URGENTE","NORMAL"))) -> NORMAL
B73: SU115136 | C73: ARANDELA PLANA 3/16" ZINCADA | D73: 1200 | E73: UND | F73: 600 | G73: 600 | H73: 23 | I73: SUMILOGISTICA S.A.S. | J73: 734 | K73: CRISTHIAN BENITEZ | L73: 80110010 | M73: 46142 | N73: 46142 | O73: 5244 | P73: =IFERROR(G73*H73,0) -> 13800 | Q73: =IFERROR(IF(N73="","",MAX(TODAY()-N73,0)),0) -> 0 | R73: =IF(B73="","",IF(G73=0,"COMPLETO",IF(G73<=D73*0.1,"CASI COMPLETO","PENDIENTE"))) -> PENDIENTE | S73: =IF(B73="","",IFERROR(F73/D73,0)) -> 0.5 | T73: =IF(B73="","",IF(Q73>30,"CRITICO",IF(Q73>7,"URGENTE","NORMAL"))) -> NORMAL
B74: SU115136 | C74: CINTA AISLANTE NEGRA | D74: 80 | E74: RLL | F74: 40 | G74: 40 | H74: 5292 | I74: SUMILOGISTICA S.A.S. | J74: 325 | K74: CRISTHIAN BENITEZ | L74: 80110025 | M74: 46142 | N74: 46142 | O74: 80438.4 | P74: =IFERROR(G74*H74,0) -> 211680 | Q74: =IFERROR(IF(N74="","",MAX(TODAY()-N74,0)),0) -> 0 | R74: =IF(B74="","",IF(G74=0,"COMPLETO",IF(G74<=D74*0.1,"CASI COMPLETO","PENDIENTE"))) -> PENDIENTE | S74: =IF(B74="","",IFERROR(F74/D74,0)) -> 0.5 | T74: =IF(B74="","",IF(Q74>30,"CRITICO",IF(Q74>7,"URGENTE","NORMAL"))) -> NORMAL
B75: SU115136 | C75: CINTA INSONORIZANTE DE 25 MM | D75: 400 | E75: M | F75: 100 | G75: 300 | H75: 4692 | I75: SUMILOGISTICA S.A.S. | J75: 2462 | K75: CRISTHIAN BENITEZ | L75: 80110028 | M75: 46142 | N75: 46142 | O75: 356592 | P75: =IFERROR(G75*H75,0) -> 1407600 | Q75: =IFERROR(IF(N75="","",MAX(TODAY()-N75,0)),0) -> 0 | R75: =IF(B75="","",IF(G75=0,"COMPLETO",IF(G75<=D75*0.1,"CASI COMPLETO","PENDIENTE"))) -> PENDIENTE | S75: =IF(B75="","",IFERROR(F75/D75,0)) -> 0.25 | T75: =IF(B75="","",IF(Q75>30,"CRITICO",IF(Q75>7,"URGENTE","NORMAL"))) -> NORMAL
B76: SU115136 | C76: BROCHA 2" | D76: 135 | E76: UND | F76: 45 | G76: 90 | H76: 3956 | I76: SUMILOGISTICA S.A.S. | J76: 354 | K76: CRISTHIAN BENITEZ | L76: 80110114 | M76: 46142 | N76: 46142 | O76: 101471.4 | P76: =IFERROR(G76*H76,0) -> 356040 | Q76: =IFERROR(IF(N76="","",MAX(TODAY()-N76,0)),0) -> 0 | R76: =IF(B76="","",IF(G76=0,"COMPLETO",IF(G76<=D76*0.1,"CASI COMPLETO","PENDIENTE"))) -> PENDIENTE | S76: =IF(B76="","",IFERROR(F76/D76,0)) -> 0.33333333 | T76: =IF(B76="","",IF(Q76>30,"CRITICO",IF(Q76>7,"URGENTE","NORMAL"))) -> NORMAL
B77: SU115136 | C77: TORNILLO HEXAGONAL 3/8"*1" | D77: 1200 | E77: UND | F77: 1000 | G77: 200 | H77: 473 | I77: SUMILOGISTICA S.A.S. | J77: 2432 | K77: CRISTHIAN BENITEZ | L77: 80110130 | M77: 46142 | N77: 46142 | O77: 107844 | P77: =IFERROR(G77*H77,0) -> 94600 | Q77: =IFERROR(IF(N77="","",MAX(TODAY()-N77,0)),0) -> 0 | R77: =IF(B77="","",IF(G77=0,"COMPLETO",IF(G77<=D77*0.1,"CASI COMPLETO","PENDIENTE"))) -> PENDIENTE | S77: =IF(B77="","",IFERROR(F77/D77,0)) -> 0.83333333 | T77: =IF(B77="","",IF(Q77>30,"CRITICO",IF(Q77>7,"URGENTE","NORMAL"))) -> NORMAL
B78: SU115136 | C78: TORNILLO AVELLANADO M8*1" | D78: 2400 | E78: UND | F78: 1200 | G78: 1200 | H78: 40 | I78: SUMILOGISTICA S.A.S. | J78: 1495 | K78: CRISTHIAN BENITEZ | L78: 80110133 | M78: 46142 | N78: 46142 | O78: 18240 | P78: =IFERROR(G78*H78,0) -> 48000 | Q78: =IFERROR(IF(N78="","",MAX(TODAY()-N78,0)),0) -> 0 | R78: =IF(B78="","",IF(G78=0,"COMPLETO",IF(G78<=D78*0.1,"CASI COMPLETO","PENDIENTE"))) -> PENDIENTE | S78: =IF(B78="","",IFERROR(F78/D78,0)) -> 0.5 | T78: =IF(B78="","",IF(Q78>30,"CRITICO",IF(Q78>7,"URGENTE","NORMAL"))) -> NORMAL
... B107: SU115857 | C107: RACOR UNION RECTO 8 MM PLASTICO | D107: 30 | E107: UND | F107: 0 | G107: 30 | H107: 15988 | I107: SUMILOGISTICA S.A.S. | J107: 2404 | K107: CRISTHIAN BENITEZ | L107: 80140028 | M107: 46119 | N107: 46113 | O107: 91131.6 | P107: =IFERROR(G107*H107,0) -> 479640 | Q107: =IFERROR(IF(N107="","",MAX(TODAY()-N107,0)),0) -> 6 | R107: =IF(B107="","",IF(G107=0,"COMPLETO",IF(G107<=D107*0.1,"CASI COMPLETO","PENDIENTE"))) -> PENDIENTE | S107: =IF(B107="","",IFERROR(F107/D107,0)) -> 0 | T107: =IF(B107="","",IF(Q107>30,"CRITICO",IF(Q107>7,"URGENTE","NORMAL"))) -> NORMAL
B108: SU115857 | C108: PEGANTE BOXER MEGASPRAY CANECA X 5 GALONES | D108: 2 | E108: UND | F108: 0 | G108: 2 | H108: 335986 | I108: SUMILOGISTICA S.A.S. | J108: LCSPE0158 | K108: CRISTHIAN BENITEZ | L108: 80130009 | M108: 46119 | N108: 46113 | O108: 127674.7 | P108: =IFERROR(G108*H108,0) -> 671972 | Q108: =IFERROR(IF(N108="","",MAX(TODAY()-N108,0)),0) -> 6 | R108: =IF(B108="","",IF(G108=0,"COMPLETO",IF(G108<=D108*0.1,"CASI COMPLETO","PENDIENTE"))) -> PENDIENTE | S108: =IF(B108="","",IFERROR(F108/D108,0)) -> 0 | T108: =IF(B108="","",IF(Q108>30,"CRITICO",IF(Q108>7,"URGENTE","NORMAL"))) -> NORMAL
B109: SU115857 | C109: PASTA MONTAJE/DESMONTAJE 3.63 KL | D109: 3 | E109: UND | F109: 0 | G109: 3 | H109: 63000 | I109: SUMILOGISTICA S.A.S. | J109: 1320 | K109: CRISTHIAN BENITEZ | L109: 77101022 | M109: 46119 | N109: 46113 | O109: 35910 | P109: =IFERROR(G109*H109,0) -> 189000 | Q109: =IFERROR(IF(N109="","",MAX(TODAY()-N109,0)),0) -> 6 | R109: =IF(B109="","",IF(G109=0,"COMPLETO",IF(G109<=D109*0.1,"CASI COMPLETO","PENDIENTE"))) -> PENDIENTE | S109: =IF(B109="","",IFERROR(F109/D109,0)) -> 0 | T109: =IF(B109="","",IF(Q109>30,"CRITICO",IF(Q109>7,"URGENTE","NORMAL"))) -> NORMAL
B110: SU115913 | C110: MOTOR DE ARRANQUE | D110: 1 | E110: UND | F110: 0 | G110: 1 | H110: 578867 | I110: SUMILOGISTICA S.A.S. | J110: 13210013-R | K110: CHARLY HUERTAS | L110: 13210013-R | M110: 46122 | N110: 46111 | O110: 109984.7 | P110: =IFERROR(G110*H110,0) -> 578867 | Q110: =IFERROR(IF(N110="","",MAX(TODAY()-N110,0)),0) -> 8 | R110: =IF(B110="","",IF(G110=0,"COMPLETO",IF(G110<=D110*0.1,"CASI COMPLETO","PENDIENTE"))) -> PENDIENTE | S110: =IF(B110="","",IFERROR(F110/D110,0)) -> 0 | T110: =IF(B110="","",IF(Q110>30,"CRITICO",IF(Q110>7,"URGENTE","NORMAL"))) -> URGENTE
B111: SU115913 | C111: MOTOR DE ARRANQUE | D111: 1 | E111: UND | F111: 0 | G111: 1 | H111: 403664 | I111: SUMILOGISTICA S.A.S. | J111: 13210013-R | K111: CHARLY HUERTAS | L111: 13210013-R | M111: 46122 | N111: 46111 | O111: 76696.16 | P111: =IFERROR(G111*H111,0) -> 403664 | Q111: =IFERROR(IF(N111="","",MAX(TODAY()-N111,0)),0) -> 8 | R111: =IF(B111="","",IF(G111=0,"COMPLETO",IF(G111<=D111*0.1,"CASI COMPLETO","PENDIENTE"))) -> PENDIENTE | S111: =IF(B111="","",IFERROR(F111/D111,0)) -> 0 | T111: =IF(B111="","",IF(Q111>30,"CRITICO",IF(Q111>7,"URGENTE","NORMAL"))) -> URGENTE
B112: SU115913 | C112: CUERPO DE FRENO (Caliper) DERECHO | D112: 1 | E112: UND | F112: 0 | G112: 1 | H112: 951766 | I112: SUMILOGISTICA S.A.S. | K112: CHARLY HUERTAS | L112: 15100005-R | M112: 46122 | N112: 46111 | O112: 180835.5 | P112: =IFERROR(G112*H112,0) -> 951766 | Q112: =IFERROR(IF(N112="","",MAX(TODAY()-N112,0)),0) -> 8 | R112: =IF(B112="","",IF(G112=0,"COMPLETO",IF(G112<=D112*0.1,"CASI COMPLETO","PENDIENTE"))) -> PENDIENTE | S112: =IF(B112="","",IFERROR(F112/D112,0)) -> 0 | T112: =IF(B112="","",IF(Q112>30,"CRITICO",IF(Q112>7,"URGENTE","NORMAL"))) -> URGENTE
B113: SU115913 | C113: CUERPO DE FRENO (Caliper) IZQUIERDO | D113: 1 | E113: UND | F113: 0 | G113: 1 | H113: 951766 | I113: SUMILOGISTICA S.A.S. | K113: CHARLY HUERTAS | L113: 15100006-R | M113: 46122 | N113: 46111 | O113: 180835.5 | P113: =IFERROR(G113*H113,0) -> 951766 | Q113: =IFERROR(IF(N113="","",MAX(TODAY()-N113,0)),0) -> 8 | R113: =IF(B113="","",IF(G113=0,"COMPLETO",IF(G113<=D113*0.1,"CASI COMPLETO","PENDIENTE"))) -> PENDIENTE | S113: =IF(B113="","",IFERROR(F113/D113,0)) -> 0 | T113: =IF(B113="","",IF(Q113>30,"CRITICO",IF(Q113>7,"URGENTE","NORMAL"))) -> URGENTE
B114: SU115933 | C114: CUERPO DE FRENO (Caliper) IZQUIERDO | D114: 2 | E114: UND | F114: 0 | G114: 2 | H114: 768916 | I114: SUMILOGISTICA S.A.S. | K114: CHARLY HUERTAS | L114: 15100006-R | M114: 46122 | N114: 46112 | O114: 292188.1 | P114: =IFERROR(G114*H114,0) -> 1537832 | Q114: =IFERROR(IF(N114="","",MAX(TODAY()-N114,0)),0) -> 7 | R114: =IF(B114="","",IF(G114=0,"COMPLETO",IF(G114<=D114*0.1,"CASI COMPLETO","PENDIENTE"))) -> PENDIENTE | S114: =IF(B114="","",IFERROR(F114/D114,0)) -> 0 | T114: =IF(B114="","",IF(Q114>30,"CRITICO",IF(Q114>7,"URGENTE","NORMAL"))) -> NORMAL
B115: SU115946 | C115: MOTOR DE ARRANQUE | D115: 2 | E115: UND | F115: 0 | G115: 2 | H115: 403664 | I115: SUMILOGISTICA S.A.S. | J115: 13210013-R | K115: CRISTHIAN BENITEZ | L115: 13210013-R | M115: 46118 | N115: 46118 | O115: 153392.3 | P115: =IFERROR(G115*H115,0) -> 807328 | Q115: =IFERROR(IF(N115="","",MAX(TODAY()-N115,0)),0) -> 1 | R115: =IF(B115="","",IF(G115=0,"COMPLETO",IF(G115<=D115*0.1,"CASI COMPLETO","PENDIENTE"))) -> PENDIENTE | S115: =IF(B115="","",IFERROR(F115/D115,0)) -> 0 | T115: =IF(B115="","",IF(Q115>30,"CRITICO",IF(Q115>7,"URGENTE","NORMAL"))) -> NORMAL
B116: SU115946 | C116: EXTRACTOR DE TECHO | D116: 12 | E116: UND | F116: 0 | G116: 12 | H116: 48849 | I116: SUMILOGISTICA S.A.S. | J116: 101330024 | K116: CRISTHIAN BENITEZ | L116: 801702001-R | M116: 46118 | N116: 46118 | O116: 111375.7 | P116: =IFERROR(G116*H116,0) -> 586188 | Q116: =IFERROR(IF(N116="","",MAX(TODAY()-N116,0)),0) -> 1 | R116: =IF(B116="","",IF(G116=0,"COMPLETO",IF(G116<=D116*0.1,"CASI COMPLETO","PENDIENTE"))) -> PENDIENTE | S116: =IF(B116="","",IFERROR(F116/D116,0)) -> 0 | T116: =IF(B116="","",IF(Q116>30,"CRITICO",IF(Q116>7,"URGENTE","NORMAL"))) -> NORMAL
B117: SU115947 | C117: MOTOR DE ARRANQUE | D117: 1 | E117: UND | F117: 0 | G117: 1 | H117: 403664 | I117: SUMILOGISTICA S.A.S. | J117: 13210013-R | K117: CRISTHIAN BENITEZ | L117: 13210013-R | M117: 46118 | N117: 46118 | O117: 76696.16 | P117: =IFERROR(G117*H117,0) -> 403664 | Q117: =IFERROR(IF(N117="","",MAX(TODAY()-N117,0)),0) -> 1 | R117: =IF(B117="","",IF(G117=0,"COMPLETO",IF(G117<=D117*0.1,"CASI COMPLETO","PENDIENTE"))) -> PENDIENTE | S117: =IF(B117="","",IFERROR(F117/D117,0)) -> 0 | T117: =IF(B117="","",IF(Q117>30,"CRITICO",IF(Q117>7,"URGENTE","NORMAL"))) -> NORMAL
B118: SU115947 | C118: MOTOR DE ARRANQUE | D118: 1 | E118: UND | F118: 0 | G118: 1 | H118: 379859 | I118: SUMILOGISTICA S.A.S. | J118: 13210013-R | K118: CRISTHIAN BENITEZ | L118: 13210013-R | M118: 46118 | N118: 46118 | O118: 72173.21 | P118: =IFERROR(G118*H118,0) -> 379859 | Q118: =IFERROR(IF(N118="","",MAX(TODAY()-N118,0)),0) -> 1 | R118: =IF(B118="","",IF(G118=0,"COMPLETO",IF(G118<=D118*0.1,"CASI COMPLETO","PENDIENTE"))) -> PENDIENTE | S118: =IF(B118="","",IFERROR(F118/D118,0)) -> 0 | T118: =IF(B118="","",IF(Q118>30,"CRITICO",IF(Q118>7,"URGENTE","NORMAL"))) -> NORMAL
B119: SU115947 | C119: BARRA TENSORA SUPERIOR | D119: 3 | E119: UND | F119: 0 | G119: 3 | H119: 801884 | I119: SUMILOGISTICA S.A.S. | K119: CRISTHIAN BENITEZ | L119: 6500108-R | M119: 46118 | N119: 46118 | O119: 457073.9 | P119: =IFERROR(G119*H119,0) -> 2405652 | Q119: =IFERROR(IF(N119="","",MAX(TODAY()-N119,0)),0) -> 1 | R119: =IF(B119="","",IF(G119=0,"COMPLETO",IF(G119<=D119*0.1,"CASI COMPLETO","PENDIENTE"))) -> PENDIENTE | S119: =IF(B119="","",IFERROR(F119/D119,0)) -> 0 | T119: =IF(B119="","",IF(Q119>30,"CRITICO",IF(Q119>7,"URGENTE","NORMAL"))) -> NORMAL
B120: SU115947 | C120: EXTRACTOR DE TECHO | D120: 1 | E120: UND | F120: 0 | G120: 1 | H120: 48849 | I120: SUMILOGISTICA S.A.S. | J120: 101330024 | K120: CRISTHIAN BENITEZ | L120: 801702001-R | M120: 46118 | N120: 46118 | O120: 9281.31 | P120: =IFERROR(G120*H120,0) -> 48849 | Q120: =IFERROR(IF(N120="","",MAX(TODAY()-N120,0)),0) -> 1 | R120: =IF(B120="","",IF(G120=0,"COMPLETO",IF(G120<=D120*0.1,"CASI COMPLETO","PENDIENTE"))) -> PENDIENTE | S120: =IF(B120="","",IFERROR(F120/D120,0)) -> 0 | T120: =IF(B120="","",IF(Q120>30,"CRITICO",IF(Q120>7,"URGENTE","NORMAL"))) -> NORMAL
B121: SU115554 | C121: SOPORTE PASAMANOS | D121: 52 | E121: UND | F121: 14 | G121: 38 | H121: 4500 | I121: SOLUCIONES INTEGRALES PARA CARROCERIAS SOCIEDAD POR ACCIONES SIMPLIFICADA | K121: CRISTHIAN BENITEZ | L121: 80110097 | M121: 46085 | N121: 46085 | O121: 44460 | P121: =IFERROR(G121*H121,0) -> 171000 | Q121: =IFERROR(IF(N121="","",MAX(TODAY()-N121,0)),0) -> 34 | R121: =IF(B121="","",IF(G121=0,"COMPLETO",IF(G121<=D121*0.1,"CASI COMPLETO","PENDIENTE"))) -> PENDIENTE | S121: =IF(B121="","",IFERROR(F121/D121,0)) -> 0.26923077 | T121: =IF(B121="","",IF(Q121>30,"CRITICO",IF(Q121>7,"URGENTE","NORMAL"))) -> CRITICO
B122: SU115554 | C122: TERMINAL MACHO 8 MM*6,3 MM | D122: 800 | E122: UND | F122: 0 | G122: 800 | H122: 127 | I122: SOLUCIONES INTEGRALES PARA CARROCERIAS SOCIEDAD POR ACCIONES SIMPLIFICADA | K122: CRISTHIAN BENITEZ | L122: 80150064 | M122: 46085 | N122: 46085 | O122: 19304 | P122: =IFERROR(G122*H122,0) -> 101600 | Q122: =IFERROR(IF(N122="","",MAX(TODAY()-N122,0)),0) -> 34 | R122: =IF(B122="","",IF(G122=0,"COMPLETO",IF(G122<=D122*0.1,"CASI COMPLETO","PENDIENTE"))) -> PENDIENTE | S122: =IF(B122="","",IFERROR(F122/D122,0)) -> 0 | T122: =IF(B122="","",IF(Q122>30,"CRITICO",IF(Q122>7,"URGENTE","NORMAL"))) -> CRITICO
B123: SU115880 | C123: UNION PLASTICA | D123: 110 | E123: UND | F123: 95 | G123: 15 | H123: 2700 | I123: SOLUCIONES INTEGRALES PARA CARROCERIAS SOCIEDAD POR ACCIONES SIMPLIFICADA | K123: CRISTHIAN BENITEZ | L123: 80110242 | M123: 46113 | N123: 46113 | O123: 56430 | P123: =IFERROR(G123*H123,0) -> 40500 | Q123: =IFERROR(IF(N123="","",MAX(TODAY()-N123,0)),0) -> 6 | R123: =IF(B123="","",IF(G123=0,"COMPLETO",IF(G123<=D123*0.1,"CASI COMPLETO","PENDIENTE"))) -> PENDIENTE | S123: =IF(B123="","",IFERROR(F123/D123,0)) -> 0.86363636 | T123: =IF(B123="","",IF(Q123>30,"CRITICO",IF(Q123>7,"URGENTE","NORMAL"))) -> NORMAL
B124: SU115880 | C124: PERFIL DE ALUMINIO 3/4 (ANGULO RANURADO) | D124: 12 | E124: M | F124: 0 | G124: 12 | H124: 4500 | I124: SOLUCIONES INTEGRALES PARA CARROCERIAS SOCIEDAD POR ACCIONES SIMPLIFICADA | J124: SCV369 | K124: CRISTHIAN BENITEZ | L124: 80110284 | M124: 46113 | N124: 46113 | O124: 10260 | P124: =IFERROR(G124*H124,0) -> 54000 | Q124: =IFERROR(IF(N124="","",MAX(TODAY()-N124,0)),0) -> 6 | R124: =IF(B124="","",IF(G124=0,"COMPLETO",IF(G124<=D124*0.1,"CASI COMPLETO","PENDIENTE"))) -> PENDIENTE | S124: =IF(B124="","",IFERROR(F124/D124,0)) -> 0 | T124: =IF(B124="","",IF(Q124>30,"CRITICO",IF(Q124>7,"URGENTE","NORMAL"))) -> NORMAL
B125: SU115880 | C125: BROCA ACERO RAPIDO HSS 013 7/32" | D125: 50 | E125: UND | F125: 26 | G125: 24 | H125: 3850 | I125: SOLUCIONES INTEGRALES PARA CARROCERIAS SOCIEDAD POR ACCIONES SIMPLIFICADA | K125: CRISTHIAN BENITEZ | L125: 80110301 | M125: 46113 | N125: 46113 | O125: 36575 | P125: =IFERROR(G125*H125,0) -> 92400 | Q125: =IFERROR(IF(N125="","",MAX(TODAY()-N125,0)),0) -> 6 | R125: =IF(B125="","",IF(G125=0,"COMPLETO",IF(G125<=D125*0.1,"CASI COMPLETO","PENDIENTE"))) -> PENDIENTE | S125: =IF(B125="","",IFERROR(F125/D125,0)) -> 0.52 | T125: =IF(B125="","",IF(Q125>30,"CRITICO",IF(Q125>7,"URGENTE","NORMAL"))) -> NORMAL
B126: SU115880 | C126: PRENSACABLE CILINDRICO (PERRO) 1/8 GALVANIZADO PARA GUAYA DE 1/16" | D126: 20 | E126: UND | F126: 0 | G126: 20 | H126: 2285 | I126: SOLUCIONES INTEGRALES PARA CARROCERIAS SOCIEDAD POR ACCIONES SIMPLIFICADA | J126: CB008 | K126: CRISTHIAN BENITEZ | L126: 80130246 | M126: 46113 | N126: 46113 | O126: 8683 | P126: =IFERROR(G126*H126,0) -> 45700 | Q126: =IFERROR(IF(N126="","",MAX(TODAY()-N126,0)),0) -> 6 | R126: =IF(B126="","",IF(G126=0,"COMPLETO",IF(G126<=D126*0.1,"CASI COMPLETO","PENDIENTE"))) -> PENDIENTE | S126: =IF(B126="","",IFERROR(F126/D126,0)) -> 0 | T126: =IF(B126="","",IF(Q126>30,"CRITICO",IF(Q126>7,"URGENTE","NORMAL"))) -> NORMAL
B127: SU115880 | C127: BUJES DE TEFLON PUERTAS | D127: 200 | E127: UND | F127: 50 | G127: 150 | H127: 14650 | I127: SOLUCIONES INTEGRALES PARA CARROCERIAS SOCIEDAD POR ACCIONES SIMPLIFICADA | K127: CRISTHIAN BENITEZ | L127: 80140049 | M127: 46113 | N127: 46113 | O127: 556700 | P127: =IFERROR(G127*H127,0) -> 2197500 | Q127: =IFERROR(IF(N127="","",MAX(TODAY()-N127,0)),0) -> 6 | R127: =IF(B127="","",IF(G127=0,"COMPLETO",IF(G127<=D127*0.1,"CASI COMPLETO","PENDIENTE"))) -> PENDIENTE | S127: =IF(B127="","",IFERROR(F127/D127,0)) -> 0.25 | T127: =IF(B127="","",IF(Q127>30,"CRITICO",IF(Q127>7,"URGENTE","NORMAL"))) -> NORMAL
B128: SU115880 | C128: ROTULA DE PUERTA DE EMERGENCIA | D128: 20 | E128: UND | F128: 1 | G128: 19 | H128: 26777 | I128: SOLUCIONES INTEGRALES PARA CARROCERIAS SOCIEDAD POR ACCIONES SIMPLIFICADA | J128: CTP1507 | K128: CRISTHIAN BENITEZ | L128: 80200058 | M128: 46113 | N128: 46113 | O128: 101752.6 | P128: =IFERROR(G128*H128,0) -> 508763 | Q128: =IFERROR(IF(N128="","",MAX(TODAY()-N128,0)),0) -> 6 | R128: =IF(B128="","",IF(G128=0,"COMPLETO",IF(G128<=D128*0.1,"CASI COMPLETO","PENDIENTE"))) -> PENDIENTE | S128: =IF(B128="","",IFERROR(F128/D128,0)) -> 0.05 | T128: =IF(B128="","",IF(Q128>30,"CRITICO",IF(Q128>7,"URGENTE","NORMAL"))) -> NORMAL
B129: SU115799 | C129: CABLE DE BATERIAS | D129: 2 | E129: UND | F129: 0 | G129: 2 | H129: 110000 | I129: SMIDT SUMINISTRO MANTENIMIENTO INDUSTRIAL DE TRANSPORTE SAS | K129: CRISTHIAN BENITEZ | L129: 30110006 | M129: 46101 | N129: 46099 | O129: 41800 | P129: =IFERROR(G129*H129,0) -> 220000 | Q129: =IFERROR(IF(N129="","",MAX(TODAY()-N129,0)),0) -> 20 | R129: =IF(B129="","",IF(G129=0,"COMPLETO",IF(G129<=D129*0.1,"CASI COMPLETO","PENDIENTE"))) -> PENDIENTE | S129: =IF(B129="","",IFERROR(F129/D129,0)) -> 0 | T129: =IF(B129="","",IF(Q129>30,"CRITICO",IF(Q129>7,"URGENTE","NORMAL"))) -> URGENTE
B130: SU115883 | C130: TERMINAL BARRILETE 1/0 *5/16 | D130: 2 | E130: UND | F130: 0 | G130: 2 | H130: 9000 | I130: SMIDT SUMINISTRO MANTENIMIENTO INDUSTRIAL DE TRANSPORTE SAS | K130: CRISTHIAN BENITEZ | L130: 30500080 | M130: 46113 | N130: 46113 | O130: 3420 | P130: =IFERROR(G130*H130,0) -> 18000 | Q130: =IFERROR(IF(N130="","",MAX(TODAY()-N130,0)),0) -> 6 | R130: =IF(B130="","",IF(G130=0,"COMPLETO",IF(G130<=D130*0.1,"CASI COMPLETO","PENDIENTE"))) -> PENDIENTE | S130: =IF(B130="","",IFERROR(F130/D130,0)) -> 0 | T130: =IF(B130="","",IF(Q130>30,"CRITICO",IF(Q130>7,"URGENTE","NORMAL"))) -> NORMAL
B131: SU115883 | C131: CORAZA DE 1/4" | D131: 50 | E131: M | F131: 0 | G131: 50 | H131: 800 | I131: SMIDT SUMINISTRO MANTENIMIENTO INDUSTRIAL DE TRANSPORTE SAS | K131: CRISTHIAN BENITEZ | L131: 80150075 | M131: 46113 | N131: 46113 | O131: 7600 | P131: =IFERROR(G131*H131,0) -> 40000 | Q131: =IFERROR(IF(N131="","",MAX(TODAY()-N131,0)),0) -> 6 | R131: =IF(B131="","",IF(G131=0,"COMPLETO",IF(G131<=D131*0.1,"CASI COMPLETO","PENDIENTE"))) -> PENDIENTE | S131: =IF(B131="","",IFERROR(F131/D131,0)) -> 0 | T131: =IF(B131="","",IF(Q131>30,"CRITICO",IF(Q131>7,"URGENTE","NORMAL"))) -> NORMAL
B132: SU115898 | C132: CABECERO SILLA OPERADOR | D132: 1 | E132: UND | F132: 0 | G132: 1 | H132: 50000 | I132: SMIDT SUMINISTRO MANTENIMIENTO INDUSTRIAL DE TRANSPORTE SAS | K132: CHARLY HUERTAS | L132: 80110297-R | M132: 46117 | N132: 46108 | O132: 9500 | P132: =IFERROR(G132*H132,0) -> 50000 | Q132: =IFERROR(IF(N132="","",MAX(TODAY()-N132,0)),0) -> 11 | R132: =IF(B132="","",IF(G132=0,"COMPLETO",IF(G132<=D132*0.1,"CASI COMPLETO","PENDIENTE"))) -> PENDIENTE | S132: =IF(B132="","",IFERROR(F132/D132,0)) -> 0 | T132: =IF(B132="","",IF(Q132>30,"CRITICO",IF(Q132>7,"URGENTE","NORMAL"))) -> URGENTE
B133: SU115898 | C133: COJIN ZONA DE DISCAPACITADOS | D133: 4 | E133: UND | F133: 3 | G133: 1 | H133: 65000 | I133: SMIDT SUMINISTRO MANTENIMIENTO INDUSTRIAL DE TRANSPORTE SAS | K133: CHARLY HUERTAS | L133: 8011141-R | M133: 46117 | N133: 46108 | O133: 49400 | P133: =IFERROR(G133*H133,0) -> 65000 | Q133: =IFERROR(IF(N133="","",MAX(TODAY()-N133,0)),0) -> 11 | R133: =IF(B133="","",IF(G133=0,"COMPLETO",IF(G133<=D133*0.1,"CASI COMPLETO","PENDIENTE"))) -> PENDIENTE | S133: =IF(B133="","",IFERROR(F133/D133,0)) -> 0.75 | T133: =IF(B133="","",IF(Q133>30,"CRITICO",IF(Q133>7,"URGENTE","NORMAL"))) -> URGENTE
B134: SU115948 | C134: LLANTA REPARADA RADIAL 295/80-R22.5 | D134: 1 | E134: UND | F134: 0 | G134: 1 | H134: 126050 | I134: SERVIREENCAUCHE BOGOTA S.A.S. | K134: CRISTHIAN BENITEZ | L134: 77101026-R | M134: 46119 | N134: 46118 | O134: 23949.5 | P134: =IFERROR(G134*H134,0) -> 126050 | Q134: =IFERROR(IF(N134="","",MAX(TODAY()-N134,0)),0) -> 1 | R134: =IF(B134="","",IF(G134=0,"COMPLETO",IF(G134<=D134*0.1,"CASI COMPLETO","PENDIENTE"))) -> PENDIENTE | S134: =IF(B134="","",IFERROR(F134/D134,0)) -> 0 | T134: =IF(B134="","",IF(Q134>30,"CRITICO",IF(Q134>7,"URGENTE","NORMAL"))) -> NORMAL
B135: SU115948 | C135: LLANTA REENCAUCHADA RADIAL 295/80-R22.5 | D135: 8 | E135: UND | F135: 0 | G135: 8 | H135: 434627 | I135: SERVIREENCAUCHE BOGOTA S.A.S. | J135: REEN295/80-R22.5 | K135: CRISTHIAN BENITEZ | L135: 77101027-R | M135: 46119 | N135: 46118 | O135: 660633 | P135: =IFERROR(G135*H135,0) -> 3477016 | Q135: =IFERROR(IF(N135="","",MAX(TODAY()-N135,0)),0) -> 1 | R135: =IF(B135="","",IF(G135=0,"COMPLETO",IF(G135<=D135*0.1,"CASI COMPLETO","PENDIENTE"))) -> PENDIENTE | S135: =IF(B135="","",IFERROR(F135/D135,0)) -> 0 | T135: =IF(B135="","",IF(Q135>30,"CRITICO",IF(Q135>7,"URGENTE","NORMAL"))) -> NORMAL
B136: SU115948 | C136: LLANTA REENCAUCHADA RADIAL 295/80-R22.5 | D136: 5 | E136: UND | F136: 0 | G136: 5 | H136: 568756 | I136: SERVIREENCAUCHE BOGOTA S.A.S. | J136: REEN295/80-R22.5 | K136: CRISTHIAN BENITEZ | L136: 77101027-R | M136: 46119 | N136: 46118 | O136: 540318.2 | P136: =IFERROR(G136*H136,0) -> 2843780 | Q136: =IFERROR(IF(N136="","",MAX(TODAY()-N136,0)),0) -> 1 | R136: =IF(B136="","",IF(G136=0,"COMPLETO",IF(G136<=D136*0.1,"CASI COMPLETO","PENDIENTE"))) -> PENDIENTE | S136: =IF(B136="","",IFERROR(F136/D136,0)) -> 0 | T136: =IF(B136="","",IF(Q136>30,"CRITICO",IF(Q136>7,"URGENTE","NORMAL"))) -> NORMAL
B137: SU115885 | C137: PROTECTOR PET PARA MULTIPLEX | D137: 50 | E137: UND | F137: 0 | G137: 50 | H137: 22000 | I137: REPUESTOS MANTENIMIENTO SERVICIOS SAS | J137: RMS001 | K137: CRISTHIAN BENITEZ | L137: 80200068 | M137: 46113 | N137: 46113 | O137: 209000 | P137: =IFERROR(G137*H137,0) -> 1100000 | Q137: =IFERROR(IF(N137="","",MAX(TODAY()-N137,0)),0) -> 6 | R137: =IF(B137="","",IF(G137=0,"COMPLETO",IF(G137<=D137*0.1,"CASI COMPLETO","PENDIENTE"))) -> PENDIENTE | S137: =IF(B137="","",IFERROR(F137/D137,0)) -> 0 | T137: =IF(B137="","",IF(Q137>30,"CRITICO",IF(Q137>7,"URGENTE","NORMAL"))) -> NORMAL
B138: SU115358 | C138: CIGUEÑAL | D138: 1 | E138: UND | F138: 0 | G138: 1 | H138: 380000 | I138: RECTIFICADORA DE MOTORES CONTINENTAL LTDA. | K138: CHARLY HUERTAS | L138: 21100012-R | M138: 46058 | N138: 46051 | O138: 72200 | P138: =IFERROR(G138*H138,0) -> 380000 | Q138: =IFERROR(IF(N138="","",MAX(TODAY()-N138,0)),0) -> 68 | R138: =IF(B138="","",IF(G138=0,"COMPLETO",IF(G138<=D138*0.1,"CASI COMPLETO","PENDIENTE"))) -> PENDIENTE | S138: =IF(B138="","",IFERROR(F138/D138,0)) -> 0 | T138: =IF(B138="","",IF(Q138>30,"CRITICO",IF(Q138>7,"URGENTE","NORMAL"))) -> CRITICO
B139: SU115824 | C139: SERVICIO DE RECTIFICACION | D139: 1 | E139: SRV | F139: 0 | G139: 1 | H139: 3750160 | I139: RECTIFICADORA DE MOTORES CONTINENTAL LTDA. | K139: CRISTHIAN BENITEZ | M139: 46101 | N139: 46093 | O139: 712530.4 | P139: =IFERROR(G139*H139,0) -> 3750160 | Q139: =IFERROR(IF(N139="","",MAX(TODAY()-N139,0)),0) -> 26 | R139: =IF(B139="","",IF(G139=0,"COMPLETO",IF(G139<=D139*0.1,"CASI COMPLETO","PENDIENTE"))) -> PENDIENTE | S139: =IF(B139="","",IFERROR(F139/D139,0)) -> 0 | T139: =IF(B139="","",IF(Q139>30,"CRITICO",IF(Q139>7,"URGENTE","NORMAL"))) -> URGENTE
B140: SU115825 | C140: CIGUEÑAL | D140: 1 | E140: UND | F140: 0 | G140: 1 | H140: 220000 | I140: RECTIFICADORA DE MOTORES CONTINENTAL LTDA. | K140: CRISTHIAN BENITEZ | L140: 21100012-R | M140: 46101 | N140: 46100 | O140: 41800 | P140: =IFERROR(G140*H140,0) -> 220000 | Q140: =IFERROR(IF(N140="","",MAX(TODAY()-N140,0)),0) -> 19 | R140: =IF(B140="","",IF(G140=0,"COMPLETO",IF(G140<=D140*0.1,"CASI COMPLETO","PENDIENTE"))) -> PENDIENTE | S140: =IF(B140="","",IFERROR(F140/D140,0)) -> 0 | T140: =IF(B140="","",IF(Q140>30,"CRITICO",IF(Q140>7,"URGENTE","NORMAL"))) -> URGENTE
B141: SU115956 | C141: SERVICIO DE RECTIFICACION | D141: 1 | E141: SRV | F141: 0 | G141: 1 | H141: 2520160 | I141: RECTIFICADORA DE MOTORES CONTINENTAL LTDA. | K141: CRISTHIAN BENITEZ | M141: 46119 | N141: 46099 | O141: 478830.4 | P141: =IFERROR(G141*H141,0) -> 2520160 | Q141: =IFERROR(IF(N141="","",MAX(TODAY()-N141,0)),0) -> 20 | R141: =IF(B141="","",IF(G141=0,"COMPLETO",IF(G141<=D141*0.1,"CASI COMPLETO","PENDIENTE"))) -> PENDIENTE | S141: =IF(B141="","",IFERROR(F141/D141,0)) -> 0 | T141: =IF(B141="","",IF(Q141>30,"CRITICO",IF(Q141>7,"URGENTE","NORMAL"))) -> URGENTE
B142: SU115912 | C142: DIODO IN5408 PUERTAS | D142: 500 | E142: UND | F142: 0 | G142: 500 | H142: 380 | I142: MASMOVIL SAS | J142: INIBXE08 | K142: CRISTHIAN BENITEZ | L142: 30500068 | M142: 46119 | N142: 46107 | O142: 36100 | P142: =IFERROR(G142*H142,0) -> 190000 | Q142: =IFERROR(IF(N142="","",MAX(TODAY()-N142,0)),0) -> 12 | R142: =IF(B142="","",IF(G142=0,"COMPLETO",IF(G142<=D142*0.1,"CASI COMPLETO","PENDIENTE"))) -> PENDIENTE | S142: =IF(B142="","",IFERROR(F142/D142,0)) -> 0 | T142: =IF(B142="","",IF(Q142>30,"CRITICO",IF(Q142>7,"URGENTE","NORMAL"))) -> URGENTE
B143: SU112988 | C143: TANQUE DE EXPANSIÓN | D143: 60 | E143: UND | F143: 22 | G143: 38 | H143: 410000 | I143: MAQUITECNICOS IMPORTADORES SAS | J143: DT8020005 | K143: CRISTHIAN BENITEZ | L143: 12630042 | M143: 46172 | N143: 46173 | O143: 4674000 | P143: =IFERROR(G143*H143,0) -> 15580000 | Q143: =IFERROR(IF(N143="","",MAX(TODAY()-N143,0)),0) -> 0 | R143: =IF(B143="","",IF(G143=0,"COMPLETO",IF(G143<=D143*0.1,"CASI COMPLETO","PENDIENTE"))) -> PENDIENTE | S143: =IF(B143="","",IFERROR(F143/D143,0)) -> 0.36666667 | T143: =IF(B143="","",IF(Q143>30,"CRITICO",IF(Q143>7,"URGENTE","NORMAL"))) -> NORMAL
B144: SU115863 | C144: TOPE VENTANA | D144: 150 | E144: UND | F144: 34 | G144: 116 | H144: 3616 | I144: MAQUITECNICOS IMPORTADORES SAS | J144: MQ001 | K144: CRISTHIAN BENITEZ | L144: 801200116 | M144: 46121 | N144: 46113 | O144: 103056 | P144: =IFERROR(G144*H144,0) -> 419456 | Q144: =IFERROR(IF(N144="","",MAX(TODAY()-N144,0)),0) -> 6 | R144: =IF(B144="","",IF(G144=0,"COMPLETO",IF(G144<=D144*0.1,"CASI COMPLETO","PENDIENTE"))) -> PENDIENTE | S144: =IF(B144="","",IFERROR(F144/D144,0)) -> 0.22666667 | T144: =IF(B144="","",IF(Q144>30,"CRITICO",IF(Q144>7,"URGENTE","NORMAL"))) -> NORMAL
B145: SU115945 | C145: SOPORTE MOTOR | D145: 4 | E145: UND | F145: 0 | G145: 4 | H145: 590000 | I145: MAQUITECNICOS IMPORTADORES SAS | J145: 70301773 | K145: CRISTHIAN BENITEZ | L145: 16500020 | M145: 46119 | N145: 46119 | O145: 448400 | P145: =IFERROR(G145*H145,0) -> 2360000 | Q145: =IFERROR(IF(N145="","",MAX(TODAY()-N145,0)),0) -> 0 | R145: =IF(B145="","",IF(G145=0,"COMPLETO",IF(G145<=D145*0.1,"CASI COMPLETO","PENDIENTE"))) -> PENDIENTE | S145: =IF(B145="","",IFERROR(F145/D145,0)) -> 0 | T145: =IF(B145="","",IF(Q145>30,"CRITICO",IF(Q145>7,"URGENTE","NORMAL"))) -> NORMAL
B146: SU115945 | C146: SOPORTE MOTOR | D146: 3 | E146: UND | F146: 0 | G146: 3 | H146: 590000 | I146: MAQUITECNICOS IMPORTADORES SAS | J146: 70301773 | K146: CRISTHIAN BENITEZ | L146: 16500020 | M146: 46119 | N146: 46113 | O146: 336300 | P146: =IFERROR(G146*H146,0) -> 1770000 | Q146: =IFERROR(IF(N146="","",MAX(TODAY()-N146,0)),0) -> 6 | R146: =IF(B146="","",IF(G146=0,"COMPLETO",IF(G146<=D146*0.1,"CASI COMPLETO","PENDIENTE"))) -> PENDIENTE | S146: =IF(B146="","",IFERROR(F146/D146,0)) -> 0 | T146: =IF(B146="","",IF(Q146>30,"CRITICO",IF(Q146>7,"URGENTE","NORMAL"))) -> NORMAL
B147: SU115860 | C147: SERVICIO REP. FUELLE SANFONA | D147: 1 | E147: SRV | F147: 0 | G147: 1 | H147: 1178903 | I147: LYC SERVITEC SAS | K147: CRISTHIAN BENITEZ | M147: 46105 | N147: 46100 | O147: 223991.6 | P147: =IFERROR(G147*H147,0) -> 1178903 | Q147: =IFERROR(IF(N147="","",MAX(TODAY()-N147,0)),0) -> 19 | R147: =IF(B147="","",IF(G147=0,"COMPLETO",IF(G147<=D147*0.1,"CASI COMPLETO","PENDIENTE"))) -> PENDIENTE | S147: =IF(B147="","",IFERROR(F147/D147,0)) -> 0 | T147: =IF(B147="","",IF(Q147>30,"CRITICO",IF(Q147>7,"URGENTE","NORMAL"))) -> URGENTE
B148: SU115930 | C148: SERVOBOMBA HIDRAULICA | D148: 3 | E148: UND | F148: 0 | G148: 3 | H148: 600000 | I148: LUCSAR SAS | K148: CHARLY HUERTAS | L148: 16430034-R | M148: 46122 | N148: 46111 | O148: 342000 | P148: =IFERROR(G148*H148,0) -> 1800000 | Q148: =IFERROR(IF(N148="","",MAX(TODAY()-N148,0)),0) -> 8 | R148: =IF(B148="","",IF(G148=0,"COMPLETO",IF(G148<=D148*0.1,"CASI COMPLETO","PENDIENTE"))) -> PENDIENTE | S148: =IF(B148="","",IFERROR(F148/D148,0)) -> 0 | T148: =IF(B148="","",IF(Q148>30,"CRITICO",IF(Q148>7,"URGENTE","NORMAL"))) -> URGENTE
B149: SU115530 | C149: LLANTA NUEVA RADIAL 295/80-R22.5 | D149: 624 | E149: UND | F149: 118 | G149: 506 | H149: 1978513 | I149: LLANTAS REPUESTOS Y SERVICIO SAS | J149: 295/80-R22.5 Michelin | K149: CRISTHIAN BENITEZ | L149: 77101008 | M149: 46472 | N149: 46069 | O149: 235000000 | P149: =IFERROR(G149*H149,0) -> 1001127578 | Q149: =IFERROR(IF(N149="","",MAX(TODAY()-N149,0)),0) -> 50 | R149: =IF(B149="","",IF(G149=0,"COMPLETO",IF(G149<=D149*0.1,"CASI COMPLETO","PENDIENTE"))) -> PENDIENTE | S149: =IF(B149="","",IFERROR(F149/D149,0)) -> 0.18910256 | T149: =IF(B149="","",IF(Q149>30,"CRITICO",IF(Q149>7,"URGENTE","NORMAL"))) -> CRITICO
...

Sheet PENDIENTES DETALLE
A1: DETALLE DE MATERIALES PENDIENTES POR LLEGAR
A2: Control de entregas | Se alimenta de DATA PENDIENTES automaticamente
A3: OC | B3: DESCRIPCION | C3: MAINSAVER | D3: PARTE FABRICANTE | E3: SOLICITADO | F3: UM | G3: RECIBIDO | H3: PENDIENTE | I3: COSTO UNIT. | J3: VALOR PENDIENTE | K3: PROVEEDOR | L3: COMPRADOR | M3: FECHA PROMESA | N3: FECHA REQUERIDA | O3: DIAS RETRASO | P3: ESTADO | Q3: CUMPLIMIENTO | R3: ALERTA | S3: PRIORIDAD | T3: VALOR IMPUESTO
A4: =IF('DATA PENDIENTES'!B45="","",'DATA PENDIENTES'!B45) -> SU115951 | B4: =IF(A4="","",'DATA PENDIENTES'!C45) -> TORNILLO EMBRIDADO M10*80 MM | C4: =IF(A4="","",'DATA PENDIENTES'!L45) -> 2150209 | D4: =IF(A4="","",'DATA PENDIENTES'!J45) -> 984759 | E4: =IF(A4="","",'DATA PENDIENTES'!D45) -> 5 | F4: =IF(A4="","",'DATA PENDIENTES'!E45) -> UND | G4: =IF(A4="","",'DATA PENDIENTES'!F45) -> 0 | H4: =IF(A4="","",'DATA PENDIENTES'!G45) -> 5 | I4: =IF(A4="","",'DATA PENDIENTES'!H45) -> 10533.37 | J4: =IF(A4="","",IFERROR(H4*F4,0)) -> 0 | K4: =IF(A4="","",'DATA PENDIENTES'!I45) -> VOLVO GROUP COLOMBIA S A S | L4: =IF(A4="","",'DATA PENDIENTES'!K45) -> CRISTHIAN BENITEZ | M4: =IF(A4="","",'DATA PENDIENTES'!M45) -> 46122 | N4: =IF(A4="","",'DATA PENDIENTES'!N45) -> 46120 | O4: =IF(A4="","",IFERROR(MAX(TODAY()-N4,0),0)) -> 0 | P4: =IF(A4="","",IF(H4=0,"COMPLETO",IF(H4<=E4*0.1,"CASI COMPLETO","PENDIENTE"))) -> PENDIENTE | Q4: =IF(A4="","",IFERROR(G4/E4,0)) -> 0 | R4: =IF(A4="","",IF(O4>30,"CRITICO",IF(O4>7,"ALERTA","OK"))) -> OK | S4: =IF(A4="","",IF(O4>30,"1-CRITICO",IF(O4>7,"2-URGENTE","3-NORMAL"))) -> 3-NORMAL | T4: =IF(A4="","",'DATA PENDIENTES'!O45) -> 10006.7
A5: =IF('DATA PENDIENTES'!B29="","",'DATA PENDIENTES'!B29) -> SU115941 | B5: =IF(A5="","",'DATA PENDIENTES'!C29) -> FILTRO DE ACEITE MOTOR DE DERIVACION | C5: =IF(A5="","",'DATA PENDIENTES'!L29) -> 2220200 | D5: =IF(A5="","",'DATA PENDIENTES'!J29) -> 21707132 | E5: =IF(A5="","",'DATA PENDIENTES'!D29) -> 40 | F5: =IF(A5="","",'DATA PENDIENTES'!E29) -> UND | G5: =IF(A5="","",'DATA PENDIENTES'!F29) -> 0 | H5: =IF(A5="","",'DATA PENDIENTES'!G29) -> 40 | I5: =IF(A5="","",'DATA PENDIENTES'!H29) -> 47122.98 | J5: =IF(A5="","",IFERROR(H5*F5,0)) -> 0 | K5: =IF(A5="","",'DATA PENDIENTES'!I29) -> VOLVO GROUP COLOMBIA S A S | L5: =IF(A5="","",'DATA PENDIENTES'!K29) -> CRISTHIAN BENITEZ | M5: =IF(A5="","",'DATA PENDIENTES'!M29) -> 46118 | N5: =IF(A5="","",'DATA PENDIENTES'!N29) -> 46108 | O5: =IF(A5="","",IFERROR(MAX(TODAY()-N5,0),0)) -> 11 | P5: =IF(A5="","",IF(H5=0,"COMPLETO",IF(H5<=E5*0.1,"CASI COMPLETO","PENDIENTE"))) -> PENDIENTE | Q5: =IF(A5="","",IFERROR(G5/E5,0)) -> 0 | R5: =IF(A5="","",IF(O5>30,"CRITICO",IF(O5>7,"ALERTA","OK"))) -> ALERTA | S5: =IF(A5="","",IF(O5>30,"1-CRITICO",IF(O5>7,"2-URGENTE","3-NORMAL"))) -> 2-URGENTE | T5: =IF(A5="","",'DATA PENDIENTES'!O29) -> 358134.6
A6: =IF('DATA PENDIENTES'!B30="","",'DATA PENDIENTES'!B30) -> SU115941 | B6: =IF(A6="","",'DATA PENDIENTES'!C30) -> FILTRO DE ACEITE MOTOR LARGA DURACION | C6: =IF(A6="","",'DATA PENDIENTES'!L30) -> 2220201 | D6: =IF(A6="","",'DATA PENDIENTES'!J30) -> 21707133 | E6: =IF(A6="","",'DATA PENDIENTES'!D30) -> 120 | F6: =IF(A6="","",'DATA PENDIENTES'!E30) -> UND | G6: =IF(A6="","",'DATA PENDIENTES'!F30) -> 0 | H6: =IF(A6="","",'DATA PENDIENTES'!G30) -> 120 | I6: =IF(A6="","",'DATA PENDIENTES'!H30) -> 58210.74 | J6: =IF(A6="","",IFERROR(H6*F6,0)) -> 0 | K6: =IF(A6="","",'DATA PENDIENTES'!I30) -> VOLVO GROUP COLOMBIA S A S | L6: =IF(A6="","",'DATA PENDIENTES'!K30) -> CRISTHIAN BENITEZ | M6: =IF(A6="","",'DATA PENDIENTES'!M30) -> 46118 | N6: =IF(A6="","",'DATA PENDIENTES'!N30) -> 46108 | O6: =IF(A6="","",IFERROR(MAX(TODAY()-N6,0),0)) -> 11 | P6: =IF(A6="","",IF(H6=0,"COMPLETO",IF(H6<=E6*0.1,"CASI COMPLETO","PENDIENTE"))) -> PENDIENTE | Q6: =IF(A6="","",IFERROR(G6/E6,0)) -> 0 | R6: =IF(A6="","",IF(O6>30,"CRITICO",IF(O6>7,"ALERTA","OK"))) -> ALERTA | S6: =IF(A6="","",IF(O6>30,"1-CRITICO",IF(O6>7,"2-URGENTE","3-NORMAL"))) -> 2-URGENTE | T6: =IF(A6="","",'DATA PENDIENTES'!O30) -> 1327205
A7: =IF('DATA PENDIENTES'!B31="","",'DATA PENDIENTES'!B31) -> SU115941 | B7: =IF(A7="","",'DATA PENDIENTES'!C31) -> FILTRO DE ACEITE DE TRANSMISION | C7: =IF(A7="","",'DATA PENDIENTES'!L31) -> 2220202 | D7: =IF(A7="","",'DATA PENDIENTES'!J31) -> 22925076 | E7: =IF(A7="","",'DATA PENDIENTES'!D31) -> 15 | F7: =IF(A7="","",'DATA PENDIENTES'!E31) -> UND | G7: =IF(A7="","",'DATA PENDIENTES'!F31) -> 0 | H7: =IF(A7="","",'DATA PENDIENTES'!G31) -> 15 | I7: =IF(A7="","",'DATA PENDIENTES'!H31) -> 210667.4 | J7: =IF(A7="","",IFERROR(H7*F7,0)) -> 0 | K7: =IF(A7="","",'DATA PENDIENTES'!I31) -> VOLVO GROUP COLOMBIA S A S | L7: =IF(A7="","",'DATA PENDIENTES'!K31) -> CRISTHIAN BENITEZ | M7: =IF(A7="","",'DATA PENDIENTES'!M31) -> 46118 | N7: =IF(A7="","",'DATA PENDIENTES'!N31) -> 46108 | O7: =IF(A7="","",IFERROR(MAX(TODAY()-N7,0),0)) -> 11 | P7: =IF(A7="","",IF(H7=0,"COMPLETO",IF(H7<=E7*0.1,"CASI COMPLETO","PENDIENTE"))) -> PENDIENTE | Q7: =IF(A7="","",IFERROR(G7/E7,0)) -> 0 | R7: =IF(A7="","",IF(O7>30,"CRITICO",IF(O7>7,"ALERTA","OK"))) -> ALERTA | S7: =IF(A7="","",IF(O7>30,"1-CRITICO",IF(O7>7,"2-URGENTE","3-NORMAL"))) -> 2-URGENTE | T7: =IF(A7="","",'DATA PENDIENTES'!O31) -> 600402.2
A8: =IF('DATA PENDIENTES'!B32="","",'DATA PENDIENTES'!B32) -> SU115941 | B8: =IF(A8="","",'DATA PENDIENTES'!C32) -> FILTRO DE COMBUSTIBLE SEPARADOR DE AGUA | C8: =IF(A8="","",'DATA PENDIENTES'!L32) -> 2330201 | D8: =IF(A8="","",'DATA PENDIENTES'!J32) -> 20998367 | E8: =IF(A8="","",'DATA PENDIENTES'!D32) -> 60 | F8: =IF(A8="","",'DATA PENDIENTES'!E32) -> UND | G8: =IF(A8="","",'DATA PENDIENTES'!F32) -> 0 | H8: =IF(A8="","",'DATA PENDIENTES'!G32) -> 60 | I8: =IF(A8="","",'DATA PENDIENTES'!H32) -> 66526.56 | J8: =IF(A8="","",IFERROR(H8*F8,0)) -> 0 | K8: =IF(A8="","",'DATA PENDIENTES'!I32) -> VOLVO GROUP COLOMBIA S A S | L8: =IF(A8="","",'DATA PENDIENTES'!K32) -> CRISTHIAN BENITEZ | M8: =IF(A8="","",'DATA PENDIENTES'!M32) -> 46118 | N8: =IF(A8="","",'DATA PENDIENTES'!N32) -> 46108 | O8: =IF(A8="","",IFERROR(MAX(TODAY()-N8,0),0)) -> 11 | P8: =IF(A8="","",IF(H8=0,"COMPLETO",IF(H8<=E8*0.1,"CASI COMPLETO","PENDIENTE"))) -> PENDIENTE | Q8: =IF(A8="","",IFERROR(G8/E8,0)) -> 0 | R8: =IF(A8="","",IF(O8>30,"CRITICO",IF(O8>7,"ALERTA","OK"))) -> ALERTA | S8: =IF(A8="","",IF(O8>30,"1-CRITICO",IF(O8>7,"2-URGENTE","3-NORMAL"))) -> 2-URGENTE | T8: =IF(A8="","",'DATA PENDIENTES'!O32) -> 758402.8
A9: =IF('DATA PENDIENTES'!B33="","",'DATA PENDIENTES'!B33) -> SU115941 | B9: =IF(A9="","",'DATA PENDIENTES'!C33) -> FILTRO DE COMBUSTIBLE | C9: =IF(A9="","",'DATA PENDIENTES'!L33) -> 2330207 | D9: =IF(A9="","",'DATA PENDIENTES'!J33) -> 22480372 | E9: =IF(A9="","",'DATA PENDIENTES'!D33) -> 60 | F9: =IF(A9="","",'DATA PENDIENTES'!E33) -> UND | G9: =IF(A9="","",'DATA PENDIENTES'!F33) -> 0 | H9: =IF(A9="","",'DATA PENDIENTES'!G33) -> 60 | I9: =IF(A9="","",'DATA PENDIENTES'!H33) -> 58210.74 | J9: =IF(A9="","",IFERROR(H9*F9,0)) -> 0 | K9: =IF(A9="","",'DATA PENDIENTES'!I33) -> VOLVO GROUP COLOMBIA S A S | L9: =IF(A9="","",'DATA PENDIENTES'!K33) -> CRISTHIAN BENITEZ | M9: =IF(A9="","",'DATA PENDIENTES'!M33) -> 46118 | N9: =IF(A9="","",'DATA PENDIENTES'!N33) -> 46108 | O9: =IF(A9="","",IFERROR(MAX(TODAY()-N9,0),0)) -> 11 | P9: =IF(A9="","",IF(H9=0,"COMPLETO",IF(H9<=E9*0.1,"CASI COMPLETO","PENDIENTE"))) -> PENDIENTE | Q9: =IF(A9="","",IFERROR(G9/E9,0)) -> 0 | R9: =IF(A9="","",IF(O9>30,"CRITICO",IF(O9>7,"ALERTA","OK"))) -> ALERTA | S9: =IF(A9="","",IF(O9>30,"1-CRITICO",IF(O9>7,"2-URGENTE","3-NORMAL"))) -> 2-URGENTE | T9: =IF(A9="","",'DATA PENDIENTES'!O33) -> 663602.4
A10: =IF('DATA PENDIENTES'!B34="","",'DATA PENDIENTES'!B34) -> SU115941 | B10: =IF(A10="","",'DATA PENDIENTES'!C34) -> FILTRO RESPIRADERO TANQUE DE COMBUSTIBLE | C10: =IF(A10="","",'DATA PENDIENTES'!L34) -> 2330209 | D10: =IF(A10="","",'DATA PENDIENTES'!J34) -> 21743197 | E10: =IF(A10="","",'DATA PENDIENTES'!D34) -> 20 | F10: =IF(A10="","",'DATA PENDIENTES'!E34) -> UND | G10: =IF(A10="","",'DATA PENDIENTES'!F34) -> 0 | H10: =IF(A10="","",'DATA PENDIENTES'!G34) -> 20 | I10: =IF(A10="","",'DATA PENDIENTES'!H34) -> 83158.2 | J10: =IF(A10="","",IFERROR(H10*F10,0)) -> 0 | K10: =IF(A10="","",'DATA PENDIENTES'!I34) -> VOLVO GROUP COLOMBIA S A S | L10: =IF(A10="","",'DATA PENDIENTES'!K34) -> CRISTHIAN BENITEZ | M10: =IF(A10="","",'DATA PENDIENTES'!M34) -> 46118 | N10: =IF(A10="","",'DATA PENDIENTES'!N34) -> 46108 | O10: =IF(A10="","",IFERROR(MAX(TODAY()-N10,0),0)) -> 11 | P10: =IF(A10="","",IF(H10=0,"COMPLETO",IF(H10<=E10*0.1,"CASI COMPLETO","PENDIENTE"))) -> PENDIENTE | Q10: =IF(A10="","",IFERROR(G10/E10,0)) -> 0 | R10: =IF(A10="","",IF(O10>30,"CRITICO",IF(O10>7,"ALERTA","OK"))) -> ALERTA | S10: =IF(A10="","",IF(O10>30,"1-CRITICO",IF(O10>7,"2-URGENTE","3-NORMAL"))) -> 2-URGENTE | T10: =IF(A10="","",'DATA PENDIENTES'!O34) -> 316001.2
A11: =IF('DATA PENDIENTES'!B178="","",'DATA PENDIENTES'!B178) -> SU114612 | B11: =IF(A11="","",'DATA PENDIENTES'!C178) -> ADBLUE ARLA 32 AUTOMOTRIZ | C11: =IF(A11="","",'DATA PENDIENTES'!L178) -> 2540131 | D11: =IF(A11="","",'DATA PENDIENTES'!J178) -> 2540131 | E11: =IF(A11="","",'DATA PENDIENTES'!D178) -> 40000 | F11: =IF(A11="","",'DATA PENDIENTES'!E178) -> L | G11: =IF(A11="","",'DATA PENDIENTES'!F178) -> 30000 | H11: =IF(A11="","",'DATA PENDIENTES'!G178) -> 10000 | I11: =IF(A11="","",'DATA PENDIENTES'!H178) -> 2600 | J11: =IF(A11="","",IFERROR(H11*F11,0)) -> 0 | K11: =IF(A11="","",'DATA PENDIENTES'!I178) -> HIDROTECNIK S A S | L11: =IF(A11="","",'DATA PENDIENTES'!K178) -> CRISTHIAN BENITEZ | M11: =IF(A11="","",'DATA PENDIENTES'!M178) -> 46022 | N11: =IF(A11="","",'DATA PENDIENTES'!N178) -> 45972 | O11: =IF(A11="","",IFERROR(MAX(TODAY()-N11,0),0)) -> 147 | P11: =IF(A11="","",IF(H11=0,"COMPLETO",IF(H11<=E11*0.1,"CASI COMPLETO","PENDIENTE"))) -> PENDIENTE | Q11: =IF(A11="","",IFERROR(G11/E11,0)) -> 0.75 | R11: =IF(A11="","",IF(O11>30,"CRITICO",IF(O11>7,"ALERTA","OK"))) -> CRITICO | S11: =IF(A11="","",IF(O11>30,"1-CRITICO",IF(O11>7,"2-URGENTE","3-NORMAL"))) -> 1-CRITICO | T11: =IF(A11="","",'DATA PENDIENTES'!O178) -> 19760000
A12: =IF('DATA PENDIENTES'!B179="","",'DATA PENDIENTES'!B179) -> SU115621 | B12: =IF(A12="","",'DATA PENDIENTES'!C179) -> ADBLUE ARLA 32 AUTOMOTRIZ | C12: =IF(A12="","",'DATA PENDIENTES'!L179) -> 2540131 | D12: =IF(A12="","",'DATA PENDIENTES'!J179) -> 400205 | E12: =IF(A12="","",'DATA PENDIENTES'!D179) -> 40000 | F12: =IF(A12="","",'DATA PENDIENTES'!E179) -> L | G12: =IF(A12="","",'DATA PENDIENTES'!F179) -> 20000 | H12: =IF(A12="","",'DATA PENDIENTES'!G179) -> 20000 | I12: =IF(A12="","",'DATA PENDIENTES'!H179) -> 2600 | J12: =IF(A12="","",IFERROR(H12*F12,0)) -> 0 | K12: =IF(A12="","",'DATA PENDIENTES'!I179) -> HIDROTECNIK S A S | L12: =IF(A12="","",'DATA PENDIENTES'!K179) -> CRISTHIAN BENITEZ | M12: =IF(A12="","",'DATA PENDIENTES'!M179) -> 46109 | N12: =IF(A12="","",'DATA PENDIENTES'!N179) -> 46079 | O12: =IF(A12="","",IFERROR(MAX(TODAY()-N12,0),0)) -> 40 | P12: =IF(A12="","",IF(H12=0,"COMPLETO",IF(H12<=E12*0.1,"CASI COMPLETO","PENDIENTE"))) -> PENDIENTE | Q12: =IF(A12="","",IFERROR(G12/E12,0)) -> 0.5 | R12: =IF(A12="","",IF(O12>30,"CRITICO",IF(O12>7,"ALERTA","OK"))) -> CRITICO | S12: =IF(A12="","",IF(O12>30,"1-CRITICO",IF(O12>7,"2-URGENTE","3-NORMAL"))) -> 1-CRITICO | T12: =IF(A12="","",'DATA PENDIENTES'!O179) -> 19760000
A13: =IF('DATA PENDIENTES'!B37="","",'DATA PENDIENTES'!B37) -> SU115941 | B13: =IF(A13="","",'DATA PENDIENTES'!C37) -> FILTRO DE HIDRAULICO VENTILADOR | C13: =IF(A13="","",'DATA PENDIENTES'!L37) -> 2630125 | D13: =IF(A13="","",'DATA PENDIENTES'!J37) -> 20801559 | E13: =IF(A13="","",'DATA PENDIENTES'!D37) -> 5 | F13: =IF(A13="","",'DATA PENDIENTES'!E37) -> UND | G13: =IF(A13="","",'DATA PENDIENTES'!F37) -> 0 | H13: =IF(A13="","",'DATA PENDIENTES'!G37) -> 5 | I13: =IF(A13="","",'DATA PENDIENTES'!H37) -> 174632.2 | J13: =IF(A13="","",IFERROR(H13*F13,0)) -> 0 | K13: =IF(A13="","",'DATA PENDIENTES'!I37) -> VOLVO GROUP COLOMBIA S A S | L13: =IF(A13="","",'DATA PENDIENTES'!K37) -> CRISTHIAN BENITEZ | M13: =IF(A13="","",'DATA PENDIENTES'!M37) -> 46118 | N13: =IF(A13="","",'DATA PENDIENTES'!N37) -> 46108 | O13: =IF(A13="","",IFERROR(MAX(TODAY()-N13,0),0)) -> 11 | P13: =IF(A13="","",IF(H13=0,"COMPLETO",IF(H13<=E13*0.1,"CASI COMPLETO","PENDIENTE"))) -> PENDIENTE | Q13: =IF(A13="","",IFERROR(G13/E13,0)) -> 0 | R13: =IF(A13="","",IF(O13>30,"CRITICO",IF(O13>7,"ALERTA","OK"))) -> ALERTA | S13: =IF(A13="","",IF(O13>30,"1-CRITICO",IF(O13>7,"2-URGENTE","3-NORMAL"))) -> 2-URGENTE | T13: =IF(A13="","",'DATA PENDIENTES'!O37) -> 165900.6
A14: =IF('DATA PENDIENTES'!B43="","",'DATA PENDIENTES'!B43) -> SU115942 | B14: =IF(A14="","",'DATA PENDIENTES'!C43) -> TENSOR DE CORREA | C14: =IF(A14="","",'DATA PENDIENTES'!L43) -> 3210113 | D14: =IF(A14="","",'DATA PENDIENTES'!J43) -> 21719386 | E14: =IF(A14="","",'DATA PENDIENTES'!D43) -> 8 | F14: =IF(A14="","",'DATA PENDIENTES'!E43) -> UND | G14: =IF(A14="","",'DATA PENDIENTES'!F43) -> 6 | H14: =IF(A14="","",'DATA PENDIENTES'!G43) -> 2 | I14: =IF(A14="","",'DATA PENDIENTES'!H43) -> 820494.2 | J14: =IF(A14="","",IFERROR(H14*F14,0)) -> 0 | K14: =IF(A14="","",'DATA PENDIENTES'!I43) -> VOLVO GROUP COLOMBIA S A S | L14: =IF(A14="","",'DATA PENDIENTES'!K43) -> CRISTHIAN BENITEZ | M14: =IF(A14="","",'DATA PENDIENTES'!M43) -> 46186 | N14: =IF(A14="","",'DATA PENDIENTES'!N43) -> 46119 | O14: =IF(A14="","",IFERROR(MAX(TODAY()-N14,0),0)) -> 0 | P14: =IF(A14="","",IF(H14=0,"COMPLETO",IF(H14<=E14*0.1,"CASI COMPLETO","PENDIENTE"))) -> PENDIENTE | Q14: =IF(A14="","",IFERROR(G14/E14,0)) -> 0.75 | R14: =IF(A14="","",IF(O14>30,"CRITICO",IF(O14>7,"ALERTA","OK"))) -> OK | S14: =IF(A14="","",IF(O14>30,"1-CRITICO",IF(O14>7,"2-URGENTE","3-NORMAL"))) -> 3-NORMAL | T14: =IF(A14="","",'DATA PENDIENTES'!O43) -> 1247151
A15: =IF('DATA PENDIENTES'!B232="","",'DATA PENDIENTES'!B232) -> SU115871 | B15: =IF(A15="","",'DATA PENDIENTES'!C232) -> LIMPIA CONTACTOS ELÉCTRICO | C15: =IF(A15="","",'DATA PENDIENTES'!L232) -> 3860202 | D15: =IF(A15="","",'DATA PENDIENTES'!J232) -> 1350 | E15: =IF(A15="","",'DATA PENDIENTES'!D232) -> 20 | F15: =IF(A15="","",'DATA PENDIENTES'!E232) -> UND | G15: =IF(A15="","",'DATA PENDIENTES'!F232) -> 0 | H15: =IF(A15="","",'DATA PENDIENTES'!G232) -> 20 | I15: =IF(A15="","",'DATA PENDIENTES'!H232) -> 13750 | J15: =IF(A15="","",IFERROR(H15*F15,0)) -> 0 | K15: =IF(A15="","",'DATA PENDIENTES'!I232) -> EMPAQUETADURAS Y EMPAQUES S.A. | L15: =IF(A15="","",'DATA PENDIENTES'!K232) -> CRISTHIAN BENITEZ | M15: =IF(A15="","",'DATA PENDIENTES'!M232) -> 46113 | N15: =IF(A15="","",'DATA PENDIENTES'!N232) -> 46113 | O15: =IF(A15="","",IFERROR(MAX(TODAY()-N15,0),0)) -> 6 | P15: =IF(A15="","",IF(H15=0,"COMPLETO",IF(H15<=E15*0.1,"CASI COMPLETO","PENDIENTE"))) -> PENDIENTE | Q15: =IF(A15="","",IFERROR(G15/E15,0)) -> 0 | R15: =IF(A15="","",IF(O15>30,"CRITICO",IF(O15>7,"ALERTA","OK"))) -> OK | S15: =IF(A15="","",IF(O15>30,"1-CRITICO",IF(O15>7,"2-URGENTE","3-NORMAL"))) -> 3-NORMAL | T15: =IF(A15="","",'DATA PENDIENTES'!O232) -> 52250
A16: =IF('DATA PENDIENTES'!B71="","",'DATA PENDIENTES'!B71) -> SU115136 | B16: =IF(A16="","",'DATA PENDIENTES'!C71) -> DISCO DE ASPIRACIÓN 3M LIMPIA HK 6" P150 | C16: =IF(A16="","",'DATA PENDIENTES'!L71) -> 3860302 | D16: =IF(A16="","",'DATA PENDIENTES'!J71) -> 501 | E16: =IF(A16="","",'DATA PENDIENTES'!D71) -> 1400 | F16: =IF(A16="","",'DATA PENDIENTES'!E71) -> UND | G16: =IF(A16="","",'DATA PENDIENTES'!F71) -> 1050 | H16: =IF(A16="","",'DATA PENDIENTES'!G71) -> 350 | I16: =IF(A16="","",'DATA PENDIENTES'!H71) -> 3255 | J16: =IF(A16="","",IFERROR(H16*F16,0)) -> 0 | K16: =IF(A16="","",'DATA PENDIENTES'!I71) -> SUMILOGISTICA S.A.S. | L16: =IF(A16="","",'DATA PENDIENTES'!K71) -> CRISTHIAN BENITEZ | M16: =IF(A16="","",'DATA PENDIENTES'!M71) -> 46142 | N16: =IF(A16="","",'DATA PENDIENTES'!N71) -> 46142 | O16: =IF(A16="","",IFERROR(MAX(TODAY()-N16,0),0)) -> 0 | P16: =IF(A16="","",IF(H16=0,"COMPLETO",IF(H16<=E16*0.1,"CASI COMPLETO","PENDIENTE"))) -> PENDIENTE | Q16: =IF(A16="","",IFERROR(G16/E16,0)) -> 0.75 | R16: =IF(A16="","",IF(O16>30,"CRITICO",IF(O16>7,"ALERTA","OK"))) -> OK | S16: =IF(A16="","",IF(O16>30,"1-CRITICO",IF(O16>7,"2-URGENTE","3-NORMAL"))) -> 3-NORMAL | T16: =IF(A16="","",'DATA PENDIENTES'!O71) -> 865830
A17: =IF('DATA PENDIENTES'!B72="","",'DATA PENDIENTES'!B72) -> SU115136 | B17: =IF(A17="","",'DATA PENDIENTES'!C72) -> DISCO DE ASPIRACIÓN 3M LIMPIA HK 6" P220 | C17: =IF(A17="","",'DATA PENDIENTES'!L72) -> 3860303 | D17: =IF(A17="","",'DATA PENDIENTES'!J72) -> 96 | E17: =IF(A17="","",'DATA PENDIENTES'!D72) -> 1400 | F17: =IF(A17="","",'DATA PENDIENTES'!E72) -> UND | G17: =IF(A17="","",'DATA PENDIENTES'!F72) -> 1050 | H17: =IF(A17="","",'DATA PENDIENTES'!G72) -> 350 | I17: =IF(A17="","",'DATA PENDIENTES'!H72) -> 3255 | J17: =IF(A17="","",IFERROR(H17*F17,0)) -> 0 | K17: =IF(A17="","",'DATA PENDIENTES'!I72) -> SUMILOGISTICA S.A.S. | L17: =IF(A17="","",'DATA PENDIENTES'!K72) -> CRISTHIAN BENITEZ | M17: =IF(A17="","",'DATA PENDIENTES'!M72) -> 46142 | N17: =IF(A17="","",'DATA PENDIENTES'!N72) -> 46142 | O17: =IF(A17="","",IFERROR(MAX(TODAY()-N17,0),0)) -> 0 | P17: =IF(A17="","",IF(H17=0,"COMPLETO",IF(H17<=E17*0.1,"CASI COMPLETO","PENDIENTE"))) -> PENDIENTE | Q17: =IF(A17="","",IFERROR(G17/E17,0)) -> 0.75 | R17: =IF(A17="","",IF(O17>30,"CRITICO",IF(O17>7,"ALERTA","OK"))) -> OK | S17: =IF(A17="","",IF(O17>30,"1-CRITICO",IF(O17>7,"2-URGENTE","3-NORMAL"))) -> 3-NORMAL | T17: =IF(A17="","",'DATA PENDIENTES'!O72) -> 865830
A18: =IF('DATA PENDIENTES'!B6="","",'DATA PENDIENTES'!B6) -> SU114003 | B18: =IF(A18="","",'DATA PENDIENTES'!C6) -> DISCO DE FRENO SOLIDO | C18: =IF(A18="","",'DATA PENDIENTES'!L6) -> 5100100 | D18: =IF(A18="","",'DATA PENDIENTES'!J6) -> 3092710 | E18: =IF(A18="","",'DATA PENDIENTES'!D6) -> 160 | F18: =IF(A18="","",'DATA PENDIENTES'!E6) -> UND | G18: =IF(A18="","",'DATA PENDIENTES'!F6) -> 110 | H18: =IF(A18="","",'DATA PENDIENTES'!G6) -> 50 | I18: =IF(A18="","",'DATA PENDIENTES'!H6) -> 1140000 | J18: =IF(A18="","",IFERROR(H18*F18,0)) -> 0 | K18: =IF(A18="","",'DATA PENDIENTES'!I6) -> VOLVO GROUP COLOMBIA S A S | L18: =IF(A18="","",'DATA PENDIENTES'!K6) -> CRISTHIAN BENITEZ | M18: =IF(A18="","",'DATA PENDIENTES'!M6) -> 46326 | N18: =IF(A18="","",'DATA PENDIENTES'!N6) -> 46265 | O18: =IF(A18="","",IFERROR(MAX(TODAY()-N18,0),0)) -> 0 | P18: =IF(A18="","",IF(H18=0,"COMPLETO",IF(H18<=E18*0.1,"CASI COMPLETO","PENDIENTE"))) -> PENDIENTE | Q18: =IF(A18="","",IFERROR(G18/E18,0)) -> 0.6875 | R18: =IF(A18="","",IF(O18>30,"CRITICO",IF(O18>7,"ALERTA","OK"))) -> OK | S18: =IF(A18="","",IF(O18>30,"1-CRITICO",IF(O18>7,"2-URGENTE","3-NORMAL"))) -> 3-NORMAL | T18: =IF(A18="","",'DATA PENDIENTES'!O6) -> 34656000
A19: =IF('DATA PENDIENTES'!B5="","",'DATA PENDIENTES'!B5) -> SU114003 | B19: =IF(A19="","",'DATA PENDIENTES'!C5) -> DISCO DE FRENO VENTILADO | C19: =IF(A19="","",'DATA PENDIENTES'!L5) -> 5100101 | D19: =IF(A19="","",'DATA PENDIENTES'!J5) -> 21575071 | E19: =IF(A19="","",'DATA PENDIENTES'!D5) -> 460 | F19: =IF(A19="","",'DATA PENDIENTES'!E5) -> UND | G19: =IF(A19="","",'DATA PENDIENTES'!F5) -> 280 | H19: =IF(A19="","",'DATA PENDIENTES'!G5) -> 180 | I19: =IF(A19="","",'DATA PENDIENTES'!H5) -> 1002911 | J19: =IF(A19="","",IFERROR(H19*F19,0)) -> 0 | K19: =IF(A19="","",'DATA PENDIENTES'!I5) -> VOLVO GROUP COLOMBIA S A S | L19: =IF(A19="","",'DATA PENDIENTES'!K5) -> CRISTHIAN BENITEZ | M19: =IF(A19="","",'DATA PENDIENTES'!M5) -> 46326 | N19: =IF(A19="","",'DATA PENDIENTES'!N5) -> 46265 | O19: =IF(A19="","",IFERROR(MAX(TODAY()-N19,0),0)) -> 0 | P19: =IF(A19="","",IF(H19=0,"COMPLETO",IF(H19<=E19*0.1,"CASI COMPLETO","PENDIENTE"))) -> PENDIENTE | Q19: =IF(A19="","",IFERROR(G19/E19,0)) -> 0.60869565 | R19: =IF(A19="","",IF(O19>30,"CRITICO",IF(O19>7,"ALERTA","OK"))) -> OK | S19: =IF(A19="","",IF(O19>30,"1-CRITICO",IF(O19>7,"2-URGENTE","3-NORMAL"))) -> 3-NORMAL | T19: =IF(A19="","",'DATA PENDIENTES'!O5) -> 87654421
A20: =IF('DATA PENDIENTES'!B233="","",'DATA PENDIENTES'!B233) -> SU115871 | B20: =IF(A20="","",'DATA PENDIENTES'!C233) -> LIMPIADOR DE FRENOS | C20: =IF(A20="","",'DATA PENDIENTES'!L233) -> 5100103 | D20: =IF(A20="","",'DATA PENDIENTES'!J233) | E20: =IF(A20="","",'DATA PENDIENTES'!D233) -> 4 | F20: =IF(A20="","",'DATA PENDIENTES'!E233) -> UND | G20: =IF(A20="","",'DATA PENDIENTES'!F233) -> 0 | H20: =IF(A20="","",'DATA PENDIENTES'!G233) -> 4 | I20: =IF(A20="","",'DATA PENDIENTES'!H233) -> 13000 | J20: =IF(A20="","",IFERROR(H20*F20,0)) -> 0 | K20: =IF(A20="","",'DATA PENDIENTES'!I233) -> EMPAQUETADURAS Y EMPAQUES S.A. | L20: =IF(A20="","",'DATA PENDIENTES'!K233) -> CRISTHIAN BENITEZ | M20: =IF(A20="","",'DATA PENDIENTES'!M233) -> 46113 | N20: =IF(A20="","",'DATA PENDIENTES'!N233) -> 46113 | O20: =IF(A20="","",IFERROR(MAX(TODAY()-N20,0),0)) -> 6 | P20: =IF(A20="","",IF(H20=0,"COMPLETO",IF(H20<=E20*0.1,"CASI COMPLETO","PENDIENTE"))) -> PENDIENTE | Q20: =IF(A20="","",IFERROR(G20/E20,0)) -> 0 | R20: =IF(A20="","",IF(O20>30,"CRITICO",IF(O20>7,"ALERTA","OK"))) -> OK | S20: =IF(A20="","",IF(O20>30,"1-CRITICO",IF(O20>7,"2-URGENTE","3-NORMAL"))) -> 3-NORMAL | T20: =IF(A20="","",'DATA PENDIENTES'!O233) -> 9880
A21: =IF('DATA PENDIENTES'!B241="","",'DATA PENDIENTES'!B241) -> SU114595 | B21: =IF(A21="","",'DATA PENDIENTES'!C241) -> JUEGO DE PASTILLAS DE DISCO DE FRENO | C21: =IF(A21="","",'DATA PENDIENTES'!L241) -> 5100200 | D21: =IF(A21="","",'DATA PENDIENTES'!J241) -> 21024702 | E21: =IF(A21="","",'DATA PENDIENTES'!D241) -> 986 | F21: =IF(A21="","",'DATA PENDIENTES'!E241) -> UND | G21: =IF(A21="","",'DATA PENDIENTES'!F241) -> 329 | H21: =IF(A21="","",'DATA PENDIENTES'!G241) -> 657 | I21: =IF(A21="","",'DATA PENDIENTES'!H241) -> 420300 | J21: =IF(A21="","",IFERROR(H21*F21,0)) -> 0 | K21: =IF(A21="","",'DATA PENDIENTES'!I241) -> COMERCONZA SAS | L21: =IF(A21="","",'DATA PENDIENTES'!K241) -> CRISTHIAN BENITEZ | M21: =IF(A21="","",'DATA PENDIENTES'!M241) -> 46387 | N21: =IF(A21="","",'DATA PENDIENTES'!N241) -> 46387 | O21: =IF(A21="","",IFERROR(MAX(TODAY()-N21,0),0)) -> 0 | P21: =IF(A21="","",IF(H21=0,"COMPLETO",IF(H21<=E21*0.1,"CASI COMPLETO","PENDIENTE"))) -> PENDIENTE | Q21: =IF(A21="","",IFERROR(G21/E21,0)) -> 0.3336714 | R21: =IF(A21="","",IF(O21>30,"CRITICO",IF(O21>7,"ALERTA","OK"))) -> OK | S21: =IF(A21="","",IF(O21>30,"1-CRITICO",IF(O21>7,"2-URGENTE","3-NORMAL"))) -> 3-NORMAL | T21: =IF(A21="","",'DATA PENDIENTES'!O241) -> 78739002
A22: =IF('DATA PENDIENTES'!B55="","",'DATA PENDIENTES'!B55) -> SU111857 | B22: =IF(A22="","",'DATA PENDIENTES'!C55) -> FUELLE NEUMATICO TRASERO | C22: =IF(A22="","",'DATA PENDIENTES'!L55) -> 7260105 | D22: =IF(A22="","",'DATA PENDIENTES'!J55) -> 954090 | E22: =IF(A22="","",'DATA PENDIENTES'!D55) -> 612 | F22: =IF(A22="","",'DATA PENDIENTES'!E55) -> UND | G22: =IF(A22="","",'DATA PENDIENTES'!F55) -> 502 | H22: =IF(A22="","",'DATA PENDIENTES'!G55) -> 110 | I22: =IF(A22="","",'DATA PENDIENTES'!H55) -> 210000 | J22: =IF(A22="","",IFERROR(H22*F22,0)) -> 0 | K22: =IF(A22="","",'DATA PENDIENTES'!I55) -> TC IMPORTACIONES S.A.S | L22: =IF(A22="","",'DATA PENDIENTES'!K55) -> CRISTHIAN BENITEZ | M22: =IF(A22="","",'DATA PENDIENTES'!M55) -> 46037 | N22: =IF(A22="","",'DATA PENDIENTES'!N55) -> 45709 | O22: =IF(A22="","",IFERROR(MAX(TODAY()-N22,0),0)) -> 410 | P22: =IF(A22="","",IF(H22=0,"COMPLETO",IF(H22<=E22*0.1,"CASI COMPLETO","PENDIENTE"))) -> PENDIENTE | Q22: =IF(A22="","",IFERROR(G22/E22,0)) -> 0.82026144 | R22: =IF(A22="","",IF(O22>30,"CRITICO",IF(O22>7,"ALERTA","OK"))) -> CRITICO | S22: =IF(A22="","",IF(O22>30,"1-CRITICO",IF(O22>7,"2-URGENTE","3-NORMAL"))) -> 1-CRITICO | T22: =IF(A22="","",'DATA PENDIENTES'!O55) -> 24418800
A23: =IF('DATA PENDIENTES'!B56="","",'DATA PENDIENTES'!B56) -> SU111857 | B23: =IF(A23="","",'DATA PENDIENTES'!C56) -> FUELLE NEUMATICO EJE DE REMOLQUE | C23: =IF(A23="","",'DATA PENDIENTES'!L56) -> 7260108 | D23: =IF(A23="","",'DATA PENDIENTES'!J56) -> 954091 | E23: =IF(A23="","",'DATA PENDIENTES'!D56) -> 500 | F23: =IF(A23="","",'DATA PENDIENTES'!E56) -> UND | G23: =IF(A23="","",'DATA PENDIENTES'!F56) -> 450 | H23: =IF(A23="","",'DATA PENDIENTES'!G56) -> 50 | I23: =IF(A23="","",'DATA PENDIENTES'!H56) -> 173000 | J23: =IF(A23="","",IFERROR(H23*F23,0)) -> 0 | K23: =IF(A23="","",'DATA PENDIENTES'!I56) -> TC IMPORTACIONES S.A.S | L23: =IF(A23="","",'DATA PENDIENTES'!K56) -> CRISTHIAN BENITEZ | M23: =IF(A23="","",'DATA PENDIENTES'!M56) -> 46037 | N23: =IF(A23="","",'DATA PENDIENTES'!N56) -> 45709 | O23: =IF(A23="","",IFERROR(MAX(TODAY()-N23,0),0)) -> 410 | P23: =IF(A23="","",IF(H23=0,"COMPLETO",IF(H23<=E23*0.1,"CASI COMPLETO","PENDIENTE"))) -> CASI COMPLETO | Q23: =IF(A23="","",IFERROR(G23/E23,0)) -> 0.9 | R23: =IF(A23="","",IF(O23>30,"CRITICO",IF(O23>7,"ALERTA","OK"))) -> CRITICO | S23: =IF(A23="","",IF(O23>30,"1-CRITICO",IF(O23>7,"2-URGENTE","3-NORMAL"))) -> 1-CRITICO | T23: =IF(A23="","",'DATA PENDIENTES'!O56) -> 16435000
A24: =IF('DATA PENDIENTES'!B57="","",'DATA PENDIENTES'!B57) -> SU111857 | B24: =IF(A24="","",'DATA PENDIENTES'!C57) -> FUELLE NEUMATICO DELANTERO | C24: =IF(A24="","",'DATA PENDIENTES'!L57) -> 7260200 | D24: =IF(A24="","",'DATA PENDIENTES'!J57) -> 954089 | E24: =IF(A24="","",'DATA PENDIENTES'!D57) -> 260 | F24: =IF(A24="","",'DATA PENDIENTES'!E57) -> UND | G24: =IF(A24="","",'DATA PENDIENTES'!F57) -> 202 | H24: =IF(A24="","",'DATA PENDIENTES'!G57) -> 58 | I24: =IF(A24="","",'DATA PENDIENTES'!H57) -> 580000 | J24: =IF(A24="","",IFERROR(H24*F24,0)) -> 0 | K24: =IF(A24="","",'DATA PENDIENTES'!I57) -> TC IMPORTACIONES S.A.S | L24: =IF(A24="","",'DATA PENDIENTES'!K57) -> CRISTHIAN BENITEZ | M24: =IF(A24="","",'DATA PENDIENTES'!M57) -> 46037 | N24: =IF(A24="","",'DATA PENDIENTES'!N57) -> 45709 | O24: =IF(A24="","",IFERROR(MAX(TODAY()-N24,0),0)) -> 410 | P24: =IF(A24="","",IF(H24=0,"COMPLETO",IF(H24<=E24*0.1,"CASI COMPLETO","PENDIENTE"))) -> PENDIENTE | Q24: =IF(A24="","",IFERROR(G24/E24,0)) -> 0.77692308 | R24: =IF(A24="","",IF(O24>30,"CRITICO",IF(O24>7,"ALERTA","OK"))) -> CRITICO | S24: =IF(A24="","",IF(O24>30,"1-CRITICO",IF(O24>7,"2-URGENTE","3-NORMAL"))) -> 1-CRITICO | T24: =IF(A24="","",'DATA PENDIENTES'!O57) -> 28652000
A25: =IF('DATA PENDIENTES'!B4="","",'DATA PENDIENTES'!B4) -> SU114003 | B25: =IF(A25="","",'DATA PENDIENTES'!C4) -> RUEDA SENSORA | C25: =IF(A25="","",'DATA PENDIENTES'!L4) -> 7640210 | D25: =IF(A25="","",'DATA PENDIENTES'!J4) -> 22537018 | E25: =IF(A25="","",'DATA PENDIENTES'!D4) -> 312 | F25: =IF(A25="","",'DATA PENDIENTES'!E4) -> UND | G25: =IF(A25="","",'DATA PENDIENTES'!F4) -> 170 | H25: =IF(A25="","",'DATA PENDIENTES'!G4) -> 142 | I25: =IF(A25="","",'DATA PENDIENTES'!H4) -> 103221 | J25: =IF(A25="","",IFERROR(H25*F25,0)) -> 0 | K25: =IF(A25="","",'DATA PENDIENTES'!I4) -> VOLVO GROUP COLOMBIA S A S | L25: =IF(A25="","",'DATA PENDIENTES'!K4) -> CRISTHIAN BENITEZ | M25: =IF(A25="","",'DATA PENDIENTES'!M4) -> 46326 | N25: =IF(A25="","",'DATA PENDIENTES'!N4) -> 46265 | O25: =IF(A25="","",IFERROR(MAX(TODAY()-N25,0),0)) -> 0 | P25: =IF(A25="","",IF(H25=0,"COMPLETO",IF(H25<=E25*0.1,"CASI COMPLETO","PENDIENTE"))) -> PENDIENTE | Q25: =IF(A25="","",IFERROR(G25/E25,0)) -> 0.54487179 | R25: =IF(A25="","",IF(O25>30,"CRITICO",IF(O25>7,"ALERTA","OK"))) -> OK | S25: =IF(A25="","",IF(O25>30,"1-CRITICO",IF(O25>7,"2-URGENTE","3-NORMAL"))) -> 3-NORMAL | T25: =IF(A25="","",'DATA PENDIENTES'!O4) -> 6118941
A26: =IF('DATA PENDIENTES'!B7="","",'DATA PENDIENTES'!B7) -> SU114003 | B26: =IF(A26="","",'DATA PENDIENTES'!C7) -> RODAMIENTO CUBO RUEDA DE REMOLQUE | C26: =IF(A26="","",'DATA PENDIENTES'!L7) -> 7730306 | D26: =IF(A26="","",'DATA PENDIENTES'!J7) -> 21036050 | E26: =IF(A26="","",'DATA PENDIENTES'!D7) -> 360 | F26: =IF(A26="","",'DATA PENDIENTES'!E7) -> UND | G26: =IF(A26="","",'DATA PENDIENTES'!F7) -> 210 | H26: =IF(A26="","",'DATA PENDIENTES'!G7) -> 150 | I26: =IF(A26="","",'DATA PENDIENTES'!H7) -> 1554538 | J26: =IF(A26="","",IFERROR(H26*F26,0)) -> 0 | K26: =IF(A26="","",'DATA PENDIENTES'!I7) -> VOLVO GROUP COLOMBIA S A S | L26: =IF(A26="","",'DATA PENDIENTES'!K7) -> CRISTHIAN BENITEZ | M26: =IF(A26="","",'DATA PENDIENTES'!M7) -> 46326 | N26: =IF(A26="","",'DATA PENDIENTES'!N7) -> 46265 | O26: =IF(A26="","",IFERROR(MAX(TODAY()-N26,0),0)) -> 0 | P26: =IF(A26="","",IF(H26=0,"COMPLETO",IF(H26<=E26*0.1,"CASI COMPLETO","PENDIENTE"))) -> PENDIENTE | Q26: =IF(A26="","",IFERROR(G26/E26,0)) -> 0.58333333 | R26: =IF(A26="","",IF(O26>30,"CRITICO",IF(O26>7,"ALERTA","OK"))) -> OK | S26: =IF(A26="","",IF(O26>30,"1-CRITICO",IF(O26>7,"2-URGENTE","3-NORMAL"))) -> 3-NORMAL | T26: =IF(A26="","",'DATA PENDIENTES'!O7) -> 106000000
A27: =IF('DATA PENDIENTES'!B12="","",'DATA PENDIENTES'!B12) -> SU115941 | B27: =IF(A27="","",'DATA PENDIENTES'!C12) -> MANGUITO INYECTOR (CAMISILLA) | C27: =IF(A27="","",'DATA PENDIENTES'!L12) -> 12110008 | D27: =IF(A27="","",'DATA PENDIENTES'!J12) -> 21351717 | E27: =IF(A27="","",'DATA PENDIENTES'!D12) -> 60 | F27: =IF(A27="","",'DATA PENDIENTES'!E12) -> UND | G27: =IF(A27="","",'DATA PENDIENTES'!F12) -> 0 | H27: =IF(A27="","",'DATA PENDIENTES'!G12) -> 60 | I27: =IF(A27="","",'DATA PENDIENTES'!H12) -> 100898.6 | J27: =IF(A27="","",IFERROR(H27*F27,0)) -> 0 | K27: =IF(A27="","",'DATA PENDIENTES'!I12) -> VOLVO GROUP COLOMBIA S A S | L27: =IF(A27="","",'DATA PENDIENTES'!K12) -> CRISTHIAN BENITEZ | M27: =IF(A27="","",'DATA PENDIENTES'!M12) -> 46118 | N27: =IF(A27="","",'DATA PENDIENTES'!N12) -> 46108 | O27: =IF(A27="","",IFERROR(MAX(TODAY()-N27,0),0)) -> 11 | P27: =IF(A27="","",IF(H27=0,"COMPLETO",IF(H27<=E27*0.1,"CASI COMPLETO","PENDIENTE"))) -> PENDIENTE | Q27: =IF(A27="","",IFERROR(G27/E27,0)) -> 0 | R27: =IF(A27="","",IF(O27>30,"CRITICO",IF(O27>7,"ALERTA","OK"))) -> ALERTA | S27: =IF(A27="","",IF(O27>30,"1-CRITICO",IF(O27>7,"2-URGENTE","3-NORMAL"))) -> 2-URGENTE | T27: =IF(A27="","",'DATA PENDIENTES'!O12) -> 1150244
A28: =IF('DATA PENDIENTES'!B41="","",'DATA PENDIENTES'!B41) -> SU115942 | B28: =IF(A28="","",'DATA PENDIENTES'!C41) -> CASQUETE DE BANCADA STD | C28: =IF(A28="","",'DATA PENDIENTES'!L41) -> 12130004 | D28: =IF(A28="","",'DATA PENDIENTES'!J41) -> 23624058 | E28: =IF(A28="","",'DATA PENDIENTES'!D41) -> 21 | F28: =IF(A28="","",'DATA PENDIENTES'!E41) -> UND | G28: =IF(A28="","",'DATA PENDIENTES'!F41) -> 19 | H28: =IF(A28="","",'DATA PENDIENTES'!G41) -> 2 | I28: =IF(A28="","",'DATA PENDIENTES'!H41) -> 95724.33 | J28: =IF(A28="","",IFERROR(H28*F28,0)) -> 0 | K28: =IF(A28="","",'DATA PENDIENTES'!I41) -> VOLVO GROUP COLOMBIA S A S | L28: =IF(A28="","",'DATA PENDIENTES'!K41) -> CRISTHIAN BENITEZ | M28: =IF(A28="","",'DATA PENDIENTES'!M41) -> 46186 | N28: =IF(A28="","",'DATA PENDIENTES'!N41) -> 46119 | O28: =IF(A28="","",IFERROR(MAX(TODAY()-N28,0),0)) -> 0 | P28: =IF(A28="","",IF(H28=0,"COMPLETO",IF(H28<=E28*0.1,"CASI COMPLETO","PENDIENTE"))) -> CASI COMPLETO | Q28: =IF(A28="","",IFERROR(G28/E28,0)) -> 0.9047619 | R28: =IF(A28="","",IF(O28>30,"CRITICO",IF(O28>7,"ALERTA","OK"))) -> OK | S28: =IF(A28="","",IF(O28>30,"1-CRITICO",IF(O28>7,"2-URGENTE","3-NORMAL"))) -> 3-NORMAL | T28: =IF(A28="","",'DATA PENDIENTES'!O41) -> 381940.1
A29: =IF('DATA PENDIENTES'!B242="","",'DATA PENDIENTES'!B242) -> SU115872 | B29: =IF(A29="","",'DATA PENDIENTES'!C242) -> SILICONA ULTRA GREY LOCTITE 300 ML | C29: =IF(A29="","",'DATA PENDIENTES'!L242) -> 12220009 | D29: =IF(A29="","",'DATA PENDIENTES'!J242) | E29: =IF(A29="","",'DATA PENDIENTES'!D242) -> 2 | F29: =IF(A29="","",'DATA PENDIENTES'!E242) -> UND | G29: =IF(A29="","",'DATA PENDIENTES'!F242) -> 0 | H29: =IF(A29="","",'DATA PENDIENTES'!G242) -> 2 | I29: =IF(A29="","",'DATA PENDIENTES'!H242) -> 120232 | J29: =IF(A29="","",IFERROR(H29*F29,0)) -> 0 | K29: =IF(A29="","",'DATA PENDIENTES'!I242) -> COMERCIALIZADORA INTERNACIONAL ATR REPRESENTACIONES S.A | L29: =IF(A29="","",'DATA PENDIENTES'!K242) -> CRISTHIAN BENITEZ | M29: =IF(A29="","",'DATA PENDIENTES'!M242) -> 46113 | N29: =IF(A29="","",'DATA PENDIENTES'!N242) -> 46113 | O29: =IF(A29="","",IFERROR(MAX(TODAY()-N29,0),0)) -> 6 | P29: =IF(A29="","",IF(H29=0,"COMPLETO",IF(H29<=E29*0.1,"CASI COMPLETO","PENDIENTE"))) -> PENDIENTE | Q29: =IF(A29="","",IFERROR(G29/E29,0)) -> 0 | R29: =IF(A29="","",IF(O29>30,"CRITICO",IF(O29>7,"ALERTA","OK"))) -> OK | S29: =IF(A29="","",IF(O29>30,"1-CRITICO",IF(O29>7,"2-URGENTE","3-NORMAL"))) -> 3-NORMAL | T29: =IF(A29="","",'DATA PENDIENTES'!O242) -> 45688.16
A30: =IF('DATA PENDIENTES'!B8="","",'DATA PENDIENTES'!B8) -> SU115774 | B30: =IF(A30="","",'DATA PENDIENTES'!C8) -> ANILLO RETÉN | C30: =IF(A30="","",'DATA PENDIENTES'!L8) -> 12330019 | D30: =IF(A30="","",'DATA PENDIENTES'!J8) -> 8148471 | E30: =IF(A30="","",'DATA PENDIENTES'!D8) -> 4 | F30: =IF(A30="","",'DATA PENDIENTES'!E8) -> UND | G30: =IF(A30="","",'DATA PENDIENTES'!F8) -> 0 | H30: =IF(A30="","",'DATA PENDIENTES'!G8) -> 4 | I30: =IF(A30="","",'DATA PENDIENTES'!H8) -> 60598.23 | J30: =IF(A30="","",IFERROR(H30*F30,0)) -> 0 | K30: =IF(A30="","",'DATA PENDIENTES'!I8) -> VOLVO GROUP COLOMBIA S A S | L30: =IF(A30="","",'DATA PENDIENTES'!K8) -> CRISTHIAN BENITEZ | M30: =IF(A30="","",'DATA PENDIENTES'!M8) -> 46098 | N30: =IF(A30="","",'DATA PENDIENTES'!N8) -> 46098 | O30: =IF(A30="","",IFERROR(MAX(TODAY()-N30,0),0)) -> 21 | P30: =IF(A30="","",IF(H30=0,"COMPLETO",IF(H30<=E30*0.1,"CASI COMPLETO","PENDIENTE"))) -> PENDIENTE | Q30: =IF(A30="","",IFERROR(G30/E30,0)) -> 0 | R30: =IF(A30="","",IF(O30>30,"CRITICO",IF(O30>7,"ALERTA","OK"))) -> ALERTA | S30: =IF(A30="","",IF(O30>30,"1-CRITICO",IF(O30>7,"2-URGENTE","3-NORMAL"))) -> 2-URGENTE | T30: =IF(A30="","",'DATA PENDIENTES'!O8) -> 46054.65
A31: =IF('DATA PENDIENTES'!B42="","",'DATA PENDIENTES'!B42) -> SU115942 | B31: =IF(A31="","",'DATA PENDIENTES'!C42) -> ANILLO RETÉN | C31: =IF(A31="","",'DATA PENDIENTES'!L42) -> 12330019 | D31: =IF(A31="","",'DATA PENDIENTES'!J42) -> 8148471 | E31: =IF(A31="","",'DATA PENDIENTES'!D42) -> 5 | F31: =IF(A31="","",'DATA PENDIENTES'!E42) -> UND | G31: =IF(A31="","",'DATA PENDIENTES'!F42) -> 2 | H31: =IF(A31="","",'DATA PENDIENTES'!G42) -> 3 | I31: =IF(A31="","",'DATA PENDIENTES'!H42) -> 60982.68 | J31: =IF(A31="","",IFERROR(H31*F31,0)) -> 0 | K31: =IF(A31="","",'DATA PENDIENTES'!I42) -> VOLVO GROUP COLOMBIA S A S | L31: =IF(A31="","",'DATA PENDIENTES'!K42) -> CRISTHIAN BENITEZ | M31: =IF(A31="","",'DATA PENDIENTES'!M42) -> 46186 | N31: =IF(A31="","",'DATA PENDIENTES'!N42) -> 46119 | O31: =IF(A31="","",IFERROR(MAX(TODAY()-N31,0),0)) -> 0 | P31: =IF(A31="","",IF(H31=0,"COMPLETO",IF(H31<=E31*0.1,"CASI COMPLETO","PENDIENTE"))) -> PENDIENTE | Q31: =IF(A31="","",IFERROR(G31/E31,0)) -> 0.4 | R31: =IF(A31="","",IF(O31>30,"CRITICO",IF(O31>7,"ALERTA","OK"))) -> OK | S31: =IF(A31="","",IF(O31>30,"1-CRITICO",IF(O31>7,"2-URGENTE","3-NORMAL"))) -> 3-NORMAL | T31: =IF(A31="","",'DATA PENDIENTES'!O42) -> 57933.55
A32: =IF('DATA PENDIENTES'!B44="","",'DATA PENDIENTES'!B44) -> SU115951 | B32: =IF(A32="","",'DATA PENDIENTES'!C44) -> SENSOR DE PRESION FILTRO PARTICULAS | C32: =IF(A32="","",'DATA PENDIENTES'!L44) -> 12540029 | D32: =IF(A32="","",'DATA PENDIENTES'!J44) -> 20733099 | E32: =IF(A32="","",'DATA PENDIENTES'!D44) -> 2 | F32: =IF(A32="","",'DATA PENDIENTES'!E44) -> UND | G32: =IF(A32="","",'DATA PENDIENTES'!F44) -> 0 | H32: =IF(A32="","",'DATA PENDIENTES'!G44) -> 2 | I32: =IF(A32="","",'DATA PENDIENTES'!H44) -> 831582 | J32: =IF(A32="","",IFERROR(H32*F32,0)) -> 0 | K32: =IF(A32="","",'DATA PENDIENTES'!I44) -> VOLVO GROUP COLOMBIA S A S | L32: =IF(A32="","",'DATA PENDIENTES'!K44) -> CRISTHIAN BENITEZ | M32: =IF(A32="","",'DATA PENDIENTES'!M44) -> 46122 | N32: =IF(A32="","",'DATA PENDIENTES'!N44) -> 46120 | O32: =IF(A32="","",IFERROR(MAX(TODAY()-N32,0),0)) -> 0 | P32: =IF(A32="","",IF(H32=0,"COMPLETO",IF(H32<=E32*0.1,"CASI COMPLETO","PENDIENTE"))) -> PENDIENTE | Q32: =IF(A32="","",IFERROR(G32/E32,0)) -> 0 | R32: =IF(A32="","",IF(O32>30,"CRITICO",IF(O32>7,"ALERTA","OK"))) -> OK | S32: =IF(A32="","",IF(O32>30,"1-CRITICO",IF(O32>7,"2-URGENTE","3-NORMAL"))) -> 3-NORMAL | T32: =IF(A32="","",'DATA PENDIENTES'!O44) -> 316001.2
A33: =IF('DATA PENDIENTES'!B10="","",'DATA PENDIENTES'!B10) -> SU115897 | B33: =IF(A33="","",'DATA PENDIENTES'!C10) -> VALVULA EPG | C33: =IF(A33="","",'DATA PENDIENTES'!L10) -> 12540034 | D33: =IF(A33="","",'DATA PENDIENTES'!J10) -> 24122364 | E33: =IF(A33="","",'DATA PENDIENTES'!D10) -> 1 | F33: =IF(A33="","",'DATA PENDIENTES'!E10) -> UND | G33: =IF(A33="","",'DATA PENDIENTES'!F10) -> 0 | H33: =IF(A33="","",'DATA PENDIENTES'!G10) -> 1 | I33: =IF(A33="","",'DATA PENDIENTES'!H10) -> 1027415 | J33: =IF(A33="","",IFERROR(H33*F33,0)) -> 0 | K33: =IF(A33="","",'DATA PENDIENTES'!I10) -> VOLVO GROUP COLOMBIA S A S | L33: =IF(A33="","",'DATA PENDIENTES'!K10) -> CRISTHIAN BENITEZ | M33: =IF(A33="","",'DATA PENDIENTES'!M10) -> 46109 | N33: =IF(A33="","",'DATA PENDIENTES'!N10) -> 46109 | O33: =IF(A33="","",IFERROR(MAX(TODAY()-N33,0),0)) -> 10 | P33: =IF(A33="","",IF(H33=0,"COMPLETO",IF(H33<=E33*0.1,"CASI COMPLETO","PENDIENTE"))) -> PENDIENTE | Q33: =IF(A33="","",IFERROR(G33/E33,0)) -> 0 | R33: =IF(A33="","",IF(O33>30,"CRITICO",IF(O33>7,"ALERTA","OK"))) -> ALERTA | S33: =IF(A33="","",IF(O33>30,"1-CRITICO",IF(O33>7,"2-URGENTE","3-NORMAL"))) -> 2-URGENTE | T33: =IF(A33="","",'DATA PENDIENTES'!O10) -> 195208.9
A34: =IF('DATA PENDIENTES'!B254="","",'DATA PENDIENTES'!B254) -> SU115902 | B34: =IF(A34="","",'DATA PENDIENTES'!C254) -> MANGUERA LONADA 3/8 PARKER | C34: =IF(A34="","",'DATA PENDIENTES'!L254) -> 12630023 | D34: =IF(A34="","",'DATA PENDIENTES'!J254) -> CTP0489 | E34: =IF(A34="","",'DATA PENDIENTES'!D254) -> 300 | F34: =IF(A34="","",'DATA PENDIENTES'!E254) -> M | G34: =IF(A34="","",'DATA PENDIENTES'!F254) -> 0 | H34: =IF(A34="","",'DATA PENDIENTES'!G254) -> 300 | I34: =IF(A34="","",'DATA PENDIENTES'!H254) -> 11340 | J34: =IF(A34="","",IFERROR(H34*F34,0)) -> 0 | K34: =IF(A34="","",'DATA PENDIENTES'!I254) -> COMERCIALIZADORA DE AUTOPARTES E INDUSTRIAL UNIVERSAL SAS | L34: =IF(A34="","",'DATA PENDIENTES'!K254) -> CRISTHIAN BENITEZ | M34: =IF(A34="","",'DATA PENDIENTES'!M254) -> 46113 | N34: =IF(A34="","",'DATA PENDIENTES'!N254) -> 46108 | O34: =IF(A34="","",IFERROR(MAX(TODAY()-N34,0),0)) -> 11 | P34: =IF(A34="","",IF(H34=0,"COMPLETO",IF(H34<=E34*0.1,"CASI COMPLETO","PENDIENTE"))) -> PENDIENTE | Q34: =IF(A34="","",IFERROR(G34/E34,0)) -> 0 | R34: =IF(A34="","",IF(O34>30,"CRITICO",IF(O34>7,"ALERTA","OK"))) -> ALERTA | S34: =IF(A34="","",IF(O34>30,"1-CRITICO",IF(O34>7,"2-URGENTE","3-NORMAL"))) -> 2-URGENTE | T34: =IF(A34="","",'DATA PENDIENTES'!O254) -> 646380
A35: =IF('DATA PENDIENTES'!B13="","",'DATA PENDIENTES'!B13) -> SU115941 | B35: =IF(A35="","",'DATA PENDIENTES'!C13) -> MANGUERA DE REFRIGERACION RADIADOR | C35: =IF(A35="","",'DATA PENDIENTES'!L13) -> 12630024 | D35: =IF(A35="","",'DATA PENDIENTES'!J13) -> 22129907 | E35: =IF(A35="","",'DATA PENDIENTES'!D13) -> 40 | F35: =IF(A35="","",'DATA PENDIENTES'!E13) -> UND | G35: =IF(A35="","",'DATA PENDIENTES'!F13) -> 0 | H35: =IF(A35="","",'DATA PENDIENTES'!G13) -> 40 | I35: =IF(A35="","",'DATA PENDIENTES'!H13) -> 141368.9 | J35: =IF(A35="","",IFERROR(H35*F35,0)) -> 0 | K35: =IF(A35="","",'DATA PENDIENTES'!I13) -> VOLVO GROUP COLOMBIA S A S | L35: =IF(A35="","",'DATA PENDIENTES'!K13) -> CRISTHIAN BENITEZ | M35: =IF(A35="","",'DATA PENDIENTES'!M13) -> 46118 | N35: =IF(A35="","",'DATA PENDIENTES'!N13) -> 46108 | O35: =IF(A35="","",IFERROR(MAX(TODAY()-N35,0),0)) -> 11 | P35: =IF(A35="","",IF(H35=0,"COMPLETO",IF(H35<=E35*0.1,"CASI COMPLETO","PENDIENTE"))) -> PENDIENTE | Q35: =IF(A35="","",IFERROR(G35/E35,0)) -> 0 | R35: =IF(A35="","",IF(O35>30,"CRITICO",IF(O35>7,"ALERTA","OK"))) -> ALERTA | S35: =IF(A35="","",IF(O35>30,"1-CRITICO",IF(O35>7,"2-URGENTE","3-NORMAL"))) -> 2-URGENTE | T35: =IF(A35="","",'DATA PENDIENTES'!O13) -> 1074404
A36: =IF('DATA PENDIENTES'!B14="","",'DATA PENDIENTES'!B14) -> SU115941 | B36: =IF(A36="","",'DATA PENDIENTES'!C14) -> MANGUERA DE REFRIGERACION RADIADOR | C36: =IF(A36="","",'DATA PENDIENTES'!L14) -> 12630025 | D36: =IF(A36="","",'DATA PENDIENTES'!J14) -> 22129120 | E36: =IF(A36="","",'DATA PENDIENTES'!D14) -> 60 | F36: =IF(A36="","",'DATA PENDIENTES'!E14) -> UND | G36: =IF(A36="","",'DATA PENDIENTES'!F14) -> 0 | H36: =IF(A36="","",'DATA PENDIENTES'!G14) -> 60 | I36: =IF(A36="","",'DATA PENDIENTES'!H14) -> 133053.1 | J36: =IF(A36="","",IFERROR(H36*F36,0)) -> 0 | K36: =IF(A36="","",'DATA PENDIENTES'!I14) -> VOLVO GROUP COLOMBIA S A S | L36: =IF(A36="","",'DATA PENDIENTES'!K14) -> CRISTHIAN BENITEZ | M36: =IF(A36="","",'DATA PENDIENTES'!M14) -> 46118 | N36: =IF(A36="","",'DATA PENDIENTES'!N14) -> 46108 | O36: =IF(A36="","",IFERROR(MAX(TODAY()-N36,0),0)) -> 11 | P36: =IF(A36="","",IF(H36=0,"COMPLETO",IF(H36<=E36*0.1,"CASI COMPLETO","PENDIENTE"))) -> PENDIENTE | Q36: =IF(A36="","",IFERROR(G36/E36,0)) -> 0 | R36: =IF(A36="","",IF(O36>30,"CRITICO",IF(O36>7,"ALERTA","OK"))) -> ALERTA | S36: =IF(A36="","",IF(O36>30,"1-CRITICO",IF(O36>7,"2-URGENTE","3-NORMAL"))) -> 2-URGENTE | T36: =IF(A36="","",'DATA PENDIENTES'!O14) -> 1516806
A37: =IF('DATA PENDIENTES'!B15="","",'DATA PENDIENTES'!B15) -> SU115941 | B37: =IF(A37="","",'DATA PENDIENTES'!C15) -> MANGUERA DE REFRIGERACION COMPRESOR ØEXT 18MM ØINT 13MM | C37: =IF(A37="","",'DATA PENDIENTES'!L15) -> 12630027 | D37: =IF(A37="","",'DATA PENDIENTES'!J15) -> 21339891 | E37: =IF(A37="","",'DATA PENDIENTES'!D15) -> 40 | F37: =IF(A37="","",'DATA PENDIENTES'!E15) -> UND | G37: =IF(A37="","",'DATA PENDIENTES'!F15) -> 0 | H37: =IF(A37="","",'DATA PENDIENTES'!G15) -> 40 | I37: =IF(A37="","",'DATA PENDIENTES'!H15) -> 69298.5 | J37: =IF(A37="","",IFERROR(H37*F37,0)) -> 0 | K37: =IF(A37="","",'DATA PENDIENTES'!I15) -> VOLVO GROUP COLOMBIA S A S | L37: =IF(A37="","",'DATA PENDIENTES'!K15) -> CRISTHIAN BENITEZ | M37: =IF(A37="","",'DATA PENDIENTES'!M15) -> 46118 | N37: =IF(A37="","",'DATA PENDIENTES'!N15) -> 46108 | O37: =IF(A37="","",IFERROR(MAX(TODAY()-N37,0),0)) -> 11 | P37: =IF(A37="","",IF(H37=0,"COMPLETO",IF(H37<=E37*0.1,"CASI COMPLETO","PENDIENTE"))) -> PENDIENTE | Q37: =IF(A37="","",IFERROR(G37/E37,0)) -> 0 | R37: =IF(A37="","",IF(O37>30,"CRITICO",IF(O37>7,"ALERTA","OK"))) -> ALERTA | S37: =IF(A37="","",IF(O37>30,"1-CRITICO",IF(O37>7,"2-URGENTE","3-NORMAL"))) -> 2-URGENTE | T37: =IF(A37="","",'DATA PENDIENTES'!O15) -> 526668.6
A38: =IF('DATA PENDIENTES'!B16="","",'DATA PENDIENTES'!B16) -> SU115941 | B38: =IF(A38="","",'DATA PENDIENTES'!C16) -> MANGUERA DE UNION LARGA | C38: =IF(A38="","",'DATA PENDIENTES'!L16) -> 12630028 | D38: =IF(A38="","",'DATA PENDIENTES'!J16) -> 22417892 | E38: =IF(A38="","",'DATA PENDIENTES'!D16) -> 30 | F38: =IF(A38="","",'DATA PENDIENTES'!E16) -> UND | G38: =IF(A38="","",'DATA PENDIENTES'!F16) -> 0 | H38: =IF(A38="","",'DATA PENDIENTES'!G16) -> 30 | I38: =IF(A38="","",'DATA PENDIENTES'!H16) -> 97017.9 | J38: =IF(A38="","",IFERROR(H38*F38,0)) -> 0 | K38: =IF(A38="","",'DATA PENDIENTES'!I16) -> VOLVO GROUP COLOMBIA S A S | L38: =IF(A38="","",'DATA PENDIENTES'!K16) -> CRISTHIAN BENITEZ | M38: =IF(A38="","",'DATA PENDIENTES'!M16) -> 46118 | N38: =IF(A38="","",'DATA PENDIENTES'!N16) -> 46108 | O38: =IF(A38="","",IFERROR(MAX(TODAY()-N38,0),0)) -> 11 | P38: =IF(A38="","",IF(H38=0,"COMPLETO",IF(H38<=E38*0.1,"CASI COMPLETO","PENDIENTE"))) -> PENDIENTE | Q38: =IF(A38="","",IFERROR(G38/E38,0)) -> 0 | R38: =IF(A38="","",IF(O38>30,"CRITICO",IF(O38>7,"ALERTA","OK"))) -> ALERTA | S38: =IF(A38="","",IF(O38>30,"1-CRITICO",IF(O38>7,"2-URGENTE","3-NORMAL"))) -> 2-URGENTE | T38: =IF(A38="","",'DATA PENDIENTES'!O16) -> 553002
A39: =IF('DATA PENDIENTES'!B17="","",'DATA PENDIENTES'!B17) -> SU115941 | B39: =IF(A39="","",'DATA PENDIENTES'!C17) -> MANGUERA DE UNION CORTA | C39: =IF(A39="","",'DATA PENDIENTES'!L17) -> 12630029 | D39: =IF(A39="","",'DATA PENDIENTES'!J17) -> 24288019 | E39: =IF(A39="","",'DATA PENDIENTES'!D17) -> 120 | F39: =IF(A39="","",'DATA PENDIENTES'!E17) -> UND | G39: =IF(A39="","",'DATA PENDIENTES'!F17) -> 0 | H39: =IF(A39="","",'DATA PENDIENTES'!G17) -> 120 | I39: =IF(A39="","",'DATA PENDIENTES'!H17) -> 77614.32 | J39: =IF(A39="","",IFERROR(H39*F39,0)) -> 0 | K39: =IF(A39="","",'DATA PENDIENTES'!I17) -> VOLVO GROUP COLOMBIA S A S | L39: =IF(A39="","",'DATA PENDIENTES'!K17) -> CRISTHIAN BENITEZ | M39: =IF(A39="","",'DATA PENDIENTES'!M17) -> 46118 | N39: =IF(A39="","",'DATA PENDIENTES'!N17) -> 46108 | O39: =IF(A39="","",IFERROR(MAX(TODAY()-N39,0),0)) -> 11 | P39: =IF(A39="","",IF(H39=0,"COMPLETO",IF(H39<=E39*0.1,"CASI COMPLETO","PENDIENTE"))) -> PENDIENTE | Q39: =IF(A39="","",IFERROR(G39/E39,0)) -> 0 | R39: =IF(A39="","",IF(O39>30,"CRITICO",IF(O39>7,"ALERTA","OK"))) -> ALERTA | S39: =IF(A39="","",IF(O39>30,"1-CRITICO",IF(O39>7,"2-URGENTE","3-NORMAL"))) -> 2-URGENTE | T39: =IF(A39="","",'DATA PENDIENTES'!O17) -> 1769606
A40: =IF('DATA PENDIENTES'!B18="","",'DATA PENDIENTES'!B18) -> SU115941 | B40: =IF(A40="","",'DATA PENDIENTES'!C18) -> MANGUERA EN S TANQUE DE EXPANSION | C40: =IF(A40="","",'DATA PENDIENTES'!L18) -> 12630031 | D40: =IF(A40="","",'DATA PENDIENTES'!J18) -> 22420663 | E40: =IF(A40="","",'DATA PENDIENTES'!D18) -> 60 | F40: =IF(A40="","",'DATA PENDIENTES'!E18) -> UND | G40: =IF(A40="","",'DATA PENDIENTES'!F18) -> 0 | H40: =IF(A40="","",'DATA PENDIENTES'!G18) -> 60 | I40: =IF(A40="","",'DATA PENDIENTES'!H18) -> 83158.2 | J40: =IF(A40="","",IFERROR(H40*F40,0)) -> 0 | K40: =IF(A40="","",'DATA PENDIENTES'!I18) -> VOLVO GROUP COLOMBIA S A S | L40: =IF(A40="","",'DATA PENDIENTES'!K18) -> CRISTHIAN BENITEZ | M40: =IF(A40="","",'DATA PENDIENTES'!M18) -> 46118 | N40: =IF(A40="","",'DATA PENDIENTES'!N18) -> 46108 | O40: =IF(A40="","",IFERROR(MAX(TODAY()-N40,0),0)) -> 11 | P40: =IF(A40="","",IF(H40=0,"COMPLETO",IF(H40<=E40*0.1,"CASI COMPLETO","PENDIENTE"))) -> PENDIENTE | Q40: =IF(A40="","",IFERROR(G40/E40,0)) -> 0 | R40: =IF(A40="","",IF(O40>30,"CRITICO",IF(O40>7,"ALERTA","OK"))) -> ALERTA | S40: =IF(A40="","",IF(O40>30,"1-CRITICO",IF(O40>7,"2-URGENTE","3-NORMAL"))) -> 2-URGENTE | T40: =IF(A40="","",'DATA PENDIENTES'!O18) -> 948003.5
A41: =IF('DATA PENDIENTES'!B19="","",'DATA PENDIENTES'!B19) -> SU115941 | B41: =IF(A41="","",'DATA PENDIENTES'!C19) -> ABRAZADERA DE MANGUERA CON TORNILLO SINFÍN Ø 75MM | C41: =IF(A41="","",'DATA PENDIENTES'!L19) -> 12630033 | D41: =IF(A41="","",'DATA PENDIENTES'!J19) -> 994565 | E41: =IF(A41="","",'DATA PENDIENTES'!D19) -> 100 | F41: =IF(A41="","",'DATA PENDIENTES'!E19) -> UND | G41: =IF(A41="","",'DATA PENDIENTES'!F19) -> 0 | H41: =IF(A41="","",'DATA PENDIENTES'!G19) -> 100 | I41: =IF(A41="","",'DATA PENDIENTES'!H19) -> 6763.53 | J41: =IF(A41="","",IFERROR(H41*F41,0)) -> 0 | K41: =IF(A41="","",'DATA PENDIENTES'!I19) -> VOLVO GROUP COLOMBIA S A S | L41: =IF(A41="","",'DATA PENDIENTES'!K19) -> CRISTHIAN BENITEZ | M41: =IF(A41="","",'DATA PENDIENTES'!M19) -> 46118 | N41: =IF(A41="","",'DATA PENDIENTES'!N19) -> 46108 | O41: =IF(A41="","",IFERROR(MAX(TODAY()-N41,0),0)) -> 11 | P41: =IF(A41="","",IF(H41=0,"COMPLETO",IF(H41<=E41*0.1,"CASI COMPLETO","PENDIENTE"))) -> PENDIENTE | Q41: =IF(A41="","",IFERROR(G41/E41,0)) -> 0 | R41: =IF(A41="","",IF(O41>30,"CRITICO",IF(O41>7,"ALERTA","OK"))) -> ALERTA | S41: =IF(A41="","",IF(O41>30,"1-CRITICO",IF(O41>7,"2-URGENTE","3-NORMAL"))) -> 2-URGENTE | T41: =IF(A41="","",'DATA PENDIENTES'!O19) -> 128507.1
A42: =IF('DATA PENDIENTES'!B20="","",'DATA PENDIENTES'!B20) -> SU115941 | B42: =IF(A42="","",'DATA PENDIENTES'!C20) -> ABRAZADERA DE MANGUERA CON TORNILLO SINFÍN Ø 66MM | C42: =IF(A42="","",'DATA PENDIENTES'!L20) -> 12630034 | D42: =IF(A42="","",'DATA PENDIENTES'!J20) -> 994564 | E42: =IF(A42="","",'DATA PENDIENTES'!D20) -> 600 | F42: =IF(A42="","",'DATA PENDIENTES'!E20) -> UND | G42: =IF(A42="","",'DATA PENDIENTES'!F20) -> 0 | H42: =IF(A42="","",'DATA PENDIENTES'!G20) -> 600 | I42: =IF(A42="","",'DATA PENDIENTES'!H20) -> 5904.23 | J42: =IF(A42="","",IFERROR(H42*F42,0)) -> 0 | K42: =IF(A42="","",'DATA PENDIENTES'!I20) -> VOLVO GROUP COLOMBIA S A S | L42: =IF(A42="","",'DATA PENDIENTES'!K20) -> CRISTHIAN BENITEZ | M42: =IF(A42="","",'DATA PENDIENTES'!M20) -> 46118 | N42: =IF(A42="","",'DATA PENDIENTES'!N20) -> 46108 | O42: =IF(A42="","",IFERROR(MAX(TODAY()-N42,0),0)) -> 11 | P42: =IF(A42="","",IF(H42=0,"COMPLETO",IF(H42<=E42*0.1,"CASI COMPLETO","PENDIENTE"))) -> PENDIENTE | Q42: =IF(A42="","",IFERROR(G42/E42,0)) -> 0 | R42: =IF(A42="","",IF(O42>30,"CRITICO",IF(O42>7,"ALERTA","OK"))) -> ALERTA | S42: =IF(A42="","",IF(O42>30,"1-CRITICO",IF(O42>7,"2-URGENTE","3-NORMAL"))) -> 2-URGENTE | T42: =IF(A42="","",'DATA PENDIENTES'!O20) -> 673082.2
A43: =IF('DATA PENDIENTES'!B21="","",'DATA PENDIENTES'!B21) -> SU115941 | B43: =IF(A43="","",'DATA PENDIENTES'!C21) -> ABRAZADERA DE MANGUERA CON TORNILLO SINFÍN Ø 15MM | C43: =IF(A43="","",'DATA PENDIENTES'!L21) -> 12630035 | D43: =IF(A43="","",'DATA PENDIENTES'!J21) -> 994557 | E43: =IF(A43="","",'DATA PENDIENTES'!D21) -> 300 | F43: =IF(A43="","",'DATA PENDIENTES'!E21) -> UND | G43: =IF(A43="","",'DATA PENDIENTES'!F21) -> 0 | H43: =IF(A43="","",'DATA PENDIENTES'!G21) -> 300 | I43: =IF(A43="","",'DATA PENDIENTES'!H21) -> 4241.07 | J43: =IF(A43="","",IFERROR(H43*F43,0)) -> 0 | K43: =IF(A43="","",'DATA PENDIENTES'!I21) -> VOLVO GROUP COLOMBIA S A S | L43: =IF(A43="","",'DATA PENDIENTES'!K21) -> CRISTHIAN BENITEZ | M43: =IF(A43="","",'DATA PENDIENTES'!M21) -> 46118 | N43: =IF(A43="","",'DATA PENDIENTES'!N21) -> 46108 | O43: =IF(A43="","",IFERROR(MAX(TODAY()-N43,0),0)) -> 11 | P43: =IF(A43="","",IF(H43=0,"COMPLETO",IF(H43<=E43*0.1,"CASI COMPLETO","PENDIENTE"))) -> PENDIENTE | Q43: =IF(A43="","",IFERROR(G43/E43,0)) -> 0 | R43: =IF(A43="","",IF(O43>30,"CRITICO",IF(O43>7,"ALERTA","OK"))) -> ALERTA | S43: =IF(A43="","",IF(O43>30,"1-CRITICO",IF(O43>7,"2-URGENTE","3-NORMAL"))) -> 2-URGENTE | T43: =IF(A43="","",'DATA PENDIENTES'!O21) -> 241741
A44: =IF('DATA PENDIENTES'!B22="","",'DATA PENDIENTES'!B22) -> SU115941 | B44: =IF(A44="","",'DATA PENDIENTES'!C22) -> ABRAZADERA DE MANGUERA CON TORNILLO SINFÍN Ø 45MM | C44: =IF(A44="","",'DATA PENDIENTES'!L22) -> 12630036 | D44: =IF(A44="","",'DATA PENDIENTES'!J22) -> 984996 | E44: =IF(A44="","",'DATA PENDIENTES'!D22) -> 120 | F44: =IF(A44="","",'DATA PENDIENTES'!E22) -> UND | G44: =IF(A44="","",'DATA PENDIENTES'!F22) -> 0 | H44: =IF(A44="","",'DATA PENDIENTES'!G22) -> 120 | I44: =IF(A44="","",'DATA PENDIENTES'!H22) -> 7317.92 | J44: =IF(A44="","",IFERROR(H44*F44,0)) -> 0 | K44: =IF(A44="","",'DATA PENDIENTES'!I22) -> VOLVO GROUP COLOMBIA S A S | L44: =IF(A44="","",'DATA PENDIENTES'!K22) -> CRISTHIAN BENITEZ | M44: =IF(A44="","",'DATA PENDIENTES'!M22) -> 46118 | N44: =IF(A44="","",'DATA PENDIENTES'!N22) -> 46108 | O44: =IF(A44="","",IFERROR(MAX(TODAY()-N44,0),0)) -> 11 | P44: =IF(A44="","",IF(H44=0,"COMPLETO",IF(H44<=E44*0.1,"CASI COMPLETO","PENDIENTE"))) -> PENDIENTE | Q44: =IF(A44="","",IFERROR(G44/E44,0)) -> 0 | R44: =IF(A44="","",IF(O44>30,"CRITICO",IF(O44>7,"ALERTA","OK"))) -> ALERTA | S44: =IF(A44="","",IF(O44>30,"1-CRITICO",IF(O44>7,"2-URGENTE","3-NORMAL"))) -> 2-URGENTE | T44: =IF(A44="","",'DATA PENDIENTES'!O22) -> 166848.6
A45: =IF('DATA PENDIENTES'!B23="","",'DATA PENDIENTES'!B23) -> SU115941 | B45: =IF(A45="","",'DATA PENDIENTES'!C23) -> ABRAZADERA DE MANGUERA CON TORNILLO SINFÍN Ø 22MM | C45: =IF(A45="","",'DATA PENDIENTES'!L23) -> 12630037 | D45: =IF(A45="","",'DATA PENDIENTES'!J23) -> 984993 | E45: =IF(A45="","",'DATA PENDIENTES'!D23) -> 600 | F45: =IF(A45="","",'DATA PENDIENTES'!E23) -> UND | G45: =IF(A45="","",'DATA PENDIENTES'!F23) -> 0 | H45: =IF(A45="","",'DATA PENDIENTES'!G23) -> 600 | I45: =IF(A45="","",'DATA PENDIENTES'!H23) -> 5128.09 | J45: =IF(A45="","",IFERROR(H45*F45,0)) -> 0 | K45: =IF(A45="","",'DATA PENDIENTES'!I23) -> VOLVO GROUP COLOMBIA S A S | L45: =IF(A45="","",'DATA PENDIENTES'!K23) -> CRISTHIAN BENITEZ | M45: =IF(A45="","",'DATA PENDIENTES'!M23) -> 46118 | N45: =IF(A45="","",'DATA PENDIENTES'!N23) -> 46108 | O45: =IF(A45="","",IFERROR(MAX(TODAY()-N45,0),0)) -> 11 | P45: =IF(A45="","",IF(H45=0,"COMPLETO",IF(H45<=E45*0.1,"CASI COMPLETO","PENDIENTE"))) -> PENDIENTE | Q45: =IF(A45="","",IFERROR(G45/E45,0)) -> 0 | R45: =IF(A45="","",IF(O45>30,"CRITICO",IF(O45>7,"ALERTA","OK"))) -> ALERTA | S45: =IF(A45="","",IF(O45>30,"1-CRITICO",IF(O45>7,"2-URGENTE","3-NORMAL"))) -> 2-URGENTE | T45: =IF(A45="","",'DATA PENDIENTES'!O23) -> 584602.3
A46: =IF('DATA PENDIENTES'!B24="","",'DATA PENDIENTES'!B24) -> SU115941 | B46: =IF(A46="","",'DATA PENDIENTES'!C24) -> MANGUERA DE REFRIGERACION TURBO | C46: =IF(A46="","",'DATA PENDIENTES'!L24) -> 12630038 | D46: =IF(A46="","",'DATA PENDIENTES'!J24) -> 425940 | E46: =IF(A46="","",'DATA PENDIENTES'!D24) -> 100 | F46: =IF(A46="","",'DATA PENDIENTES'!E24) -> UND | G46: =IF(A46="","",'DATA PENDIENTES'!F24) -> 0 | H46: =IF(A46="","",'DATA PENDIENTES'!G24) -> 100 | I46: =IF(A46="","",'DATA PENDIENTES'!H24) -> 36035.22 | J46: =IF(A46="","",IFERROR(H46*F46,0)) -> 0 | K46: =IF(A46="","",'DATA PENDIENTES'!I24) -> VOLVO GROUP COLOMBIA S A S | L46: =IF(A46="","",'DATA PENDIENTES'!K24) -> CRISTHIAN BENITEZ | M46: =IF(A46="","",'DATA PENDIENTES'!M24) -> 46118 | N46: =IF(A46="","",'DATA PENDIENTES'!N24) -> 46108 | O46: =IF(A46="","",IFERROR(MAX(TODAY()-N46,0),0)) -> 11 | P46: =IF(A46="","",IF(H46=0,"COMPLETO",IF(H46<=E46*0.1,"CASI COMPLETO","PENDIENTE"))) -> PENDIENTE | Q46: =IF(A46="","",IFERROR(G46/E46,0)) -> 0 | R46: =IF(A46="","",IF(O46>30,"CRITICO",IF(O46>7,"ALERTA","OK"))) -> ALERTA | S46: =IF(A46="","",IF(O46>30,"1-CRITICO",IF(O46>7,"2-URGENTE","3-NORMAL"))) -> 2-URGENTE | T46: =IF(A46="","",'DATA PENDIENTES'!O24) -> 684669.2
A47: =IF('DATA PENDIENTES'!B143="","",'DATA PENDIENTES'!B143) -> SU112988 | B47: =IF(A47="","",'DATA PENDIENTES'!C143) -> TANQUE DE EXPANSIÓN | C47: =IF(A47="","",'DATA PENDIENTES'!L143) -> 12630042 | D47: =IF(A47="","",'DATA PENDIENTES'!J143) -> DT8020005 | E47: =IF(A47="","",'DATA PENDIENTES'!D143) -> 60 | F47: =IF(A47="","",'DATA PENDIENTES'!E143) -> UND | G47: =IF(A47="","",'DATA PENDIENTES'!F143) -> 22 | H47: =IF(A47="","",'DATA PENDIENTES'!G143) -> 38 | I47: =IF(A47="","",'DATA PENDIENTES'!H143) -> 410000 | J47: =IF(A47="","",IFERROR(H47*F47,0)) -> 0 | K47: =IF(A47="","",'DATA PENDIENTES'!I143) -> MAQUITECNICOS IMPORTADORES SAS | L47: =IF(A47="","",'DATA PENDIENTES'!K143) -> CRISTHIAN BENITEZ | M47: =IF(A47="","",'DATA PENDIENTES'!M143) -> 46172 | N47: =IF(A47="","",'DATA PENDIENTES'!N143) -> 46173 | O47: =IF(A47="","",IFERROR(MAX(TODAY()-N47,0),0)) -> 0 | P47: =IF(A47="","",IF(H47=0,"COMPLETO",IF(H47<=E47*0.1,"CASI COMPLETO","PENDIENTE"))) -> PENDIENTE | Q47: =IF(A47="","",IFERROR(G47/E47,0)) -> 0.36666667 | R47: =IF(A47="","",IF(O47>30,"CRITICO",IF(O47>7,"ALERTA","OK"))) -> OK | S47: =IF(A47="","",IF(O47>30,"1-CRITICO",IF(O47>7,"2-URGENTE","3-NORMAL"))) -> 3-NORMAL | T47: =IF(A47="","",'DATA PENDIENTES'!O143) -> 4674000
A48: =IF('DATA PENDIENTES'!B151="","",'DATA PENDIENTES'!B151) -> SU114827 | B48: =IF(A48="","",'DATA PENDIENTES'!C151) -> ALTERNADOR | C48: =IF(A48="","",'DATA PENDIENTES'!L151) -> 13210008 | D48: =IF(A48="","",'DATA PENDIENTES'!J151) -> DT1115-2.21049 | E48: =IF(A48="","",'DATA PENDIENTES'!D151) -> 231 | F48: =IF(A48="","",'DATA PENDIENTES'!E151) -> UND | G48: =IF(A48="","",'DATA PENDIENTES'!F151) -> 147 | H48: =IF(A48="","",'DATA PENDIENTES'!G151) -> 84 | I48: =IF(A48="","",'DATA PENDIENTES'!H151) -> 1250000 | J48: =IF(A48="","",IFERROR(H48*F48,0)) -> 0 | K48: =IF(A48="","",'DATA PENDIENTES'!I151) -> INNOVATEQ S. A.S | L48: =IF(A48="","",'DATA PENDIENTES'!K151) -> CRISTHIAN BENITEZ | M48: =IF(A48="","",'DATA PENDIENTES'!M151) -> 46387 | N48: =IF(A48="","",'DATA PENDIENTES'!N151) -> 46387 | O48: =IF(A48="","",IFERROR(MAX(TODAY()-N48,0),0)) -> 0 | P48: =IF(A48="","",IF(H48=0,"COMPLETO",IF(H48<=E48*0.1,"CASI COMPLETO","PENDIENTE"))) -> PENDIENTE | Q48: =IF(A48="","",IFERROR(G48/E48,0)) -> 0.63636364 | R48: =IF(A48="","",IF(O48>30,"CRITICO",IF(O48>7,"ALERTA","OK"))) -> OK | S48: =IF(A48="","",IF(O48>30,"1-CRITICO",IF(O48>7,"2-URGENTE","3-NORMAL"))) -> 3-NORMAL | T48: =IF(A48="","",'DATA PENDIENTES'!O151) -> 54862500
A49: =IF('DATA PENDIENTES'!B145="","",'DATA PENDIENTES'!B145) -> SU115945 | B49: =IF(A49="","",'DATA PENDIENTES'!C145) -> SOPORTE MOTOR | C49: =IF(A49="","",'DATA PENDIENTES'!L145) -> 16500020 | D49: =IF(A49="","",'DATA PENDIENTES'!J145) -> 70301773 | E49: =IF(A49="","",'DATA PENDIENTES'!D145) -> 4 | F49: =IF(A49="","",'DATA PENDIENTES'!E145) -> UND | G49: =IF(A49="","",'DATA PENDIENTES'!F145) -> 0 | H49: =IF(A49="","",'DATA PENDIENTES'!G145) -> 4 | I49: =IF(A49="","",'DATA PENDIENTES'!H145) -> 590000 | J49: =IF(A49="","",IFERROR(H49*F49,0)) -> 0 | K49: =IF(A49="","",'DATA PENDIENTES'!I145) -> MAQUITECNICOS IMPORTADORES SAS | L49: =IF(A49="","",'DATA PENDIENTES'!K145) -> CRISTHIAN BENITEZ | M49: =IF(A49="","",'DATA PENDIENTES'!M145) -> 46119 | N49: =IF(A49="","",'DATA PENDIENTES'!N145) -> 46119 | O49: =IF(A49="","",IFERROR(MAX(TODAY()-N49,0),0)) -> 0 | P49: =IF(A49="","",IF(H49=0,"COMPLETO",IF(H49<=E49*0.1,"CASI COMPLETO","PENDIENTE"))) -> PENDIENTE | Q49: =IF(A49="","",IFERROR(G49/E49,0)) -> 0 | R49: =IF(A49="","",IF(O49>30,"CRITICO",IF(O49>7,"ALERTA","OK"))) -> OK | S49: =IF(A49="","",IF(O49>30,"1-CRITICO",IF(O49>7,"2-URGENTE","3-NORMAL"))) -> 3-NORMAL | T49: =IF(A49="","",'DATA PENDIENTES'!O145) -> 448400
A50: =IF('DATA PENDIENTES'!B146="","",'DATA PENDIENTES'!B146) -> SU115945 | B50: =IF(A50="","",'DATA PENDIENTES'!C146) -> SOPORTE MOTOR | C50: =IF(A50="","",'DATA PENDIENTES'!L146) -> 16500020 | D50: =IF(A50="","",'DATA PENDIENTES'!J146) -> 70301773 | E50: =IF(A50="","",'DATA PENDIENTES'!D146) -> 3 | F50: =IF(A50="","",'DATA PENDIENTES'!E146) -> UND | G50: =IF(A50="","",'DATA PENDIENTES'!F146) -> 0 | H50: =IF(A50="","",'DATA PENDIENTES'!G146) -> 3 | I50: =IF(A50="","",'DATA PENDIENTES'!H146) -> 590000 | J50: =IF(A50="","",IFERROR(H50*F50,0)) -> 0 | K50: =IF(A50="","",'DATA PENDIENTES'!I146) -> MAQUITECNICOS IMPORTADORES SAS | L50: =IF(A50="","",'DATA PENDIENTES'!K146) -> CRISTHIAN BENITEZ | M50: =IF(A50="","",'DATA PENDIENTES'!M146) -> 46119 | N50: =IF(A50="","",'DATA PENDIENTES'!N146) -> 46113 | O50: =IF(A50="","",IFERROR(MAX(TODAY()-N50,0),0)) -> 6 | P50: =IF(A50="","",IF(H50=0,"COMPLETO",IF(H50<=E50*0.1,"CASI COMPLETO","PENDIENTE"))) -> PENDIENTE | Q50: =IF(A50="","",IFERROR(G50/E50,0)) -> 0 | R50: =IF(A50="","",IF(O50>30,"CRITICO",IF(O50>7,"ALERTA","OK"))) -> OK | S50: =IF(A50="","",IF(O50>30,"1-CRITICO",IF(O50>7,"2-URGENTE","3-NORMAL"))) -> 3-NORMAL | T50: =IF(A50="","",'DATA PENDIENTES'!O146) -> 336300
A51: =IF('DATA PENDIENTES'!B247="","",'DATA PENDIENTES'!B247) -> SU115858 | B51: =IF(A51="","",'DATA PENDIENTES'!C247) -> BISAGRA TAPA DE INSPECCION ARTICULACION | C51: =IF(A51="","",'DATA PENDIENTES'!L247) -> 17741001 | D51: =IF(A51="","",'DATA PENDIENTES'!J247) -> 5034 | E51: =IF(A51="","",'DATA PENDIENTES'!D247) -> 2 | F51: =IF(A51="","",'DATA PENDIENTES'!E247) -> UND | G51: =IF(A51="","",'DATA PENDIENTES'!F247) -> 1 | H51: =IF(A51="","",'DATA PENDIENTES'!G247) -> 1 | I51: =IF(A51="","",'DATA PENDIENTES'!H247) -> 148027 | J51: =IF(A51="","",IFERROR(H51*F51,0)) -> 0 | K51: =IF(A51="","",'DATA PENDIENTES'!I247) -> COMERCIALIZADORA DE AUTOPARTES E INDUSTRIAL UNIVERSAL SAS | L51: =IF(A51="","",'DATA PENDIENTES'!K247) -> CRISTHIAN BENITEZ | M51: =IF(A51="","",'DATA PENDIENTES'!M247) -> 46134 | N51: =IF(A51="","",'DATA PENDIENTES'!N247) -> 46113 | O51: =IF(A51="","",IFERROR(MAX(TODAY()-N51,0),0)) -> 6 | P51: =IF(A51="","",IF(H51=0,"COMPLETO",IF(H51<=E51*0.1,"CASI COMPLETO","PENDIENTE"))) -> PENDIENTE | Q51: =IF(A51="","",IFERROR(G51/E51,0)) -> 0.5 | R51: =IF(A51="","",IF(O51>30,"CRITICO",IF(O51>7,"ALERTA","OK"))) -> OK | S51: =IF(A51="","",IF(O51>30,"1-CRITICO",IF(O51>7,"2-URGENTE","3-NORMAL"))) -> 3-NORMAL | T51: =IF(A51="","",'DATA PENDIENTES'!O247) -> 56250.26
A52: =IF('DATA PENDIENTES'!B25="","",'DATA PENDIENTES'!B25) -> SU115941 | B52: =IF(A52="","",'DATA PENDIENTES'!C25) -> EMPAQUE TAPA VALVULAS | C52: =IF(A52="","",'DATA PENDIENTES'!L25) -> 21100001 | D52: =IF(A52="","",'DATA PENDIENTES'!J25) -> 21123014 | E52: =IF(A52="","",'DATA PENDIENTES'!D25) -> 15 | F52: =IF(A52="","",'DATA PENDIENTES'!E25) -> UND | G52: =IF(A52="","",'DATA PENDIENTES'!F25) -> 0 | H52: =IF(A52="","",'DATA PENDIENTES'!G25) -> 15 | I52: =IF(A52="","",'DATA PENDIENTES'!H25) -> 239495.6 | J52: =IF(A52="","",IFERROR(H52*F52,0)) -> 0 | K52: =IF(A52="","",'DATA PENDIENTES'!I25) -> VOLVO GROUP COLOMBIA S A S | L52: =IF(A52="","",'DATA PENDIENTES'!K25) -> CRISTHIAN BENITEZ | M52: =IF(A52="","",'DATA PENDIENTES'!M25) -> 46118 | N52: =IF(A52="","",'DATA PENDIENTES'!N25) -> 46108 | O52: =IF(A52="","",IFERROR(MAX(TODAY()-N52,0),0)) -> 11 | P52: =IF(A52="","",IF(H52=0,"COMPLETO",IF(H52<=E52*0.1,"CASI COMPLETO","PENDIENTE"))) -> PENDIENTE | Q52: =IF(A52="","",IFERROR(G52/E52,0)) -> 0 | R52: =IF(A52="","",IF(O52>30,"CRITICO",IF(O52>7,"ALERTA","OK"))) -> ALERTA | S52: =IF(A52="","",IF(O52>30,"1-CRITICO",IF(O52>7,"2-URGENTE","3-NORMAL"))) -> 2-URGENTE | T52: =IF(A52="","",'DATA PENDIENTES'!O25) -> 682562.5
A53: =IF('DATA PENDIENTES'!B26="","",'DATA PENDIENTES'!B26) -> SU115941 | B53: =IF(A53="","",'DATA PENDIENTES'!C26) -> CASQUILLO DE TAPA VALVULAS | C53: =IF(A53="","",'DATA PENDIENTES'!L26) -> 21100002 | D53: =IF(A53="","",'DATA PENDIENTES'!J26) -> 3964604 | E53: =IF(A53="","",'DATA PENDIENTES'!D26) -> 200 | F53: =IF(A53="","",'DATA PENDIENTES'!E26) -> UND | G53: =IF(A53="","",'DATA PENDIENTES'!F26) -> 0 | H53: =IF(A53="","",'DATA PENDIENTES'!G26) -> 200 | I53: =IF(A53="","",'DATA PENDIENTES'!H26) -> 4841.66 | J53: =IF(A53="","",IFERROR(H53*F53,0)) -> 0 | K53: =IF(A53="","",'DATA PENDIENTES'!I26) -> VOLVO GROUP COLOMBIA S A S | L53: =IF(A53="","",'DATA PENDIENTES'!K26) -> CRISTHIAN BENITEZ | M53: =IF(A53="","",'DATA PENDIENTES'!M26) -> 46118 | N53: =IF(A53="","",'DATA PENDIENTES'!N26) -> 46108 | O53: =IF(A53="","",IFERROR(MAX(TODAY()-N53,0),0)) -> 11 | P53: =IF(A53="","",IF(H53=0,"COMPLETO",IF(H53<=E53*0.1,"CASI COMPLETO","PENDIENTE"))) -> PENDIENTE | Q53: =IF(A53="","",IFERROR(G53/E53,0)) -> 0 | R53: =IF(A53="","",IF(O53>30,"CRITICO",IF(O53>7,"ALERTA","OK"))) -> ALERTA | S53: =IF(A53="","",IF(O53>30,"1-CRITICO",IF(O53>7,"2-URGENTE","3-NORMAL"))) -> 2-URGENTE | T53: =IF(A53="","",'DATA PENDIENTES'!O26) -> 183983.1
A54: =IF('DATA PENDIENTES'!B27="","",'DATA PENDIENTES'!B27) -> SU115941 | B54: =IF(A54="","",'DATA PENDIENTES'!C27) -> ARANDELA DE COBRE Ø24 A Ø29 MM | C54: =IF(A54="","",'DATA PENDIENTES'!L27) -> 21701111 | D54: =IF(A54="","",'DATA PENDIENTES'!J27) -> 949329 | E54: =IF(A54="","",'DATA PENDIENTES'!D27) -> 200 | F54: =IF(A54="","",'DATA PENDIENTES'!E27) -> UND | G54: =IF(A54="","",'DATA PENDIENTES'!F27) -> 0 | H54: =IF(A54="","",'DATA PENDIENTES'!G27) -> 200 | I54: =IF(A54="","",'DATA PENDIENTES'!H27) -> 1801.76 | J54: =IF(A54="","",IFERROR(H54*F54,0)) -> 0 | K54: =IF(A54="","",'DATA PENDIENTES'!I27) -> VOLVO GROUP COLOMBIA S A S | L54: =IF(A54="","",'DATA PENDIENTES'!K27) -> CRISTHIAN BENITEZ | M54: =IF(A54="","",'DATA PENDIENTES'!M27) -> 46118 | N54: =IF(A54="","",'DATA PENDIENTES'!N27) -> 46108 | O54: =IF(A54="","",IFERROR(MAX(TODAY()-N54,0),0)) -> 11 | P54: =IF(A54="","",IF(H54=0,"COMPLETO",IF(H54<=E54*0.1,"CASI COMPLETO","PENDIENTE"))) -> PENDIENTE | Q54: =IF(A54="","",IFERROR(G54/E54,0)) -> 0 | R54: =IF(A54="","",IF(O54>30,"CRITICO",IF(O54>7,"ALERTA","OK"))) -> ALERTA | S54: =IF(A54="","",IF(O54>30,"1-CRITICO",IF(O54>7,"2-URGENTE","3-NORMAL"))) -> 2-URGENTE | T54: =IF(A54="","",'DATA PENDIENTES'!O27) -> 68466.88
A55: =IF('DATA PENDIENTES'!B28="","",'DATA PENDIENTES'!B28) -> SU115941 | B55: =IF(A55="","",'DATA PENDIENTES'!C28) -> ARANDELA DE COBRE Ø24 A Ø31 MM | C55: =IF(A55="","",'DATA PENDIENTES'!L28) -> 21701112 | D55: =IF(A55="","",'DATA PENDIENTES'!J28) -> 18813 | E55: =IF(A55="","",'DATA PENDIENTES'!D28) -> 100 | F55: =IF(A55="","",'DATA PENDIENTES'!E28) -> UND | G55: =IF(A55="","",'DATA PENDIENTES'!F28) -> 0 | H55: =IF(A55="","",'DATA PENDIENTES'!G28) -> 100 | I55: =IF(A55="","",'DATA PENDIENTES'!H28) -> 3658.96 | J55: =IF(A55="","",IFERROR(H55*F55,0)) -> 0 | K55: =IF(A55="","",'DATA PENDIENTES'!I28) -> VOLVO GROUP COLOMBIA S A S | L55: =IF(A55="","",'DATA PENDIENTES'!K28) -> CRISTHIAN BENITEZ | M55: =IF(A55="","",'DATA PENDIENTES'!M28) -> 46118 | N55: =IF(A55="","",'DATA PENDIENTES'!N28) -> 46108 | O55: =IF(A55="","",IFERROR(MAX(TODAY()-N55,0),0)) -> 11 | P55: =IF(A55="","",IF(H55=0,"COMPLETO",IF(H55<=E55*0.1,"CASI COMPLETO","PENDIENTE"))) -> PENDIENTE | Q55: =IF(A55="","",IFERROR(G55/E55,0)) -> 0 | R55: =IF(A55="","",IF(O55>30,"CRITICO",IF(O55>7,"ALERTA","OK"))) -> ALERTA | S55: =IF(A55="","",IF(O55>30,"1-CRITICO",IF(O55>7,"2-URGENTE","3-NORMAL"))) -> 2-URGENTE | T55: =IF(A55="","",'DATA PENDIENTES'!O28) -> 69520.24
A56: =IF('DATA PENDIENTES'!B36="","",'DATA PENDIENTES'!B36) -> SU115941 | B56: =IF(A56="","",'DATA PENDIENTES'!C36) -> FILTRO DE AIRE MOTOR | C56: =IF(A56="","",'DATA PENDIENTES'!L36) -> 25601002 | D56: =IF(A56="","",'DATA PENDIENTES'!J36) -> 1544449 | E56: =IF(A56="","",'DATA PENDIENTES'!D36) -> 25 | F56: =IF(A56="","",'DATA PENDIENTES'!E36) -> UND | G56: =IF(A56="","",'DATA PENDIENTES'!F36) -> 0 | H56: =IF(A56="","",'DATA PENDIENTES'!G36) -> 25 | I56: =IF(A56="","",'DATA PENDIENTES'!H36) -> 263334.3 | J56: =IF(A56="","",IFERROR(H56*F56,0)) -> 0 | K56: =IF(A56="","",'DATA PENDIENTES'!I36) -> VOLVO GROUP COLOMBIA S A S | L56: =IF(A56="","",'DATA PENDIENTES'!K36) -> CRISTHIAN BENITEZ | M56: =IF(A56="","",'DATA PENDIENTES'!M36) -> 46118 | N56: =IF(A56="","",'DATA PENDIENTES'!N36) -> 46108 | O56: =IF(A56="","",IFERROR(MAX(TODAY()-N56,0),0)) -> 11 | P56: =IF(A56="","",IF(H56=0,"COMPLETO",IF(H56<=E56*0.1,"CASI COMPLETO","PENDIENTE"))) -> PENDIENTE | Q56: =IF(A56="","",IFERROR(G56/E56,0)) -> 0 | R56: =IF(A56="","",IF(O56>30,"CRITICO",IF(O56>7,"ALERTA","OK"))) -> ALERTA | S56: =IF(A56="","",IF(O56>30,"1-CRITICO",IF(O56>7,"2-URGENTE","3-NORMAL"))) -> 2-URGENTE | T56: =IF(A56="","",'DATA PENDIENTES'!O36) -> 1250838
A57: =IF('DATA PENDIENTES'!B38="","",'DATA PENDIENTES'!B38) -> SU115941 | B57: =IF(A57="","",'DATA PENDIENTES'!C38) -> MANGUERA EN S ENFRIADOR DE CAJA | C57: =IF(A57="","",'DATA PENDIENTES'!L38) -> 26301270 | D57: =IF(A57="","",'DATA PENDIENTES'!J38) -> 22129842 | E57: =IF(A57="","",'DATA PENDIENTES'!D38) -> 40 | F57: =IF(A57="","",'DATA PENDIENTES'!E38) -> UND | G57: =IF(A57="","",'DATA PENDIENTES'!F38) -> 0 | H57: =IF(A57="","",'DATA PENDIENTES'!G38) -> 40 | I57: =IF(A57="","",'DATA PENDIENTES'!H38) -> 127509.2 | J57: =IF(A57="","",IFERROR(H57*F57,0)) -> 0 | K57: =IF(A57="","",'DATA PENDIENTES'!I38) -> VOLVO GROUP COLOMBIA S A S | L57: =IF(A57="","",'DATA PENDIENTES'!K38) -> CRISTHIAN BENITEZ | M57: =IF(A57="","",'DATA PENDIENTES'!M38) -> 46118 | N57: =IF(A57="","",'DATA PENDIENTES'!N38) -> 46108 | O57: =IF(A57="","",IFERROR(MAX(TODAY()-N57,0),0)) -> 11 | P57: =IF(A57="","",IF(H57=0,"COMPLETO",IF(H57<=E57*0.1,"CASI COMPLETO","PENDIENTE"))) -> PENDIENTE | Q57: =IF(A57="","",IFERROR(G57/E57,0)) -> 0 | R57: =IF(A57="","",IF(O57>30,"CRITICO",IF(O57>7,"ALERTA","OK"))) -> ALERTA | S57: =IF(A57="","",IF(O57>30,"1-CRITICO",IF(O57>7,"2-URGENTE","3-NORMAL"))) -> 2-URGENTE | T57: =IF(A57="","",'DATA PENDIENTES'!O38) -> 969070.2
A58: =IF('DATA PENDIENTES'!B39="","",'DATA PENDIENTES'!B39) -> SU115941 | B58: =IF(A58="","",'DATA PENDIENTES'!C39) -> MANGUERA RECTA ENFRIADOR DE CAJA | C58: =IF(A58="","",'DATA PENDIENTES'!L39) -> 26301271 | D58: =IF(A58="","",'DATA PENDIENTES'!J39) -> 22144024 | E58: =IF(A58="","",'DATA PENDIENTES'!D39) -> 40 | F58: =IF(A58="","",'DATA PENDIENTES'!E39) -> UND | G58: =IF(A58="","",'DATA PENDIENTES'!F39) -> 0 | H58: =IF(A58="","",'DATA PENDIENTES'!G39) -> 40 | I58: =IF(A58="","",'DATA PENDIENTES'!H39) -> 63754.62 | J58: =IF(A58="","",IFERROR(H58*F58,0)) -> 0 | K58: =IF(A58="","",'DATA PENDIENTES'!I39) -> VOLVO GROUP COLOMBIA S A S | L58: =IF(A58="","",'DATA PENDIENTES'!K39) -> CRISTHIAN BENITEZ | M58: =IF(A58="","",'DATA PENDIENTES'!M39) -> 46118 | N58: =IF(A58="","",'DATA PENDIENTES'!N39) -> 46108 | O58: =IF(A58="","",IFERROR(MAX(TODAY()-N58,0),0)) -> 11 | P58: =IF(A58="","",IF(H58=0,"COMPLETO",IF(H58<=E58*0.1,"CASI COMPLETO","PENDIENTE"))) -> PENDIENTE | Q58: =IF(A58="","",IFERROR(G58/E58,0)) -> 0 | R58: =IF(A58="","",IF(O58>30,"CRITICO",IF(O58>7,"ALERTA","OK"))) -> ALERTA | S58: =IF(A58="","",IF(O58>30,"1-CRITICO",IF(O58>7,"2-URGENTE","3-NORMAL"))) -> 2-URGENTE | T58: =IF(A58="","",'DATA PENDIENTES'!O39) -> 484535.1
A59: =IF('DATA PENDIENTES'!B129="","",'DATA PENDIENTES'!B129) -> SU115799 | B59: =IF(A59="","",'DATA PENDIENTES'!C129) -> CABLE DE BATERIAS | C59: =IF(A59="","",'DATA PENDIENTES'!L129) -> 30110006 | D59: =IF(A59="","",'DATA PENDIENTES'!J129) | E59: =IF(A59="","",'DATA PENDIENTES'!D129) -> 2 | F59: =IF(A59="","",'DATA PENDIENTES'!E129) -> UND | G59: =IF(A59="","",'DATA PENDIENTES'!F129) -> 0 | H59: =IF(A59="","",'DATA PENDIENTES'!G129) -> 2 | I59: =IF(A59="","",'DATA PENDIENTES'!H129) -> 110000 | J59: =IF(A59="","",IFERROR(H59*F59,0)) -> 0 | K59: =IF(A59="","",'DATA PENDIENTES'!I129) -> SMIDT SUMINISTRO MANTENIMIENTO INDUSTRIAL DE TRANSPORTE SAS | L59: =IF(A59="","",'DATA PENDIENTES'!K129) -> CRISTHIAN BENITEZ | M59: =IF(A59="","",'DATA PENDIENTES'!M129) -> 46101 | N59: =IF(A59="","",'DATA PENDIENTES'!N129) -> 46099 | O59: =IF(A59="","",IFERROR(MAX(TODAY()-N59,0),0)) -> 20 | P59: =IF(A59="","",IF(H59=0,"COMPLETO",IF(H59<=E59*0.1,"CASI COMPLETO","PENDIENTE"))) -> PENDIENTE | Q59: =IF(A59="","",IFERROR(G59/E59,0)) -> 0 | R59: =IF(A59="","",IF(O59>30,"CRITICO",IF(O59>7,"ALERTA","OK"))) -> ALERTA | S59: =IF(A59="","",IF(O59>30,"1-CRITICO",IF(O59>7,"2-URGENTE","3-NORMAL"))) -> 2-URGENTE | T59: =IF(A59="","",'DATA PENDIENTES'!O129) -> 41800
A60: =IF('DATA PENDIENTES'!B261="","",'DATA PENDIENTES'!B261) -> SU115503 | B60: =IF(A60="","",'DATA PENDIENTES'!C261) -> BATERIA 8D ÓPTIMA YELLOW | C60: =IF(A60="","",'DATA PENDIENTES'!L261) -> 30110008 | D60: =IF(A60="","",'DATA PENDIENTES'!J261) | E60: =IF(A60="","",'DATA PENDIENTES'!D261) -> 220 | F60: =IF(A60="","",'DATA PENDIENTES'!E261) -> UND | G60: =IF(A60="","",'DATA PENDIENTES'!F261) -> 0 | H60: =IF(A60="","",'DATA PENDIENTES'!G261) -> 220 | I60: =IF(A60="","",'DATA PENDIENTES'!H261) -> 1290000 | J60: =IF(A60="","",IFERROR(H60*F60,0)) -> 0 | K60: =IF(A60="","",'DATA PENDIENTES'!I261) -> COEXITO S.A.S. | L60: =IF(A60="","",'DATA PENDIENTES'!K261) -> CRISTHIAN BENITEZ | M60: =IF(A60="","",'DATA PENDIENTES'!M261) -> 46477 | N60: =IF(A60="","",'DATA PENDIENTES'!N261) -> 46418 | O60: =IF(A60="","",IFERROR(MAX(TODAY()-N60,0),0)) -> 0 | P60: =IF(A60="","",IF(H60=0,"COMPLETO",IF(H60<=E60*0.1,"CASI COMPLETO","PENDIENTE"))) -> PENDIENTE | Q60: =IF(A60="","",IFERROR(G60/E60,0)) -> 0 | R60: =IF(A60="","",IF(O60>30,"CRITICO",IF(O60>7,"ALERTA","OK"))) -> OK | S60: =IF(A60="","",IF(O60>30,"1-CRITICO",IF(O60>7,"2-URGENTE","3-NORMAL"))) -> 3-NORMAL | T60: =IF(A60="","",'DATA PENDIENTES'!O261) -> 53922000
A61: =IF('DATA PENDIENTES'!B142="","",'DATA PENDIENTES'!B142) -> SU115912 | B61: =IF(A61="","",'DATA PENDIENTES'!C142) -> DIODO IN5408 PUERTAS | C61: =IF(A61="","",'DATA PENDIENTES'!L142) -> 30500068 | D61: =IF(A61="","",'DATA PENDIENTES'!J142) -> INIBXE08 | E61: =IF(A61="","",'DATA PENDIENTES'!D142) -> 500 | F61: =IF(A61="","",'DATA PENDIENTES'!E142) -> UND | G61: =IF(A61="","",'DATA PENDIENTES'!F142) -> 0 | H61: =IF(A61="","",'DATA PENDIENTES'!G142) -> 500 | I61: =IF(A61="","",'DATA PENDIENTES'!H142) -> 380 | J61: =IF(A61="","",IFERROR(H61*F61,0)) -> 0 | K61: =IF(A61="","",'DATA PENDIENTES'!I142) -> MASMOVIL SAS | L61: =IF(A61="","",'DATA PENDIENTES'!K142) -> CRISTHIAN BENITEZ | M61: =IF(A61="","",'DATA PENDIENTES'!M142) -> 46119 | N61: =IF(A61="","",'DATA PENDIENTES'!N142) -> 46107 | O61: =IF(A61="","",IFERROR(MAX(TODAY()-N61,0),0)) -> 12 | P61: =IF(A61="","",IF(H61=0,"COMPLETO",IF(H61<=E61*0.1,"CASI COMPLETO","PENDIENTE"))) -> PENDIENTE | Q61: =IF(A61="","",IFERROR(G61/E61,0)) -> 0 | R61: =IF(A61="","",IF(O61>30,"CRITICO",IF(O61>7,"ALERTA","OK"))) -> ALERTA | S61: =IF(A61="","",IF(O61>30,"1-CRITICO",IF(O61>7,"2-URGENTE","3-NORMAL"))) -> 2-URGENTE | T61: =IF(A61="","",'DATA PENDIENTES'!O142) -> 36100
A62: =IF('DATA PENDIENTES'!B130="","",'DATA PENDIENTES'!B130) -> SU115883 | B62: =IF(A62="","",'DATA PENDIENTES'!C130) -> TERMINAL BARRILETE 1/0 *5/16 | C62: =IF(A62="","",'DATA PENDIENTES'!L130) -> 30500080 | D62: =IF(A62="","",'DATA PENDIENTES'!J130) | E62: =IF(A62="","",'DATA PENDIENTES'!D130) -> 2 | F62: =IF(A62="","",'DATA PENDIENTES'!E130) -> UND | G62: =IF(A62="","",'DATA PENDIENTES'!F130) -> 0 | H62: =IF(A62="","",'DATA PENDIENTES'!G130) -> 2 | I62: =IF(A62="","",'DATA PENDIENTES'!H130) -> 9000 | J62: =IF(A62="","",IFERROR(H62*F62,0)) -> 0 | K62: =IF(A62="","",'DATA PENDIENTES'!I130) -> SMIDT SUMINISTRO MANTENIMIENTO INDUSTRIAL DE TRANSPORTE SAS | L62: =IF(A62="","",'DATA PENDIENTES'!K130) -> CRISTHIAN BENITEZ | M62: =IF(A62="","",'DATA PENDIENTES'!M130) -> 46113 | N62: =IF(A62="","",'DATA PENDIENTES'!N130) -> 46113 | O62: =IF(A62="","",IFERROR(MAX(TODAY()-N62,0),0)) -> 6 | P62: =IF(A62="","",IF(H62=0,"COMPLETO",IF(H62<=E62*0.1,"CASI COMPLETO","PENDIENTE"))) -> PENDIENTE | Q62: =IF(A62="","",IFERROR(G62/E62,0)) -> 0 | R62: =IF(A62="","",IF(O62>30,"CRITICO",IF(O62>7,"ALERTA","OK"))) -> OK | S62: =IF(A62="","",IF(O62>30,"1-CRITICO",IF(O62>7,"2-URGENTE","3-NORMAL"))) -> 3-NORMAL | T62: =IF(A62="","",'DATA PENDIENTES'!O130) -> 3420
A63: =IF('DATA PENDIENTES'!B243="","",'DATA PENDIENTES'!B243) -> SU115872 | B63: =IF(A63="","",'DATA PENDIENTES'!C243) -> ELIMINADOR DE EMPAQUE | C63: =IF(A63="","",'DATA PENDIENTES'!L243) -> 51110004 | D63: =IF(A63="","",'DATA PENDIENTES'!J243) -> COMP001 | E63: =IF(A63="","",'DATA PENDIENTES'!D243) -> 5 | F63: =IF(A63="","",'DATA PENDIENTES'!E243) -> UND | G63: =IF(A63="","",'DATA PENDIENTES'!F243) -> 0 | H63: =IF(A63="","",'DATA PENDIENTES'!G243) -> 5 | I63: =IF(A63="","",'DATA PENDIENTES'!H243) -> 69000 | J63: =IF(A63="","",IFERROR(H63*F63,0)) -> 0 | K63: =IF(A63="","",'DATA PENDIENTES'!I243) -> COMERCIALIZADORA INTERNACIONAL ATR REPRESENTACIONES S.A | L63: =IF(A63="","",'DATA PENDIENTES'!K243) -> CRISTHIAN BENITEZ | M63: =IF(A63="","",'DATA PENDIENTES'!M243) -> 46113 | N63: =IF(A63="","",'DATA PENDIENTES'!N243) -> 46113 | O63: =IF(A63="","",IFERROR(MAX(TODAY()-N63,0),0)) -> 6 | P63: =IF(A63="","",IF(H63=0,"COMPLETO",IF(H63<=E63*0.1,"CASI COMPLETO","PENDIENTE"))) -> PENDIENTE | Q63: =IF(A63="","",IFERROR(G63/E63,0)) -> 0 | R63: =IF(A63="","",IF(O63>30,"CRITICO",IF(O63>7,"ALERTA","OK"))) -> OK | S63: =IF(A63="","",IF(O63>30,"1-CRITICO",IF(O63>7,"2-URGENTE","3-NORMAL"))) -> 3-NORMAL | T63: =IF(A63="","",'DATA PENDIENTES'!O243) -> 65550
A64: =IF('DATA PENDIENTES'!B40="","",'DATA PENDIENTES'!B40) -> SU115941 | B64: =IF(A64="","",'DATA PENDIENTES'!C40) -> FILTRO SECADOR | C64: =IF(A64="","",'DATA PENDIENTES'!L40) -> 56102003 | D64: =IF(A64="","",'DATA PENDIENTES'!J40) -> 20773824 | E64: =IF(A64="","",'DATA PENDIENTES'!D40) -> 50 | F64: =IF(A64="","",'DATA PENDIENTES'!E40) -> UND | G64: =IF(A64="","",'DATA PENDIENTES'!F40) -> 0 | H64: =IF(A64="","",'DATA PENDIENTES'!G40) -> 50 | I64: =IF(A64="","",'DATA PENDIENTES'!H40) -> 365896.1 | J64: =IF(A64="","",IFERROR(H64*F64,0)) -> 0 | K64: =IF(A64="","",'DATA PENDIENTES'!I40) -> VOLVO GROUP COLOMBIA S A S | L64: =IF(A64="","",'DATA PENDIENTES'!K40) -> CRISTHIAN BENITEZ | M64: =IF(A64="","",'DATA PENDIENTES'!M40) -> 46118 | N64: =IF(A64="","",'DATA PENDIENTES'!N40) -> 46108 | O64: =IF(A64="","",IFERROR(MAX(TODAY()-N64,0),0)) -> 11 | P64: =IF(A64="","",IF(H64=0,"COMPLETO",IF(H64<=E64*0.1,"CASI COMPLETO","PENDIENTE"))) -> PENDIENTE | Q64: =IF(A64="","",IFERROR(G64/E64,0)) -> 0 | R64: =IF(A64="","",IF(O64>30,"CRITICO",IF(O64>7,"ALERTA","OK"))) -> ALERTA | S64: =IF(A64="","",IF(O64>30,"1-CRITICO",IF(O64>7,"2-URGENTE","3-NORMAL"))) -> 2-URGENTE | T64: =IF(A64="","",'DATA PENDIENTES'!O40) -> 3476013
A65: =IF('DATA PENDIENTES'!B180="","",'DATA PENDIENTES'!B180) -> SU115886 | B65: =IF(A65="","",'DATA PENDIENTES'!C180) -> DIAFRAGMA CAMARA DE FRENO TIPO 24 | C65: =IF(A65="","",'DATA PENDIENTES'!L180) -> 56103157 | D65: =IF(A65="","",'DATA PENDIENTES'!J180) | E65: =IF(A65="","",'DATA PENDIENTES'!D180) -> 8 | F65: =IF(A65="","",'DATA PENDIENTES'!E180) -> UND | G65: =IF(A65="","",'DATA PENDIENTES'!F180) -> 0 | H65: =IF(A65="","",'DATA PENDIENTES'!G180) -> 8 | I65: =IF(A65="","",'DATA PENDIENTES'!H180) -> 52000 | J65: =IF(A65="","",IFERROR(H65*F65,0)) -> 0 | K65: =IF(A65="","",'DATA PENDIENTES'!I180) -> GRUPO EMPRESARIAL PINEDA SAS | L65: =IF(A65="","",'DATA PENDIENTES'!K180) -> CRISTHIAN BENITEZ | M65: =IF(A65="","",'DATA PENDIENTES'!M180) -> 46113 | N65: =IF(A65="","",'DATA PENDIENTES'!N180) -> 46113 | O65: =IF(A65="","",IFERROR(MAX(TODAY()-N65,0),0)) -> 6 | P65: =IF(A65="","",IF(H65=0,"COMPLETO",IF(H65<=E65*0.1,"CASI COMPLETO","PENDIENTE"))) -> PENDIENTE | Q65: =IF(A65="","",IFERROR(G65/E65,0)) -> 0 | R65: =IF(A65="","",IF(O65>30,"CRITICO",IF(O65>7,"ALERTA","OK"))) -> OK | S65: =IF(A65="","",IF(O65>30,"1-CRITICO",IF(O65>7,"2-URGENTE","3-NORMAL"))) -> 3-NORMAL | T65: =IF(A65="","",'DATA PENDIENTES'!O180) -> 79040
A66: =IF('DATA PENDIENTES'!B9="","",'DATA PENDIENTES'!B9) -> SU115845 | B66: =IF(A66="","",'DATA PENDIENTES'!C9) -> TUERCA DE SUJECION FUELLE NEUMATICO | C66: =IF(A66="","",'DATA PENDIENTES'!L9) -> 72601008 | D66: =IF(A66="","",'DATA PENDIENTES'!J9) -> 990943 | E66: =IF(A66="","",'DATA PENDIENTES'!D9) -> 2 | F66: =IF(A66="","",'DATA PENDIENTES'!E9) -> UND | G66: =IF(A66="","",'DATA PENDIENTES'!F9) -> 0 | H66: =IF(A66="","",'DATA PENDIENTES'!G9) -> 2 | I66: =IF(A66="","",'DATA PENDIENTES'!H9) -> 6417.9 | J66: =IF(A66="","",IFERROR(H66*F66,0)) -> 0 | K66: =IF(A66="","",'DATA PENDIENTES'!I9) -> VOLVO GROUP COLOMBIA S A S | L66: =IF(A66="","",'DATA PENDIENTES'!K9) -> CRISTHIAN BENITEZ | M66: =IF(A66="","",'DATA PENDIENTES'!M9) -> 46106 | N66: =IF(A66="","",'DATA PENDIENTES'!N9) -> 46106 | O66: =IF(A66="","",IFERROR(MAX(TODAY()-N66,0),0)) -> 13 | P66: =IF(A66="","",IF(H66=0,"COMPLETO",IF(H66<=E66*0.1,"CASI COMPLETO","PENDIENTE"))) -> PENDIENTE | Q66: =IF(A66="","",IFERROR(G66/E66,0)) -> 0 | R66: =IF(A66="","",IF(O66>30,"CRITICO",IF(O66>7,"ALERTA","OK"))) -> ALERTA | S66: =IF(A66="","",IF(O66>30,"1-CRITICO",IF(O66>7,"2-URGENTE","3-NORMAL"))) -> 2-URGENTE | T66: =IF(A66="","",'DATA PENDIENTES'!O9) -> 2438.802
A67: =IF('DATA PENDIENTES'!B100="","",'DATA PENDIENTES'!B100) -> SU115857 | B67: =IF(A67="","",'DATA PENDIENTES'!C100) -> VASTAGO PARA REPARACIÓN LLANTAS DIAMETRO 6MM (1/4") | C67: =IF(A67="","",'DATA PENDIENTES'!L100) -> 77100026 | D67: =IF(A67="","",'DATA PENDIENTES'!J100) -> 1482 | E67: =IF(A67="","",'DATA PENDIENTES'!D100) -> 20 | F67: =IF(A67="","",'DATA PENDIENTES'!E100) -> UND | G67: =IF(A67="","",'DATA PENDIENTES'!F100) -> 0 | H67: =IF(A67="","",'DATA PENDIENTES'!G100) -> 20 | I67: =IF(A67="","",'DATA PENDIENTES'!H100) -> 2470 | J67: =IF(A67="","",IFERROR(H67*F67,0)) -> 0 | K67: =IF(A67="","",'DATA PENDIENTES'!I100) -> SUMILOGISTICA S.A.S. | L67: =IF(A67="","",'DATA PENDIENTES'!K100) -> CRISTHIAN BENITEZ | M67: =IF(A67="","",'DATA PENDIENTES'!M100) -> 46119 | N67: =IF(A67="","",'DATA PENDIENTES'!N100) -> 46113 | O67: =IF(A67="","",IFERROR(MAX(TODAY()-N67,0),0)) -> 6 | P67: =IF(A67="","",IF(H67=0,"COMPLETO",IF(H67<=E67*0.1,"CASI COMPLETO","PENDIENTE"))) -> PENDIENTE | Q67: =IF(A67="","",IFERROR(G67/E67,0)) -> 0 | R67: =IF(A67="","",IF(O67>30,"CRITICO",IF(O67>7,"ALERTA","OK"))) -> OK | S67: =IF(A67="","",IF(O67>30,"1-CRITICO",IF(O67>7,"2-URGENTE","3-NORMAL"))) -> 3-NORMAL | T67: =IF(A67="","",'DATA PENDIENTES'!O100) -> 9386
A68: =IF('DATA PENDIENTES'!B98="","",'DATA PENDIENTES'!B98) -> SU115857 | B68: =IF(A68="","",'DATA PENDIENTES'!C98) -> VASTAGO PARA REPARACIÓN LLANTAS DIAMETRO 8MM (5/16") | C68: =IF(A68="","",'DATA PENDIENTES'!L98) -> 77100027 | D68: =IF(A68="","",'DATA PENDIENTES'!J98) -> 1483 | E68: =IF(A68="","",'DATA PENDIENTES'!D98) -> 20 | F68: =IF(A68="","",'DATA PENDIENTES'!E98) -> UND | G68: =IF(A68="","",'DATA PENDIENTES'!F98) -> 0 | H68: =IF(A68="","",'DATA PENDIENTES'!G98) -> 20 | I68: =IF(A68="","",'DATA PENDIENTES'!H98) -> 2470 | J68: =IF(A68="","",IFERROR(H68*F68,0)) -> 0 | K68: =IF(A68="","",'DATA PENDIENTES'!I98) -> SUMILOGISTICA S.A.S. | L68: =IF(A68="","",'DATA PENDIENTES'!K98) -> CRISTHIAN BENITEZ | M68: =IF(A68="","",'DATA PENDIENTES'!M98) -> 46119 | N68: =IF(A68="","",'DATA PENDIENTES'!N98) -> 46113 | O68: =IF(A68="","",IFERROR(MAX(TODAY()-N68,0),0)) -> 6 | P68: =IF(A68="","",IF(H68=0,"COMPLETO",IF(H68<=E68*0.1,"CASI COMPLETO","PENDIENTE"))) -> PENDIENTE | Q68: =IF(A68="","",IFERROR(G68/E68,0)) -> 0 | R68: =IF(A68="","",IF(O68>30,"CRITICO",IF(O68>7,"ALERTA","OK"))) -> OK | S68: =IF(A68="","",IF(O68>30,"1-CRITICO",IF(O68>7,"2-URGENTE","3-NORMAL"))) -> 3-NORMAL | T68: =IF(A68="","",'DATA PENDIENTES'!O98) -> 9386
A69: =IF('DATA PENDIENTES'!B149="","",'DATA PENDIENTES'!B149) -> SU115530 | B69: =IF(A69="","",'DATA PENDIENTES'!C149) -> LLANTA NUEVA RADIAL 295/80-R22.5 | C69: =IF(A69="","",'DATA PENDIENTES'!L149) -> 77101008 | D69: =IF(A69="","",'DATA PENDIENTES'!J149) -> 295/80-R22.5 Michelin | E69: =IF(A69="","",'DATA PENDIENTES'!D149) -> 624 | F69: =IF(A69="","",'DATA PENDIENTES'!E149) -> UND | G69: =IF(A69="","",'DATA PENDIENTES'!F149) -> 118 | H69: =IF(A69="","",'DATA PENDIENTES'!G149) -> 506 | I69: =IF(A69="","",'DATA PENDIENTES'!H149) -> 1978513 | J69: =IF(A69="","",IFERROR(H69*F69,0)) -> 0 | K69: =IF(A69="","",'DATA PENDIENTES'!I149) -> LLANTAS REPUESTOS Y SERVICIO SAS | L69: =IF(A69="","",'DATA PENDIENTES'!K149) -> CRISTHIAN BENITEZ | M69: =IF(A69="","",'DATA PENDIENTES'!M149) -> 46472 | N69: =IF(A69="","",'DATA PENDIENTES'!N149) -> 46069 | O69: =IF(A69="","",IFERROR(MAX(TODAY()-N69,0),0)) -> 50 | P69: =IF(A69="","",IF(H69=0,"COMPLETO",IF(H69<=E69*0.1,"CASI COMPLETO","PENDIENTE"))) -> PENDIENTE | Q69: =IF(A69="","",IFERROR(G69/E69,0)) -> 0.18910256 | R69: =IF(A69="","",IF(O69>30,"CRITICO",IF(O69>7,"ALERTA","OK"))) -> CRITICO | S69: =IF(A69="","",IF(O69>30,"1-CRITICO",IF(O69>7,"2-URGENTE","3-NORMAL"))) -> 1-CRITICO | T69: =IF(A69="","",'DATA PENDIENTES'!O149) -> 235000000
A70: =IF('DATA PENDIENTES'!B95="","",'DATA PENDIENTES'!B95) -> SU115857 | B70: =IF(A70="","",'DATA PENDIENTES'!C95) -> RAC 12 PARCHE LLANTA RAD 115x70 MM VIPAL | C70: =IF(A70="","",'DATA PENDIENTES'!L95) -> 77101010 | D70: =IF(A70="","",'DATA PENDIENTES'!J95) -> 574 | E70: =IF(A70="","",'DATA PENDIENTES'!D95) -> 20 | F70: =IF(A70="","",'DATA PENDIENTES'!E95) -> UND | G70: =IF(A70="","",'DATA PENDIENTES'!F95) -> 0 | H70: =IF(A70="","",'DATA PENDIENTES'!G95) -> 20 | I70: =IF(A70="","",'DATA PENDIENTES'!H95) -> 5382 | J70: =IF(A70="","",IFERROR(H70*F70,0)) -> 0 | K70: =IF(A70="","",'DATA PENDIENTES'!I95) -> SUMILOGISTICA S.A.S. | L70: =IF(A70="","",'DATA PENDIENTES'!K95) -> CRISTHIAN BENITEZ | M70: =IF(A70="","",'DATA PENDIENTES'!M95) -> 46119 | N70: =IF(A70="","",'DATA PENDIENTES'!N95) -> 46113 | O70: =IF(A70="","",IFERROR(MAX(TODAY()-N70,0),0)) -> 6 | P70: =IF(A70="","",IF(H70=0,"COMPLETO",IF(H70<=E70*0.1,"CASI COMPLETO","PENDIENTE"))) -> PENDIENTE | Q70: =IF(A70="","",IFERROR(G70/E70,0)) -> 0 | R70: =IF(A70="","",IF(O70>30,"CRITICO",IF(O70>7,"ALERTA","OK"))) -> OK | S70: =IF(A70="","",IF(O70>30,"1-CRITICO",IF(O70>7,"2-URGENTE","3-NORMAL"))) -> 3-NORMAL | T70: =IF(A70="","",'DATA PENDIENTES'!O95) -> 20451.6
A71: =IF('DATA PENDIENTES'!B109="","",'DATA PENDIENTES'!B109) -> SU115857 | B71: =IF(A71="","",'DATA PENDIENTES'!C109) -> PASTA MONTAJE/DESMONTAJE 3.63 KL | C71: =IF(A71="","",'DATA PENDIENTES'!L109) -> 77101022 | D71: =IF(A71="","",'DATA PENDIENTES'!J109) -> 1320 | E71: =IF(A71="","",'DATA PENDIENTES'!D109) -> 3 | F71: =IF(A71="","",'DATA PENDIENTES'!E109) -> UND | G71: =IF(A71="","",'DATA PENDIENTES'!F109) -> 0 | H71: =IF(A71="","",'DATA PENDIENTES'!G109) -> 3 | I71: =IF(A71="","",'DATA PENDIENTES'!H109) -> 63000 | J71: =IF(A71="","",IFERROR(H71*F71,0)) -> 0 | K71: =IF(A71="","",'DATA PENDIENTES'!I109) -> SUMILOGISTICA S.A.S. | L71: =IF(A71="","",'DATA PENDIENTES'!K109) -> CRISTHIAN BENITEZ | M71: =IF(A71="","",'DATA PENDIENTES'!M109) -> 46119 | N71: =IF(A71="","",'DATA PENDIENTES'!N109) -> 46113 | O71: =IF(A71="","",IFERROR(MAX(TODAY()-N71,0),0)) -> 6 | P71: =IF(A71="","",IF(H71=0,"COMPLETO",IF(H71<=E71*0.1,"CASI COMPLETO","PENDIENTE"))) -> PENDIENTE | Q71: =IF(A71="","",IFERROR(G71/E71,0)) -> 0 | R71: =IF(A71="","",IF(O71>30,"CRITICO",IF(O71>7,"ALERTA","OK"))) -> OK | S71: =IF(A71="","",IF(O71>30,"1-CRITICO",IF(O71>7,"2-URGENTE","3-NORMAL"))) -> 3-NORMAL | T71: =IF(A71="","",'DATA PENDIENTES'!O109) -> 35910
A72: =IF('DATA PENDIENTES'!B106="","",'DATA PENDIENTES'!B106) -> SU115857 | B72: =IF(A72="","",'DATA PENDIENTES'!C106) -> GUSANILLO PARA VALVULA NORMAL | C72: =IF(A72="","",'DATA PENDIENTES'!L106) -> 77101023 | D72: =IF(A72="","",'DATA PENDIENTES'!J106) -> 1321 | E72: =IF(A72="","",'DATA PENDIENTES'!D106) -> 100 | F72: =IF(A72="","",'DATA PENDIENTES'!E106) -> UND | G72: =IF(A72="","",'DATA PENDIENTES'!F106) -> 0 | H72: =IF(A72="","",'DATA PENDIENTES'!G106) -> 100 | I72: =IF(A72="","",'DATA PENDIENTES'!H106) -> 132 | J72: =IF(A72="","",IFERROR(H72*F72,0)) -> 0 | K72: =IF(A72="","",'DATA PENDIENTES'!I106) -> SUMILOGISTICA S.A.S. | L72: =IF(A72="","",'DATA PENDIENTES'!K106) -> CRISTHIAN BENITEZ | M72: =IF(A72="","",'DATA PENDIENTES'!M106) -> 46119 | N72: =IF(A72="","",'DATA PENDIENTES'!N106) -> 46113 | O72: =IF(A72="","",IFERROR(MAX(TODAY()-N72,0),0)) -> 6 | P72: =IF(A72="","",IF(H72=0,"COMPLETO",IF(H72<=E72*0.1,"CASI COMPLETO","PENDIENTE"))) -> PENDIENTE | Q72: =IF(A72="","",IFERROR(G72/E72,0)) -> 0 | R72: =IF(A72="","",IF(O72>30,"CRITICO",IF(O72>7,"ALERTA","OK"))) -> OK | S72: =IF(A72="","",IF(O72>30,"1-CRITICO",IF(O72>7,"2-URGENTE","3-NORMAL"))) -> 3-NORMAL | T72: =IF(A72="","",'DATA PENDIENTES'!O106) -> 2508
A73: =IF('DATA PENDIENTES'!B150="","",'DATA PENDIENTES'!B150) -> SU115530 | B73: =IF(A73="","",'DATA PENDIENTES'!C150) -> LLANTA NUEVA RADIAL 295/80-R22.5 CONTINENTAL | C73: =IF(A73="","",'DATA PENDIENTES'!L150) -> 77101031 | D73: =IF(A73="","",'DATA PENDIENTES'!J150) | E73: =IF(A73="","",'DATA PENDIENTES'!D150) -> 24 | F73: =IF(A73="","",'DATA PENDIENTES'!E150) -> UND | G73: =IF(A73="","",'DATA PENDIENTES'!F150) -> 22 | H73: =IF(A73="","",'DATA PENDIENTES'!G150) -> 2 | I73: =IF(A73="","",'DATA PENDIENTES'!H150) -> 1561667 | J73: =IF(A73="","",IFERROR(H73*F73,0)) -> 0 | K73: =IF(A73="","",'DATA PENDIENTES'!I150) -> LLANTAS REPUESTOS Y SERVICIO SAS | L73: =IF(A73="","",'DATA PENDIENTES'!K150) -> CRISTHIAN BENITEZ | M73: =IF(A73="","",'DATA PENDIENTES'!M150) -> 46472 | N73: =IF(A73="","",'DATA PENDIENTES'!N150) -> 46069 | O73: =IF(A73="","",IFERROR(MAX(TODAY()-N73,0),0)) -> 50 | P73: =IF(A73="","",IF(H73=0,"COMPLETO",IF(H73<=E73*0.1,"CASI COMPLETO","PENDIENTE"))) -> CASI COMPLETO | Q73: =IF(A73="","",IFERROR(G73/E73,0)) -> 0.91666667 | R73: =IF(A73="","",IF(O73>30,"CRITICO",IF(O73>7,"ALERTA","OK"))) -> CRITICO | S73: =IF(A73="","",IF(O73>30,"1-CRITICO",IF(O73>7,"2-URGENTE","3-NORMAL"))) -> 1-CRITICO | T73: =IF(A73="","",'DATA PENDIENTES'!O150) -> 7121202
A74: =IF('DATA PENDIENTES'!B101="","",'DATA PENDIENTES'!B101) -> SU115857 | B74: =IF(A74="","",'DATA PENDIENTES'!C101) -> AMARRE PLASTICO DE 30 CM | C74: =IF(A74="","",'DATA PENDIENTES'!L101) -> 80110008 | D74: =IF(A74="","",'DATA PENDIENTES'!J101) -> 1912 | E74: =IF(A74="","",'DATA PENDIENTES'!D101) -> 2000 | F74: =IF(A74="","",'DATA PENDIENTES'!E101) -> UND | G74: =IF(A74="","",'DATA PENDIENTES'!F101) -> 0 | H74: =IF(A74="","",'DATA PENDIENTES'!G101) -> 2000 | I74: =IF(A74="","",'DATA PENDIENTES'!H101) -> 93 | J74: =IF(A74="","",IFERROR(H74*F74,0)) -> 0 | K74: =IF(A74="","",'DATA PENDIENTES'!I101) -> SUMILOGISTICA S.A.S. | L74: =IF(A74="","",'DATA PENDIENTES'!K101) -> CRISTHIAN BENITEZ | M74: =IF(A74="","",'DATA PENDIENTES'!M101) -> 46119 | N74: =IF(A74="","",'DATA PENDIENTES'!N101) -> 46113 | O74: =IF(A74="","",IFERROR(MAX(TODAY()-N74,0),0)) -> 6 | P74: =IF(A74="","",IF(H74=0,"COMPLETO",IF(H74<=E74*0.1,"CASI COMPLETO","PENDIENTE"))) -> PENDIENTE | Q74: =IF(A74="","",IFERROR(G74/E74,0)) -> 0 | R74: =IF(A74="","",IF(O74>30,"CRITICO",IF(O74>7,"ALERTA","OK"))) -> OK | S74: =IF(A74="","",IF(O74>30,"1-CRITICO",IF(O74>7,"2-URGENTE","3-NORMAL"))) -> 3-NORMAL | T74: =IF(A74="","",'DATA PENDIENTES'!O101) -> 35340
A75: =IF('DATA PENDIENTES'!B99="","",'DATA PENDIENTES'!B99) -> SU115857 | B75: =IF(A75="","",'DATA PENDIENTES'!C99) -> AMARRE PLASTICO DE 55 CM | C75: =IF(A75="","",'DATA PENDIENTES'!L99) -> 80110009 | D75: =IF(A75="","",'DATA PENDIENTES'!J99) -> 1908 | E75: =IF(A75="","",'DATA PENDIENTES'!D99) -> 2000 | F75: =IF(A75="","",'DATA PENDIENTES'!E99) -> UND | G75: =IF(A75="","",'DATA PENDIENTES'!F99) -> 0 | H75: =IF(A75="","",'DATA PENDIENTES'!G99) -> 2000 | I75: =IF(A75="","",'DATA PENDIENTES'!H99) -> 347 | J75: =IF(A75="","",IFERROR(H75*F75,0)) -> 0 | K75: =IF(A75="","",'DATA PENDIENTES'!I99) -> SUMILOGISTICA S.A.S. | L75: =IF(A75="","",'DATA PENDIENTES'!K99) -> CRISTHIAN BENITEZ | M75: =IF(A75="","",'DATA PENDIENTES'!M99) -> 46119 | N75: =IF(A75="","",'DATA PENDIENTES'!N99) -> 46113 | O75: =IF(A75="","",IFERROR(MAX(TODAY()-N75,0),0)) -> 6 | P75: =IF(A75="","",IF(H75=0,"COMPLETO",IF(H75<=E75*0.1,"CASI COMPLETO","PENDIENTE"))) -> PENDIENTE | Q75: =IF(A75="","",IFERROR(G75/E75,0)) -> 0 | R75: =IF(A75="","",IF(O75>30,"CRITICO",IF(O75>7,"ALERTA","OK"))) -> OK | S75: =IF(A75="","",IF(O75>30,"1-CRITICO",IF(O75>7,"2-URGENTE","3-NORMAL"))) -> 3-NORMAL | T75: =IF(A75="","",'DATA PENDIENTES'!O99) -> 131860
A76: =IF('DATA PENDIENTES'!B73="","",'DATA PENDIENTES'!B73) -> SU115136 | B76: =IF(A76="","",'DATA PENDIENTES'!C73) -> ARANDELA PLANA 3/16" ZINCADA | C76: =IF(A76="","",'DATA PENDIENTES'!L73) -> 80110010 | D76: =IF(A76="","",'DATA PENDIENTES'!J73) -> 734 | E76: =IF(A76="","",'DATA PENDIENTES'!D73) -> 1200 | F76: =IF(A76="","",'DATA PENDIENTES'!E73) -> UND | G76: =IF(A76="","",'DATA PENDIENTES'!F73) -> 600 | H76: =IF(A76="","",'DATA PENDIENTES'!G73) -> 600 | I76: =IF(A76="","",'DATA PENDIENTES'!H73) -> 23 | J76: =IF(A76="","",IFERROR(H76*F76,0)) -> 0 | K76: =IF(A76="","",'DATA PENDIENTES'!I73) -> SUMILOGISTICA S.A.S. | L76: =IF(A76="","",'DATA PENDIENTES'!K73) -> CRISTHIAN BENITEZ | M76: =IF(A76="","",'DATA PENDIENTES'!M73) -> 46142 | N76: =IF(A76="","",'DATA PENDIENTES'!N73) -> 46142 | O76: =IF(A76="","",IFERROR(MAX(TODAY()-N76,0),0)) -> 0 | P76: =IF(A76="","",IF(H76=0,"COMPLETO",IF(H76<=E76*0.1,"CASI COMPLETO","PENDIENTE"))) -> PENDIENTE | Q76: =IF(A76="","",IFERROR(G76/E76,0)) -> 0.5 | R76: =IF(A76="","",IF(O76>30,"CRITICO",IF(O76>7,"ALERTA","OK"))) -> OK | S76: =IF(A76="","",IF(O76>30,"1-CRITICO",IF(O76>7,"2-URGENTE","3-NORMAL"))) -> 3-NORMAL | T76: =IF(A76="","",'DATA PENDIENTES'!O73) -> 5244
A77: =IF('DATA PENDIENTES'!B103="","",'DATA PENDIENTES'!B103) -> SU115857 | B77: =IF(A77="","",'DATA PENDIENTES'!C103) -> BROCA DE 1/8" H.S.S | C77: =IF(A77="","",'DATA PENDIENTES'!L103) -> 80110016 | D77: =IF(A77="","",'DATA PENDIENTES'!J103) -> 510 | E77: =IF(A77="","",'DATA PENDIENTES'!D103) -> 30 | F77: =IF(A77="","",'DATA PENDIENTES'!E103) -> UND | G77: =IF(A77="","",'DATA PENDIENTES'!F103) -> 0 | H77: =IF(A77="","",'DATA PENDIENTES'!G103) -> 30 | I77: =IF(A77="","",'DATA PENDIENTES'!H103) -> 2100 | J77: =IF(A77="","",IFERROR(H77*F77,0)) -> 0 | K77: =IF(A77="","",'DATA PENDIENTES'!I103) -> SUMILOGISTICA S.A.S. | L77: =IF(A77="","",'DATA PENDIENTES'!K103) -> CRISTHIAN BENITEZ | M77: =IF(A77="","",'DATA PENDIENTES'!M103) -> 46119 | N77: =IF(A77="","",'DATA PENDIENTES'!N103) -> 46113 | O77: =IF(A77="","",IFERROR(MAX(TODAY()-N77,0),0)) -> 6 | P77: =IF(A77="","",IF(H77=0,"COMPLETO",IF(H77<=E77*0.1,"CASI COMPLETO","PENDIENTE"))) -> PENDIENTE | Q77: =IF(A77="","",IFERROR(G77/E77,0)) -> 0 | R77: =IF(A77="","",IF(O77>30,"CRITICO",IF(O77>7,"ALERTA","OK"))) -> OK | S77: =IF(A77="","",IF(O77>30,"1-CRITICO",IF(O77>7,"2-URGENTE","3-NORMAL"))) -> 3-NORMAL | T77: =IF(A77="","",'DATA PENDIENTES'!O103) -> 11970
A78: =IF('DATA PENDIENTES'!B104="","",'DATA PENDIENTES'!B104) -> SU115857 | B78: =IF(A78="","",'DATA PENDIENTES'!C104) -> BROCA DE 9/64" H.S.S | C78: =IF(A78="","",'DATA PENDIENTES'!L104) -> 80110020 | D78: =IF(A78="","",'DATA PENDIENTES'!J104) -> 321 | E78: =IF(A78="","",'DATA PENDIENTES'!D104) -> 100 | F78: =IF(A78="","",'DATA PENDIENTES'!E104) -> UND | G78: =IF(A78="","",'DATA PENDIENTES'!F104) -> 0 | H78: =IF(A78="","",'DATA PENDIENTES'!G104) -> 100 | I78: =IF(A78="","",'DATA PENDIENTES'!H104) -> 2888 | J78: =IF(A78="","",IFERROR(H78*F78,0)) -> 0 | K78: =IF(A78="","",'DATA PENDIENTES'!I104) -> SUMILOGISTICA S.A.S. | L78: =IF(A78="","",'DATA PENDIENTES'!K104) -> CRISTHIAN BENITEZ | M78: =IF(A78="","",'DATA PENDIENTES'!M104) -> 46119 | N78: =IF(A78="","",'DATA PENDIENTES'!N104) -> 46113 | O78: =IF(A78="","",IFERROR(MAX(TODAY()-N78,0),0)) -> 6 | P78: =IF(A78="","",IF(H78=0,"COMPLETO",IF(H78<=E78*0.1,"CASI COMPLETO","PENDIENTE"))) -> PENDIENTE | Q78: =IF(A78="","",IFERROR(G78/E78,0)) -> 0 | R78: =IF(A78="","",IF(O78>30,"CRITICO",IF(O78>7,"ALERTA","OK"))) -> OK | S78: =IF(A78="","",IF(O78>30,"1-CRITICO",IF(O78>7,"2-URGENTE","3-NORMAL"))) -> 3-NORMAL | T78: =IF(A78="","",'DATA PENDIENTES'!O104) -> 54872
A79: =IF('DATA PENDIENTES'!B155="","",'DATA PENDIENTES'!B155) -> SU115870 | B79: =IF(A79="","",'DATA PENDIENTES'!C155) -> CALCOMANIA SALIDA DE EMERGENCIA | C79: =IF(A79="","",'DATA PENDIENTES'!L155) -> 80110021 | D79: =IF(A79="","",'DATA PENDIENTES'!J155) -> CA1044 | E79: =IF(A79="","",'DATA PENDIENTES'!D155) -> 10 | F79: =IF(A79="","",'DATA PENDIENTES'!E155) -> UND | G79: =IF(A79="","",'DATA PENDIENTES'!F155) -> 0 | H79: =IF(A79="","",'DATA PENDIENTES'!G155) -> 10 | I79: =IF(A79="","",'DATA PENDIENTES'!H155) -> 1800 | J79: =IF(A79="","",IFERROR(H79*F79,0)) -> 0 | K79: =IF(A79="","",'DATA PENDIENTES'!I155) -> INDUSTRIAS GRAFICAS Y TERMOPLASTICAS SAS | L79: =IF(A79="","",'DATA PENDIENTES'!K155) -> CRISTHIAN BENITEZ | M79: =IF(A79="","",'DATA PENDIENTES'!M155) -> 46116 | N79: =IF(A79="","",'DATA PENDIENTES'!N155) -> 46113 | O79: =IF(A79="","",IFERROR(MAX(TODAY()-N79,0),0)) -> 6 | P79: =IF(A79="","",IF(H79=0,"COMPLETO",IF(H79<=E79*0.1,"CASI COMPLETO","PENDIENTE"))) -> PENDIENTE | Q79: =IF(A79="","",IFERROR(G79/E79,0)) -> 0 | R79: =IF(A79="","",IF(O79>30,"CRITICO",IF(O79>7,"ALERTA","OK"))) -> OK | S79: =IF(A79="","",IF(O79>30,"1-CRITICO",IF(O79>7,"2-URGENTE","3-NORMAL"))) -> 3-NORMAL | T79: =IF(A79="","",'DATA PENDIENTES'!O155) -> 3420
A80: =IF('DATA PENDIENTES'!B74="","",'DATA PENDIENTES'!B74) -> SU115136 | B80: =IF(A80="","",'DATA PENDIENTES'!C74) -> CINTA AISLANTE NEGRA | C80: =IF(A80="","",'DATA PENDIENTES'!L74) -> 80110025 | D80: =IF(A80="","",'DATA PENDIENTES'!J74) -> 325 | E80: =IF(A80="","",'DATA PENDIENTES'!D74) -> 80 | F80: =IF(A80="","",'DATA PENDIENTES'!E74) -> RLL | G80: =IF(A80="","",'DATA PENDIENTES'!F74) -> 40 | H80: =IF(A80="","",'DATA PENDIENTES'!G74) -> 40 | I80: =IF(A80="","",'DATA PENDIENTES'!H74) -> 5292 | J80: =IF(A80="","",IFERROR(H80*F80,0)) -> 0 | K80: =IF(A80="","",'DATA PENDIENTES'!I74) -> SUMILOGISTICA S.A.S. | L80: =IF(A80="","",'DATA PENDIENTES'!K74) -> CRISTHIAN BENITEZ | M80: =IF(A80="","",'DATA PENDIENTES'!M74) -> 46142 | N80: =IF(A80="","",'DATA PENDIENTES'!N74) -> 46142 | O80: =IF(A80="","",IFERROR(MAX(TODAY()-N80,0),0)) -> 0 | P80: =IF(A80="","",IF(H80=0,"COMPLETO",IF(H80<=E80*0.1,"CASI COMPLETO","PENDIENTE"))) -> PENDIENTE | Q80: =IF(A80="","",IFERROR(G80/E80,0)) -> 0.5 | R80: =IF(A80="","",IF(O80>30,"CRITICO",IF(O80>7,"ALERTA","OK"))) -> OK | S80: =IF(A80="","",IF(O80>30,"1-CRITICO",IF(O80>7,"2-URGENTE","3-NORMAL"))) -> 3-NORMAL | T80: =IF(A80="","",'DATA PENDIENTES'!O74) -> 80438.4
A81: =IF('DATA PENDIENTES'!B75="","",'DATA PENDIENTES'!B75) -> SU115136 | B81: =IF(A81="","",'DATA PENDIENTES'!C75) -> CINTA INSONORIZANTE DE 25 MM | C81: =IF(A81="","",'DATA PENDIENTES'!L75) -> 80110028 | D81: =IF(A81="","",'DATA PENDIENTES'!J75) -> 2462 | E81: =IF(A81="","",'DATA PENDIENTES'!D75) -> 400 | F81: =IF(A81="","",'DATA PENDIENTES'!E75) -> M | G81: =IF(A81="","",'DATA PENDIENTES'!F75) -> 100 | H81: =IF(A81="","",'DATA PENDIENTES'!G75) -> 300 | I81: =IF(A81="","",'DATA PENDIENTES'!H75) -> 4692 | J81: =IF(A81="","",IFERROR(H81*F81,0)) -> 0 | K81: =IF(A81="","",'DATA PENDIENTES'!I75) -> SUMILOGISTICA S.A.S. | L81: =IF(A81="","",'DATA PENDIENTES'!K75) -> CRISTHIAN BENITEZ | M81: =IF(A81="","",'DATA PENDIENTES'!M75) -> 46142 | N81: =IF(A81="","",'DATA PENDIENTES'!N75) -> 46142 | O81: =IF(A81="","",IFERROR(MAX(TODAY()-N81,0),0)) -> 0 | P81: =IF(A81="","",IF(H81=0,"COMPLETO",IF(H81<=E81*0.1,"CASI COMPLETO","PENDIENTE"))) -> PENDIENTE | Q81: =IF(A81="","",IFERROR(G81/E81,0)) -> 0.25 | R81: =IF(A81="","",IF(O81>30,"CRITICO",IF(O81>7,"ALERTA","OK"))) -> OK | S81: =IF(A81="","",IF(O81>30,"1-CRITICO",IF(O81>7,"2-URGENTE","3-NORMAL"))) -> 3-NORMAL | T81: =IF(A81="","",'DATA PENDIENTES'!O75) -> 356592
A82: =IF('DATA PENDIENTES'!B248="","",'DATA PENDIENTES'!B248) -> SU115858 | B82: =IF(A82="","",'DATA PENDIENTES'!C248) -> ESPEJO RETROVISOR EXTERNO DERECHO | C82: =IF(A82="","",'DATA PENDIENTES'!L248) -> 80110042 | D82: =IF(A82="","",'DATA PENDIENTES'!J248) -> 11289820 | E82: =IF(A82="","",'DATA PENDIENTES'!D248) -> 15 | F82: =IF(A82="","",'DATA PENDIENTES'!E248) -> UND | G82: =IF(A82="","",'DATA PENDIENTES'!F248) -> 0 | H82: =IF(A82="","",'DATA PENDIENTES'!G248) -> 15 | I82: =IF(A82="","",'DATA PENDIENTES'!H248) -> 47361 | J82: =IF(A82="","",IFERROR(H82*F82,0)) -> 0 | K82: =IF(A82="","",'DATA PENDIENTES'!I248) -> COMERCIALIZADORA DE AUTOPARTES E INDUSTRIAL UNIVERSAL SAS | L82: =IF(A82="","",'DATA PENDIENTES'!K248) -> CRISTHIAN BENITEZ | M82: =IF(A82="","",'DATA PENDIENTES'!M248) -> 46134 | N82: =IF(A82="","",'DATA PENDIENTES'!N248) -> 46113 | O82: =IF(A82="","",IFERROR(MAX(TODAY()-N82,0),0)) -> 6 | P82: =IF(A82="","",IF(H82=0,"COMPLETO",IF(H82<=E82*0.1,"CASI COMPLETO","PENDIENTE"))) -> PENDIENTE | Q82: =IF(A82="","",IFERROR(G82/E82,0)) -> 0 | R82: =IF(A82="","",IF(O82>30,"CRITICO",IF(O82>7,"ALERTA","OK"))) -> OK | S82: =IF(A82="","",IF(O82>30,"1-CRITICO",IF(O82>7,"2-URGENTE","3-NORMAL"))) -> 3-NORMAL | T82: =IF(A82="","",'DATA PENDIENTES'!O248) -> 134978.9
A83: =IF('DATA PENDIENTES'!B70="","",'DATA PENDIENTES'!B70) -> SU115070 | B83: =IF(A83="","",'DATA PENDIENTES'!C70) -> PUNTAS P3 | C83: =IF(A83="","",'DATA PENDIENTES'!L70) -> 80110080 | D83: =IF(A83="","",'DATA PENDIENTES'!J70) -> 875 | E83: =IF(A83="","",'DATA PENDIENTES'!D70) -> 50 | F83: =IF(A83="","",'DATA PENDIENTES'!E70) -> UND | G83: =IF(A83="","",'DATA PENDIENTES'!F70) -> 34 | H83: =IF(A83="","",'DATA PENDIENTES'!G70) -> 16 | I83: =IF(A83="","",'DATA PENDIENTES'!H70) -> 4347 | J83: =IF(A83="","",IFERROR(H83*F83,0)) -> 0 | K83: =IF(A83="","",'DATA PENDIENTES'!I70) -> SUMILOGISTICA S.A.S. | L83: =IF(A83="","",'DATA PENDIENTES'!K70) -> CRISTHIAN BENITEZ | M83: =IF(A83="","",'DATA PENDIENTES'!M70) -> 46021 | N83: =IF(A83="","",'DATA PENDIENTES'!N70) -> 46021 | O83: =IF(A83="","",IFERROR(MAX(TODAY()-N83,0),0)) -> 98 | P83: =IF(A83="","",IF(H83=0,"COMPLETO",IF(H83<=E83*0.1,"CASI COMPLETO","PENDIENTE"))) -> PENDIENTE | Q83: =IF(A83="","",IFERROR(G83/E83,0)) -> 0.68 | R83: =IF(A83="","",IF(O83>30,"CRITICO",IF(O83>7,"ALERTA","OK"))) -> CRITICO | S83: =IF(A83="","",IF(O83>30,"1-CRITICO",IF(O83>7,"2-URGENTE","3-NORMAL"))) -> 1-CRITICO | T83: =IF(A83="","",'DATA PENDIENTES'!O70) -> 41296.5
